Workbook
Name UPDATE: 'Data Sheet'!$E$1

Sheet Sheet3
A1: VALUE
A2: 6.8411153e+09 | C2: Top Shareholder | D2: Shares Holding | E2: Share Price (₹)
A3: 7.3777692e+09 | C3: Tata Sons Pvt. Ltd. | D3: 2595499419 | E3: Current TCS Price | M3: Top Shareholder | N3: Share % | O3: Shares Holding | P3: Share Price (₹) | Q3: Market Value (₹ Cr.)
A4: 1.0269563e+10 | C4: LIC of India | D4: 199553451 | E4: Current TCS Price | N4: 0.7174 | P4: Current TCS Price | Q4: {=Shares * Share Price} -> #NAME?
A5: 1.2055719e+10 | C5: SBI Mutual Fund | D5: 45239395 | E5: Current TCS Price | N5: 0.0552 | P5: Current TCS Price | Q5: {=Shares * Share Price} -> #NAME?
A6: 1.7571237e+10 | C6: ICICI Prudential MF | D6: 38172688 | E6: Current TCS Price | N6: 0.0125 | P6: Current TCS Price | Q6: {=Shares * Share Price} -> #NAME?
A7: 19711786830 | C7: NPS Trust | D7: 28525843 | E7: Current TCS Price | N7: 0.0106 | P7: Current TCS Price | Q7: {=Shares * Share Price} -> #NAME?
A8: 9.2162958e+09 | N8: 0.0079 | P8: Current TCS Price | Q8: {=Shares * Share Price} -> #NAME?
A9: 7.2136561e+09
A10: 5.5852587e+09
A11: 3.5378399e+09
A12: 5.3120746e+09
A13: 4.9716236e+09
A14: 1.2666031e+10
A15: 1.1501045e+10
A16: 1.1854245e+10
A17: 2.100566e+10
A18: 2.6782359e+10
A19: 1.4020751e+10
A20: 7.748164e+09
... A23: 5.2936196e+09

Sheet Profit & Loss
A1: ='Data Sheet'!B1 -> TATA CONSULTANCY SERVICES LTD | H1: =UPDATE | M1: SCREENER.IN
A3: Narration | B3: ='Data Sheet'!B16 -> 42825 | C3: ='Data Sheet'!C16 -> 43190 | D3: ='Data Sheet'!D16 -> 43555 | E3: ='Data Sheet'!E16 -> 43921 | F3: ='Data Sheet'!F16 -> 44286 | G3: ='Data Sheet'!G16 -> 44651 | H3: ='Data Sheet'!H16 -> 45016 | I3: ='Data Sheet'!I16 -> 45382 | ... K3: ='Data Sheet'!K16 -> 46112 | L3: Trailing | M3: Best Case | N3: Worst Case
A4: Sales | B4: ='Data Sheet'!B17 -> 117966 | C4: ='Data Sheet'!C17 -> 123104 | D4: ='Data Sheet'!D17 -> 146463 | E4: ='Data Sheet'!E17 -> 156949 | F4: ='Data Sheet'!F17 -> 164177 | G4: ='Data Sheet'!G17 -> 191754 | H4: ='Data Sheet'!H17 -> 225458 | I4: ='Data Sheet'!I17 -> 240893 | ... K4: ='Data Sheet'!K17 -> 267021 | L4: =SUM(Quarters!H4:K4) -> 275859 | M4: =$K4+M23*K4 -> 282513.15 | N4: =$K4+N23*L4 -> 279658.76
A5: Expenses | B5: =SUM('Data Sheet'!B18,'Data Sheet'!B20:B24, -1*'Data Sheet'!B19) -> 85655 | C5: =SUM('Data Sheet'!C18,'Data Sheet'!C20:C24, -1*'Data Sheet'!C19) -> 90588 | D5: =SUM('Data Sheet'!D18,'Data Sheet'!D20:D24, -1*'Data Sheet'!D19) -> 106957 | E5: =SUM('Data Sheet'!E18,'Data Sheet'!E20:E24, -1*'Data Sheet'!E19) -> 114840 | F5: =SUM('Data Sheet'!F18,'Data Sheet'!F20:F24, -1*'Data Sheet'!F19) -> 117631 | G5: =SUM('Data Sheet'!G18,'Data Sheet'!G20:G24, -1*'Data Sheet'!G19) -> 138697 | H5: =SUM('Data Sheet'!H18,'Data Sheet'!H20:H24, -1*'Data Sheet'!H19) -> 166199 | I5: =SUM('Data Sheet'!I18,'Data Sheet'!I20:I24, -1*'Data Sheet'!I19) -> 176597 | ... K5: =SUM('Data Sheet'!K18,'Data Sheet'!K20:K24, -1*'Data Sheet'!K19) -> 194623 | L5: =SUM(Quarters!H5:K5) -> 201780 | M5: =M4-M6 -> 206647.25 | N5: =N4-N6 -> 204873.92
A6: Operating Profit | B6: =B4-B5 -> 32311 | C6: =C4-C5 -> 32516 | D6: =D4-D5 -> 39506 | E6: =E4-E5 -> 42109 | F6: =F4-F5 -> 46546 | G6: =G4-G5 -> 53057 | H6: =H4-H5 -> 59259 | I6: =I4-I5 -> 64296 | ... K6: =K4-K5 -> 72398 | L6: =SUM(Quarters!H6:K6) -> 74079 | M6: =M4*M24 -> 75865.902 | N6: =N4*N24 -> 74784.84
A7: Other Income | B7: ='Data Sheet'!B25 -> 4221 | C7: ='Data Sheet'!C25 -> 3642 | D7: ='Data Sheet'!D25 -> 4311 | E7: ='Data Sheet'!E25 -> 4592 | F7: ='Data Sheet'!F25 -> 1916 | G7: ='Data Sheet'!G25 -> 4018 | H7: ='Data Sheet'!H25 -> 3449 | I7: ='Data Sheet'!I25 -> 3464 | ... K7: ='Data Sheet'!K25 -> -124 | L7: =SUM(Quarters!H7:K7) -> -884 | M7: 0 | N7: 0
A8: Depreciation | B8: ='Data Sheet'!B26 -> 1987 | C8: ='Data Sheet'!C26 -> 2014 | D8: ='Data Sheet'!D26 -> 2056 | E8: ='Data Sheet'!E26 -> 3529 | F8: ='Data Sheet'!F26 -> 4065 | G8: ='Data Sheet'!G26 -> 4604 | H8: ='Data Sheet'!H26 -> 5022 | I8: ='Data Sheet'!I26 -> 4985 | ... K8: ='Data Sheet'!K26 -> 5560 | L8: =SUM(Quarters!H8:K8) -> 5438 | M8: =+$L8 -> 5438 | N8: =+$L8 -> 5438
A9: Interest | B9: ='Data Sheet'!B27 -> 32 | C9: ='Data Sheet'!C27 -> 52 | D9: ='Data Sheet'!D27 -> 198 | E9: ='Data Sheet'!E27 -> 924 | F9: ='Data Sheet'!F27 -> 637 | G9: ='Data Sheet'!G27 -> 784 | H9: ='Data Sheet'!H27 -> 779 | I9: ='Data Sheet'!I27 -> 778 | ... K9: ='Data Sheet'!K27 -> 1227 | L9: =SUM(Quarters!H9:K9) -> 1305 | M9: =+$L9 -> 1305 | N9: =+$L9 -> 1305
A10: Profit before tax | B10: ='Data Sheet'!B28 -> 34513 | C10: ='Data Sheet'!C28 -> 34092 | D10: ='Data Sheet'!D28 -> 41563 | E10: ='Data Sheet'!E28 -> 42248 | F10: ='Data Sheet'!F28 -> 43760 | G10: ='Data Sheet'!G28 -> 51687 | H10: ='Data Sheet'!H28 -> 56907 | I10: ='Data Sheet'!I28 -> 61997 | ... K10: ='Data Sheet'!K28 -> 65487 | L10: =SUM(Quarters!H10:K10) -> 66452 | M10: =M6+M7-SUM(M8:M9) -> 69122.902 | N10: =N6+N7-SUM(N8:N9) -> 68041.84
A11: Tax | B11: ='Data Sheet'!B29 -> 8156 | C11: ='Data Sheet'!C29 -> 8212 | D11: ='Data Sheet'!D29 -> 10001 | E11: ='Data Sheet'!E29 -> 9801 | F11: ='Data Sheet'!F29 -> 11198 | G11: ='Data Sheet'!G29 -> 13238 | H11: ='Data Sheet'!H29 -> 14604 | I11: ='Data Sheet'!I29 -> 15898 | ... K11: ='Data Sheet'!K29 -> 16033 | L11: =SUM(Quarters!H11:K11) -> 16397 | M11: =IF($L10>0,$L11/$L10,0) -> 0.24674953 | N11: =IF($L10>0,$L11/$L10,0) -> 0.24674953
A12: Net profit | B12: ='Data Sheet'!B30 -> 26289 | C12: ='Data Sheet'!C30 -> 25826 | D12: ='Data Sheet'!D30 -> 31472 | E12: ='Data Sheet'!E30 -> 32340 | F12: ='Data Sheet'!F30 -> 32430 | G12: ='Data Sheet'!G30 -> 38327 | H12: ='Data Sheet'!H30 -> 42147 | I12: ='Data Sheet'!I30 -> 45908 | ... K12: ='Data Sheet'!K30 -> 49210 | L12: =SUM(Quarters!H12:K12) -> 49799 | M12: =M10-M11*M10 -> 52066.858 | N12: =N10-N11*N10 -> 51252.548
A13: EPS | B13: =IF('Data Sheet'!B93>0,B12/'Data Sheet'!B93,0) -> 66.708112 | C13: =IF('Data Sheet'!C93>0,C12/'Data Sheet'!C93,0) -> 67.455467 | D13: =IF('Data Sheet'!D93>0,D12/'Data Sheet'!D93,0) -> 83.871655 | E13: =IF('Data Sheet'!E93>0,E12/'Data Sheet'!E93,0) -> 86.184842 | F13: =IF('Data Sheet'!F93>0,F12/'Data Sheet'!F93,0) -> 87.669974 | G13: =IF('Data Sheet'!G93>0,G12/'Data Sheet'!G93,0) -> 104.74434 | H13: =IF('Data Sheet'!H93>0,H12/'Data Sheet'!H93,0) -> 115.18406 | I13: =IF('Data Sheet'!I93>0,I12/'Data Sheet'!I93,0) -> 126.88428 | ... K13: =IF('Data Sheet'!K93>0,K12/'Data Sheet'!K93,0) -> 136.01061 | L13: =IF('Data Sheet'!$B6>0,'Profit & Loss'!L12/'Data Sheet'!$B6,0) -> 137.63901 | M13: =IF('Data Sheet'!$B6>0,'Profit & Loss'!M12/'Data Sheet'!$B6,0) -> 143.90713 | N13: =IF('Data Sheet'!$B6>0,'Profit & Loss'!N12/'Data Sheet'!$B6,0) -> 141.65646
A14: Price to earning | B14: =IF(B15>0,B15/B13,"") -> 18.227168 | C14: =IF(C15>0,C15/C13,"") -> 21.118822 | D14: =IF(D15>0,D15/D13,"") -> 23.865631 | E14: =IF(E15>0,E15/E13,"") -> 21.188181 | F14: =IF(F15>0,F15/F13,"") -> 36.247872 | G14: =IF(G15>0,G15/G13,"") -> 35.705511 | H14: =IF(H15>0,H15/H13,"") -> 27.832844 | I14: =IF(I15>0,I15/I13,"") -> 30.549885 | ... K14: =IF(K15>0,K15/K13,"") -> 17.343499 | L14: =IF(L13>0,L15/L13,0) -> 17.186987 | M14: =M25 -> 22.988221 | N14: =N25 -> 17.186987
A15: Price | B15: ='Data Sheet'!B90 -> 1215.9 | C15: ='Data Sheet'!C90 -> 1424.58 | D15: ='Data Sheet'!D90 -> 2001.65 | E15: ='Data Sheet'!E90 -> 1826.1 | F15: ='Data Sheet'!F90 -> 3177.85 | G15: ='Data Sheet'!G90 -> 3739.95 | H15: ='Data Sheet'!H90 -> 3205.9 | I15: ='Data Sheet'!I90 -> 3876.3 | ... K15: ='Data Sheet'!K90 -> 2358.9 | L15: ='Data Sheet'!B8 -> 2365.6 | M15: =M13*M14 -> 3308.1689 | N15: =N13*N14 -> 2434.6478
A17: RATIOS:
A18: Dividend Payout | B18: =IF('Data Sheet'!B30>0, 'Data Sheet'!B31/'Data Sheet'!B30, 0) -> 0.35220054 | C18: =IF('Data Sheet'!C30>0, 'Data Sheet'!C31/'Data Sheet'!C30, 0) -> 0.36978239 | D18: =IF('Data Sheet'!D30>0, 'Data Sheet'!D31/'Data Sheet'!D30, 0) -> 0.3574606 | E18: =IF('Data Sheet'!E30>0, 'Data Sheet'!E31/'Data Sheet'!E30, 0) -> 0.84647495 | F18: =IF('Data Sheet'!F30>0, 'Data Sheet'!F31/'Data Sheet'!F30, 0) -> 0.43354918 | G18: =IF('Data Sheet'!G30>0, 'Data Sheet'!G31/'Data Sheet'!G30, 0) -> 0.41062436 | H18: =IF('Data Sheet'!H30>0, 'Data Sheet'!H31/'Data Sheet'!H30, 0) -> 0.99864759 | I18: =IF('Data Sheet'!I30>0, 'Data Sheet'!I31/'Data Sheet'!I30, 0) -> 0.57562952 | ... K18: =IF('Data Sheet'!K30>0, 'Data Sheet'!K31/'Data Sheet'!K30, 0) -> 0.80918512
A19: OPM | B19: =IF(B6>0,B6/B4,0) -> 0.27390095 | C19: =IF(C6>0,C6/C4,0) -> 0.26413439 | D19: =IF(D6>0,D6/D4,0) -> 0.26973365 | E19: =IF(E6>0,E6/E4,0) -> 0.26829734 | F19: =IF(F6>0,F6/F4,0) -> 0.28351109 | G19: =IF(G6>0,G6/G4,0) -> 0.27669305 | H19: =IF(H6>0,H6/H4,0) -> 0.26283831 | I19: =IF(I6>0,I6/I4,0) -> 0.26690688 | ... L19: =IF(L6>0,L6/L4,0) -> 0.26853936
G22: TRENDS: | H22: 10 YEARS | I22: 7 YEARS | J22: 5 YEARS | K22: 3 YEARS | L22: RECENT | M22: BEST | N22: WORST
G23: Sales Growth | H23: =IF(B4=0,"",POWER($K4/B4,1/9)-1) -> 0.095017227 | I23: =IF(D4=0,"",POWER($K4/D4,1/7)-1) -> 0.089581302 | J23: =IF(F4=0,"",POWER($K4/F4,1/5)-1) -> 0.10216501 | K23: =IF(H4=0,"",POWER($K4/H4, 1/3)-1) -> 0.058018486 | L23: =IF(ISERROR(MAX(IF(J4=0,"",(K4-J4)/J4),IF(K4=0,"",(L4-K4)/K4))),"",MAX(IF(J4=0,"",(K4-J4)/J4),IF(K4=0,"",(L4-K4)/K4))) -> 0.04581238 | M23: =MAX(K23:L23) -> 0.058018486 | N23: =MIN(H23:L23) -> 0.04581238
G24: OPM | H24: =IF(SUM(B4:$K$4)=0,"",SUMPRODUCT(B19:$K$19,B4:$K$4)/SUM(B4:$K$4)) -> 0.26965358 | I24: =IF(SUM(E4:$K$4)=0,"",SUMPRODUCT(E19:$K$19,E4:$K$4)/SUM(E4:$K$4)) -> 0.26976457 | J24: =IF(SUM(G4:$K$4)=0,"",SUMPRODUCT(G19:$K$19,G4:$K$4)/SUM(G4:$K$4)) -> 0.26804778 | K24: =IF(SUM(I4:$K$4)=0, "", SUMPRODUCT(I19:$K$19,I4:$K$4)/SUM(I4:$K$4)) -> 0.26741462 | L24: =L19 -> 0.26853936 | M24: =MAX(K24:L24) -> 0.26853936 | N24: =MIN(H24:L24) -> 0.26741462
G25: Price to Earning | H25: =IF(ISERROR(AVERAGEIF(B14:$L14,">0")),"",AVERAGEIF(B14:$L14,">0")) -> 25.103538 | I25: =IF(ISERROR(AVERAGEIF(E14:$L14,">0")),"",AVERAGEIF(E14:$L14,">0")) -> 26.615911 | J25: =IF(ISERROR(AVERAGEIF(G14:$L14,">0")),"",AVERAGEIF(G14:$L14,">0")) -> 25.915206 | K25: =IF(ISERROR(AVERAGEIF(I14:$L14,">0")),"",AVERAGEIF(I14:$L14,">0")) -> 22.988221 | L25: =L14 -> 17.186987 | M25: =MAX(K25:L25) -> 22.988221 | N25: =MIN(H25:L25) -> 17.186987
E49: Date | F49: Open | G49: High | H49: Low | I49: Close | J49: Shares Traded | K49: Turnover (₹ Cr) | L49: Adjest | N49: Date | O49: Open | P49: High | Q49: Low | R49: Close | S49: Prev. Close | T49: Change | U49: % Change
E50: 46234 | F50: 24361.45 | G50: 24429.4 | H50: 24299.7 | I50: 24383.6 | J50: 411693361 | K50: 34459.53 | N50: 45931 | O50: 11.065 | P50: 11.255 | Q50: 10.1525 | R50: 10.29 | S50: 11.065 | T50: -0.78 | U50: -7
E51: 46233 | F51: 24249.55 | G51: 24342.95 | H51: 24187.1 | I51: 24317.15 | J51: 400636260 | K51: 33566.22 | N51: 45933 | O51: 10.2875 | P51: 10.6225 | Q51: 9.945 | R51: 10.06 | S51: 10.2875 | T51: -0.23 | U51: -2.21
E52: 46232 | F52: 24176.65 | G52: 24283.55 | H52: 24136.75 | I52: 24250.2 | J52: 424150311 | K52: 34189.33 | N52: 45936 | O52: 10.06 | P52: 10.5375 | Q52: 9.6575 | R52: 10.19 | S52: 10.06 | T52: 0.13 | U52: 1.29
E53: 46231 | F53: 23971.25 | G53: 24041.15 | H53: 23954.6 | I53: 23985.35 | J53: 437827320 | K53: 35846.87 | N53: 45937 | O53: 10.1925 | P53: 10.45 | Q53: 10 | R53: 10.05 | S53: 10.1925 | T53: -0.14 | U53: -1.4
E54: 46230 | F54: 23928.4 | G54: 24011.6 | H54: 23891.55 | I54: 23995.95 | J54: 319367545 | K54: 25340.46 | N54: 45938 | O54: 10.05 | P54: 10.5225 | Q54: 9.6875 | R54: 10.31 | S54: 10.05 | T54: 0.26 | U54: 2.59
E55: 46227 | F55: 23666.35 | G55: 23823.6 | H55: 23606.3 | I55: 23767.45 | J55: 333870912 | K55: 28825.72 | N55: 45939 | O55: 10.3125 | P55: 10.565 | Q55: 9.9975 | R55: 10.12 | S55: 10.3125 | T55: -0.19 | U55: -1.87
E56: 46226 | F56: 23904.8 | G56: 23990.75 | H56: 23807.2 | I56: 23869.6 | J56: 344042832 | K56: 28259.45 | N56: 45940 | O56: 10.12 | P56: 10.3425 | Q56: 9.71 | R56: 10.1 | S56: 10.12 | T56: -0.02 | U56: -0.2
E57: 46225 | F57: 24150.45 | G57: 24166.3 | H57: 23961.4 | I57: 23996.25 | J57: 304745142 | K57: 25211.83 | N57: 45943 | O57: 10.1025 | P57: 11.2575 | Q57: 9.7775 | R57: 11.01 | S57: 10.1025 | T57: 0.91 | U57: 8.98
E58: 46224 | F58: 24216.05 | G58: 24262.2 | H58: 24135.65 | I58: 24187.7 | J58: 315560285 | K58: 28361.57 | N58: 45944 | O58: 11.0075 | P58: 11.6675 | Q58: 10.0125 | R58: 11.16 | S58: 11.0075 | T58: 0.15 | U58: 1.39
E59: 46223 | F59: 24190.05 | G59: 24266.1 | H59: 24135.85 | I59: 24238.5 | J59: 353095939 | K59: 31370.66 | N59: 45945 | O59: 11.155 | P59: 11.155 | Q59: 10.4325 | R59: 10.53 | S59: 11.155 | T59: -0.63 | U59: -5.6
E60: 46220 | F60: 24127.6 | G60: 24367.3 | H60: 24099.05 | I60: 24334.3 | J60: 387772135 | K60: 28825.71 | N60: 45946 | O60: 10.53 | P60: 11.0575 | Q60: 10.3825 | R60: 10.87 | S60: 10.53 | T60: 0.34 | U60: 3.23
E61: 46219 | F61: 24142.1 | G61: 24186.5 | H61: 24050 | I61: 24072.75 | J61: 264271962 | K61: 24244.17 | N61: 45947 | O61: 10.865 | P61: 11.81 | Q61: 9.775 | R61: 11.63 | S61: 10.865 | T61: 0.77 | U61: 7.04
... E171: 46055 | F171: 24796.5 | G171: 25108.1 | H171: 24679.4 | I171: 25088.4 | J171: 449215604 | K171: 34038.26 | N171: 46111 | O171: 26.8025 | P171: 28.9075 | Q171: 26.8025 | R171: 27.89 | S171: 26.8025 | T171: 1.09 | U171: 4.06
E172: 46054 | F172: 25333.75 | G172: 25440.9 | H172: 24571.75 | I172: 24825.45 | J172: 379370206 | K172: 25572.6
E173: 46052 | F173: 25247.55 | G173: 25370.7 | H173: 25213.65 | I173: 25320.65 | J173: 508388604 | K173: 40772.08
E174: 46051 | F174: 25345 | G174: 25458.15 | H174: 25159.8 | I174: 25418.9 | J174: 582389331 | K174: 44306.95
E175: 46050 | F175: 25258.85 | G175: 25372.1 | H175: 25187.65 | I175: 25342.75 | J175: 574903942 | K175: 42364.52
E176: 46049 | F176: 25063.35 | G176: 25246.65 | H176: 24932.55 | I176: 25175.4 | J176: 618696080 | K176: 50989.25
E177: 46045 | F177: 25344.6 | G177: 25347.95 | H177: 25025.3 | I177: 25048.65 | J177: 393944908 | K177: 31844.65
E178: 46044 | F178: 25344.15 | G178: 25435.75 | H178: 25168.5 | I178: 25289.9 | J178: 486395433 | K178: 34583.24
E179: 46043 | F179: 25141 | G179: 25300.95 | H179: 24919.8 | I179: 25157.5 | J179: 395624981 | K179: 30984.61
E180: 46042 | F180: 25580.3 | G180: 25585 | H180: 25171.35 | I180: 25232.5 | J180: 409772324 | K180: 31020.36
E181: 46041 | F181: 25653.1 | G181: 25653.3 | H181: 25494.35 | I181: 25585.5 | J181: 443087953 | K181: 33632.38
E182: 46038 | F182: 25696.05 | G182: 25873.5 | H182: 25662.4 | I182: 25694.35 | J182: 434041776 | K182: 37156.05
E183: 46036 | F183: 25648.55 | G183: 25791.75 | H183: 25603.95 | I183: 25665.6 | J183: 393126596 | K183: 28944.88
... E294: 45873 | F294: 24596.05 | G294: 24736.25 | H294: 24554 | I294: 24722.75 | J294: 259329477 | K294: 20372.68

Sheet Quarters
A1: ='Profit & Loss'!A1 -> TATA CONSULTANCY SERVICES LTD | E1: =UPDATE | J1: SCREENER.IN
A3: Narration | B3: ='Data Sheet'!B41 -> 45382 | C3: ='Data Sheet'!C41 -> 45473 | D3: ='Data Sheet'!D41 -> 45565 | E3: ='Data Sheet'!E41 -> 45657 | F3: ='Data Sheet'!F41 -> 45747 | G3: ='Data Sheet'!G41 -> 45838 | H3: ='Data Sheet'!H41 -> 45930 | I3: ='Data Sheet'!I41 -> 46022 | ... K3: ='Data Sheet'!K41 -> 46203
A4: Sales | B4: ='Data Sheet'!B42 -> 61237 | C4: ='Data Sheet'!C42 -> 62613 | D4: ='Data Sheet'!D42 -> 64259 | E4: ='Data Sheet'!E42 -> 63973 | F4: ='Data Sheet'!F42 -> 64479 | G4: ='Data Sheet'!G42 -> 63437 | H4: ='Data Sheet'!H42 -> 65799 | I4: ='Data Sheet'!I42 -> 67087 | ... K4: ='Data Sheet'!K42 -> 72275
A5: Expenses | B5: ='Data Sheet'!B43 -> 44073 | C5: ='Data Sheet'!C43 -> 45951 | D5: ='Data Sheet'!D43 -> 47528 | E5: ='Data Sheet'!E43 -> 46939 | F5: ='Data Sheet'!F43 -> 47499 | G5: ='Data Sheet'!G43 -> 46562 | H5: ='Data Sheet'!H43 -> 47821 | I5: ='Data Sheet'!I43 -> 48818 | ... K5: ='Data Sheet'!K43 -> 53719
A6: Operating Profit | B6: ='Data Sheet'!B50 -> 17164 | C6: ='Data Sheet'!C50 -> 16662 | D6: ='Data Sheet'!D50 -> 16731 | E6: ='Data Sheet'!E50 -> 17034 | F6: ='Data Sheet'!F50 -> 16980 | G6: ='Data Sheet'!G50 -> 16875 | H6: ='Data Sheet'!H50 -> 17978 | I6: ='Data Sheet'!I50 -> 18269 | ... K6: ='Data Sheet'!K50 -> 18556
A7: Other Income | B7: ='Data Sheet'!B44 -> 1157 | C7: ='Data Sheet'!C44 -> 962 | D7: ='Data Sheet'!D44 -> 729 | E7: ='Data Sheet'!E44 -> 1243 | F7: ='Data Sheet'!F44 -> 1028 | G7: ='Data Sheet'!G44 -> 1660 | H7: ='Data Sheet'!H44 -> -268 | I7: ='Data Sheet'!I44 -> -2273 | ... K7: ='Data Sheet'!K44 -> 900
A8: Depreciation | B8: ='Data Sheet'!B45 -> 1246 | C8: ='Data Sheet'!C45 -> 1220 | D8: ='Data Sheet'!D45 -> 1266 | E8: ='Data Sheet'!E45 -> 1377 | F8: ='Data Sheet'!F45 -> 1379 | G8: ='Data Sheet'!G45 -> 1361 | H8: ='Data Sheet'!H45 -> 1413 | I8: ='Data Sheet'!I45 -> 1380 | ... K8: ='Data Sheet'!K45 -> 1239
A9: Interest | B9: ='Data Sheet'!B46 -> 226 | C9: ='Data Sheet'!C46 -> 173 | D9: ='Data Sheet'!D46 -> 162 | E9: ='Data Sheet'!E46 -> 234 | F9: ='Data Sheet'!F46 -> 227 | G9: ='Data Sheet'!G46 -> 195 | H9: ='Data Sheet'!H46 -> 229 | I9: ='Data Sheet'!I46 -> 538 | ... K9: ='Data Sheet'!K46 -> 273
A10: Profit before tax | B10: ='Data Sheet'!B47 -> 16849 | C10: ='Data Sheet'!C47 -> 16231 | D10: ='Data Sheet'!D47 -> 16032 | E10: ='Data Sheet'!E47 -> 16666 | F10: ='Data Sheet'!F47 -> 16402 | G10: ='Data Sheet'!G47 -> 16979 | H10: ='Data Sheet'!H47 -> 16068 | I10: ='Data Sheet'!I47 -> 14078 | ... K10: ='Data Sheet'!K47 -> 17944
A11: Tax | B11: ='Data Sheet'!B48 -> 4347 | C11: ='Data Sheet'!C48 -> 4126 | D11: ='Data Sheet'!D48 -> 4077 | E11: ='Data Sheet'!E48 -> 4222 | F11: ='Data Sheet'!F48 -> 4109 | G11: ='Data Sheet'!G48 -> 4160 | H11: ='Data Sheet'!H48 -> 3937 | I11: ='Data Sheet'!I48 -> 3358 | ... K11: ='Data Sheet'!K48 -> 4524
A12: Net profit | B12: ='Data Sheet'!B49 -> 12434 | C12: ='Data Sheet'!C49 -> 12040 | D12: ='Data Sheet'!D49 -> 11909 | E12: ='Data Sheet'!E49 -> 12380 | F12: ='Data Sheet'!F49 -> 12224 | G12: ='Data Sheet'!G49 -> 12760 | H12: ='Data Sheet'!H49 -> 12075 | I12: ='Data Sheet'!I49 -> 10657 | ... K12: ='Data Sheet'!K49 -> 13349
A14: OPM | B14: =IF(B4>0,B6/B4,"") -> 0.28028806 | C14: =IF(C4>0,C6/C4,"") -> 0.26611087 | D14: =IF(D4>0,D6/D4,"") -> 0.2603682 | E14: =IF(E4>0,E6/E4,"") -> 0.26626858 | F14: =IF(F4>0,F6/F4,"") -> 0.26334155 | G14: =IF(G4>0,G6/G4,"") -> 0.26601195 | H14: =IF(H4>0,H6/H4,"") -> 0.27322604 | I14: =IF(I4>0,I6/I4,"") -> 0.27231803 | ... K14: =IF(K4>0,K6/K4,"") -> 0.25674161

Sheet Balance Sheet
A1: ='Profit & Loss'!A1 -> TATA CONSULTANCY SERVICES LTD | E1: =UPDATE | J1: SCREENER.IN
A3: Narration | B3: ='Data Sheet'!B56 -> 42825 | C3: ='Data Sheet'!C56 -> 43190 | D3: ='Data Sheet'!D56 -> 43555 | E3: ='Data Sheet'!E56 -> 43921 | F3: ='Data Sheet'!F56 -> 44286 | G3: ='Data Sheet'!G56 -> 44651 | H3: ='Data Sheet'!H56 -> 45016 | I3: ='Data Sheet'!I56 -> 45382 | ... K3: ='Data Sheet'!K56 -> 46112
A4: Equity Share Capital | B4: ='Data Sheet'!B57 -> 197 | C4: ='Data Sheet'!C57 -> 191 | D4: ='Data Sheet'!D57 -> 375 | E4: ='Data Sheet'!E57 -> 375 | F4: ='Data Sheet'!F57 -> 370 | G4: ='Data Sheet'!G57 -> 366 | H4: ='Data Sheet'!H57 -> 366 | I4: ='Data Sheet'!I57 -> 362 | ... K4: ='Data Sheet'!K57 -> 362
A5: Reserves | B5: ='Data Sheet'!B58 -> 86017 | C5: ='Data Sheet'!C58 -> 84937 | D5: ='Data Sheet'!D58 -> 89071 | E5: ='Data Sheet'!E58 -> 83751 | F5: ='Data Sheet'!F58 -> 86063 | G5: ='Data Sheet'!G58 -> 88773 | H5: ='Data Sheet'!H58 -> 90058 | I5: ='Data Sheet'!I58 -> 90127 | ... K5: ='Data Sheet'!K58 -> 106878
A6: Borrowings | B6: ='Data Sheet'!B59 -> 289 | C6: ='Data Sheet'!C59 -> 247 | D6: ='Data Sheet'!D59 -> 62 | E6: ='Data Sheet'!E59 -> 8174 | F6: ='Data Sheet'!F59 -> 7795 | G6: ='Data Sheet'!G59 -> 7818 | H6: ='Data Sheet'!H59 -> 7688 | I6: ='Data Sheet'!I59 -> 8021 | ... K6: ='Data Sheet'!K59 -> 11283
A7: Other Liabilities | B7: ='Data Sheet'!B60 -> 15830 | C7: ='Data Sheet'!C60 -> 19751 | D7: ='Data Sheet'!D60 -> 24393 | E7: ='Data Sheet'!E60 -> 27827 | F7: ='Data Sheet'!F60 -> 35764 | G7: ='Data Sheet'!G60 -> 43967 | H7: ='Data Sheet'!H60 -> 44747 | I7: ='Data Sheet'!I60 -> 46962 | ... K7: ='Data Sheet'!K60 -> 62644
A8: Total | B8: ='Data Sheet'!B61 -> 102333 | C8: ='Data Sheet'!C61 -> 105126 | D8: ='Data Sheet'!D61 -> 113901 | E8: ='Data Sheet'!E61 -> 120127 | F8: ='Data Sheet'!F61 -> 129992 | G8: ='Data Sheet'!G61 -> 140924 | H8: ='Data Sheet'!H61 -> 142859 | I8: ='Data Sheet'!I61 -> 145472 | ... K8: ='Data Sheet'!K61 -> 181167
A10: Net Block | B10: ='Data Sheet'!B62 -> 11701 | C10: ='Data Sheet'!C62 -> 11973 | D10: ='Data Sheet'!D62 -> 12290 | E10: ='Data Sheet'!E62 -> 20928 | F10: ='Data Sheet'!F62 -> 21021 | G10: ='Data Sheet'!G62 -> 21298 | H10: ='Data Sheet'!H62 -> 20515 | I10: ='Data Sheet'!I62 -> 19604 | ... K10: ='Data Sheet'!K62 -> 31343
A11: Capital Work in Progress | B11: ='Data Sheet'!B63 -> 1541 | C11: ='Data Sheet'!C63 -> 1278 | D11: ='Data Sheet'!D63 -> 963 | E11: ='Data Sheet'!E63 -> 906 | F11: ='Data Sheet'!F63 -> 926 | G11: ='Data Sheet'!G63 -> 1205 | H11: ='Data Sheet'!H63 -> 1234 | I11: ='Data Sheet'!I63 -> 1564 | ... K11: ='Data Sheet'!K63 -> 2665
A12: Investments | B12: ='Data Sheet'!B64 -> 41980 | C12: ='Data Sheet'!C64 -> 36008 | D12: ='Data Sheet'!D64 -> 29330 | E12: ='Data Sheet'!E64 -> 26356 | F12: ='Data Sheet'!F64 -> 29373 | G12: ='Data Sheet'!G64 -> 30485 | H12: ='Data Sheet'!H64 -> 37163 | I12: ='Data Sheet'!I64 -> 31762 | ... K12: ='Data Sheet'!K64 -> 33988
A13: Other Assets | B13: ='Data Sheet'!B65 -> 47111 | C13: ='Data Sheet'!C65 -> 55867 | D13: ='Data Sheet'!D65 -> 71318 | E13: ='Data Sheet'!E65 -> 71937 | F13: ='Data Sheet'!F65 -> 78672 | G13: ='Data Sheet'!G65 -> 87936 | H13: ='Data Sheet'!H65 -> 83947 | I13: ='Data Sheet'!I65 -> 92542 | ... K13: ='Data Sheet'!K65 -> 113171
A14: Total | B14: ='Data Sheet'!B66 -> 102333 | C14: ='Data Sheet'!C66 -> 105126 | D14: ='Data Sheet'!D66 -> 113901 | E14: ='Data Sheet'!E66 -> 120127 | F14: ='Data Sheet'!F66 -> 129992 | G14: ='Data Sheet'!G66 -> 140924 | H14: ='Data Sheet'!H66 -> 142859 | I14: ='Data Sheet'!I66 -> 145472 | ... K14: ='Data Sheet'!K66 -> 181167
A16: Working Capital | B16: =B13-B7 -> 31281 | C16: =C13-C7 -> 36116 | D16: =D13-D7 -> 46925 | E16: =E13-E7 -> 44110 | F16: =F13-F7 -> 42908 | G16: =G13-G7 -> 43969 | H16: =H13-H7 -> 39200 | I16: =I13-I7 -> 45580 | ... K16: =K13-K7 -> 50527
A17: Debtors | B17: ='Data Sheet'!B67 -> 22617 | C17: ='Data Sheet'!C67 -> 24943 | D17: ='Data Sheet'!D67 -> 27346 | E17: ='Data Sheet'!E67 -> 30532 | F17: ='Data Sheet'!F67 -> 30079 | G17: ='Data Sheet'!G67 -> 41810 | H17: ='Data Sheet'!H67 -> 49954 | I17: ='Data Sheet'!I67 -> 53577 | ... K17: ='Data Sheet'!K67 -> 67714
A18: Inventory | B18: ='Data Sheet'!B68 -> 21 | C18: ='Data Sheet'!C68 -> 26 | D18: ='Data Sheet'!D68 -> 10 | E18: ='Data Sheet'!E68 -> 5 | F18: ='Data Sheet'!F68 -> 8 | G18: ='Data Sheet'!G68 -> 20 | H18: ='Data Sheet'!H68 -> 28 | I18: ='Data Sheet'!I68 -> 28 | ... K18: ='Data Sheet'!K68 -> 29
A20: Debtor Days | B20: =IF('Profit & Loss'!B4>0,'Balance Sheet'!B17/('Profit & Loss'!B4/365),0) -> 69.979528 | C20: =IF('Profit & Loss'!C4>0,'Balance Sheet'!C17/('Profit & Loss'!C4/365),0) -> 73.955314 | D20: =IF('Profit & Loss'!D4>0,'Balance Sheet'!D17/('Profit & Loss'!D4/365),0) -> 68.148884 | E20: =IF('Profit & Loss'!E4>0,'Balance Sheet'!E17/('Profit & Loss'!E4/365),0) -> 71.005104 | F20: =IF('Profit & Loss'!F4>0,'Balance Sheet'!F17/('Profit & Loss'!F4/365),0) -> 66.871943 | G20: =IF('Profit & Loss'!G4>0,'Balance Sheet'!G17/('Profit & Loss'!G4/365),0) -> 79.58452 | H20: =IF('Profit & Loss'!H4>0,'Balance Sheet'!H17/('Profit & Loss'!H4/365),0) -> 80.87187 | I20: =IF('Profit & Loss'!I4>0,'Balance Sheet'!I17/('Profit & Loss'!I4/365),0) -> 81.179632 | ... K20: =IF('Profit & Loss'!K4>0,'Balance Sheet'!K17/('Profit & Loss'!K4/365),0) -> 92.560548
A21: Inventory Turnover | B21: =IF('Balance Sheet'!B18>0,'Profit & Loss'!B4/'Balance Sheet'!B18,0) -> 5617.4286 | C21: =IF('Balance Sheet'!C18>0,'Profit & Loss'!C4/'Balance Sheet'!C18,0) -> 4734.7692 | D21: =IF('Balance Sheet'!D18>0,'Profit & Loss'!D4/'Balance Sheet'!D18,0) -> 14646.3 | E21: =IF('Balance Sheet'!E18>0,'Profit & Loss'!E4/'Balance Sheet'!E18,0) -> 31389.8 | F21: =IF('Balance Sheet'!F18>0,'Profit & Loss'!F4/'Balance Sheet'!F18,0) -> 20522.125 | G21: =IF('Balance Sheet'!G18>0,'Profit & Loss'!G4/'Balance Sheet'!G18,0) -> 9587.7 | H21: =IF('Balance Sheet'!H18>0,'Profit & Loss'!H4/'Balance Sheet'!H18,0) -> 8052.0714 | I21: =IF('Balance Sheet'!I18>0,'Profit & Loss'!I4/'Balance Sheet'!I18,0) -> 8603.3214 | ... K21: =IF('Balance Sheet'!K18>0,'Profit & Loss'!K4/'Balance Sheet'!K18,0) -> 9207.6207
A23: Return on Equity | B23: =IF(SUM('Balance Sheet'!B4:B5)>0,'Profit & Loss'!B12/SUM('Balance Sheet'!B4:B5),"") -> 0.30492727 | C23: =IF(SUM('Balance Sheet'!C4:C5)>0,'Profit & Loss'!C12/SUM('Balance Sheet'!C4:C5),"") -> 0.30337844 | D23: =IF(SUM('Balance Sheet'!D4:D5)>0,'Profit & Loss'!D12/SUM('Balance Sheet'!D4:D5),"") -> 0.35185475 | E23: =IF(SUM('Balance Sheet'!E4:E5)>0,'Profit & Loss'!E12/SUM('Balance Sheet'!E4:E5),"") -> 0.38442336 | F23: =IF(SUM('Balance Sheet'!F4:F5)>0,'Profit & Loss'!F12/SUM('Balance Sheet'!F4:F5),"") -> 0.37520392 | G23: =IF(SUM('Balance Sheet'!G4:G5)>0,'Profit & Loss'!G12/SUM('Balance Sheet'!G4:G5),"") -> 0.42996892 | H23: =IF(SUM('Balance Sheet'!H4:H5)>0,'Profit & Loss'!H12/SUM('Balance Sheet'!H4:H5),"") -> 0.46610413 | I23: =IF(SUM('Balance Sheet'!I4:I5)>0,'Profit & Loss'!I12/SUM('Balance Sheet'!I4:I5),"") -> 0.50733238 | ... K23: =IF(SUM('Balance Sheet'!K4:K5)>0,'Profit & Loss'!K12/SUM('Balance Sheet'!K4:K5),"") -> 0.45887728
A24: Return on Capital Emp | C24: =IF((B4+B5+B6+C4+C5+C6)>0,('Profit & Loss'!C10+'Profit & Loss'!C9)*2/(B4+B5+B6+C4+C5+C6),"") -> 0.39730507 | D24: =IF((C4+C5+C6+D4+D5+D6)>0,('Profit & Loss'!D10+'Profit & Loss'!D9)*2/(C4+C5+C6+D4+D5+D6),"") -> 0.47758787 | E24: =IF((D4+D5+D6+E4+E5+E6)>0,('Profit & Loss'!E10+'Profit & Loss'!E9)*2/(D4+D5+D6+E4+E5+E6),"") -> 0.4749186 | F24: =IF((E4+E5+E6+F4+F5+F6)>0,('Profit & Loss'!F10+'Profit & Loss'!F9)*2/(E4+E5+E6+F4+F5+F6),"") -> 0.47603577 | G24: =IF((F4+F5+F6+G4+G5+G6)>0,('Profit & Loss'!G10+'Profit & Loss'!G9)*2/(F4+F5+F6+G4+G5+G6),"") -> 0.5489029 | H24: =IF((G4+G5+G6+H4+H5+H6)>0,('Profit & Loss'!H10+'Profit & Loss'!H9)*2/(G4+G5+G6+H4+H5+H6),"") -> 0.591442 | I24: =IF((H4+H5+H6+I4+I5+I6)>0,('Profit & Loss'!I10+'Profit & Loss'!I9)*2/(H4+H5+H6+I4+I5+I6),"") -> 0.63853485 | J24: =IF((I4+I5+I6+J4+J5+J6)>0,('Profit & Loss'!J10+'Profit & Loss'!J9)*2/(I4+I5+I6+J4+J5+J6),"") -> 0.65259699 | K24: =IF((J4+J5+J6+K4+K5+K6)>0,('Profit & Loss'!K10+'Profit & Loss'!K9)*2/(J4+J5+J6+K4+K5+K6),"") -> 0.59921588

Sheet Cash Flow
A1: ='Balance Sheet'!A1 -> TATA CONSULTANCY SERVICES LTD | E1: =UPDATE | J1: SCREENER.IN
A3: Narration | B3: ='Data Sheet'!B81 -> 42825 | C3: ='Data Sheet'!C81 -> 43190 | D3: ='Data Sheet'!D81 -> 43555 | E3: ='Data Sheet'!E81 -> 43921 | F3: ='Data Sheet'!F81 -> 44286 | G3: ='Data Sheet'!G81 -> 44651 | H3: ='Data Sheet'!H81 -> 45016 | I3: ='Data Sheet'!I81 -> 45382 | ... K3: ='Data Sheet'!K81 -> 46112
A4: Cash from Operating Activity | B4: ='Data Sheet'!B82 -> 25223 | C4: ='Data Sheet'!C82 -> 25067 | D4: ='Data Sheet'!D82 -> 28593 | E4: ='Data Sheet'!E82 -> 32369 | F4: ='Data Sheet'!F82 -> 38802 | G4: ='Data Sheet'!G82 -> 39949 | H4: ='Data Sheet'!H82 -> 41965 | I4: ='Data Sheet'!I82 -> 44338 | ... K4: ='Data Sheet'!K82 -> 52094
A5: Cash from Investing Activity | B5: ='Data Sheet'!B83 -> -16895 | C5: ='Data Sheet'!C83 -> 3104 | D5: ='Data Sheet'!D83 -> 1645 | E5: ='Data Sheet'!E83 -> 8968 | F5: ='Data Sheet'!F83 -> -7956 | G5: ='Data Sheet'!G83 -> -738 | H5: ='Data Sheet'!H83 -> 548 | I5: ='Data Sheet'!I83 -> 6091 | ... K5: ='Data Sheet'!K83 -> -11886
A6: Cash from Financing Activity | B6: ='Data Sheet'!B84 -> -11026 | C6: ='Data Sheet'!C84 -> -26885 | D6: ='Data Sheet'!D84 -> -27897 | E6: ='Data Sheet'!E84 -> -39915 | F6: ='Data Sheet'!F84 -> -32634 | G6: ='Data Sheet'!G84 -> -33581 | H6: ='Data Sheet'!H84 -> -47878 | I6: ='Data Sheet'!I84 -> -48536 | ... K6: ='Data Sheet'!K84 -> -42133
A7: Net Cash Flow | B7: ='Data Sheet'!B85 -> -2698 | C7: ='Data Sheet'!C85 -> 1286 | D7: ='Data Sheet'!D85 -> 2341 | E7: ='Data Sheet'!E85 -> 1422 | F7: ='Data Sheet'!F85 -> -1788 | G7: ='Data Sheet'!G85 -> 5630 | H7: ='Data Sheet'!H85 -> -5365 | I7: ='Data Sheet'!I85 -> 1893 | ... K7: ='Data Sheet'!K85 -> -1925
A9: Fixed assets purchased | B9: -2949 | C9: -1987 | D9: -1989 | E9: -1862 | F9: -2231 | G9: -3249 | H9: -3176 | I9: -2995 | J9: -3100 | K9: -2674 | L9: -3937 | M9: -4146
A10: Fixed assets sold | B10: 7 | C10: 22 | D10: 36 | E10: 58 | F10: 99 | G10: 161 | H10: 37 | I10: 31 | J10: 37 | K10: 24 | L10: 23 | M10: 65
A11: Investments purchased | B11: -67371 | C11: -116847 | D11: -121423 | E11: -97473 | F11: -96751 | G11: -80002 | H11: -54462 | I11: -75374 | J11: -129745 | K11: -141011 | L11: -145962 | M11: -152114
A12: Investments sold | B12: 69361 | C12: 97154 | D12: 102798 | E12: 103482 | F12: 104133 | G12: 84089 | H12: 51630 | I12: 73852 | J12: 122687 | K12: 147204 | L12: 147695 | M12: 148023
A23: Particulars | B23: Value
A24: Current Market Price | B24: 2365.6
A25: Intrinsic Value (DCF) | B25: 2766.23
A26: Potential Upside | B26: 0.1694
A27: DCF Valuation | B27: Undervalued
A28: Recommendation | B28: BUY

Sheet Customization
A1: How to use it?
A3: You can customize this workbook as you want.
B4: You can add custom formating, add conditional formating, add your own formulas… do ANYTHING.
B5: Please don't edit the "Data Sheet" only.
A7: After customization, you can upload this back on Screener.
B8: Upload on: | C8: https://www.screener.in/excel/
A10: Download your customized workbooks now onwards.
B11: Now whenever you will "Export to excel" from Screener, it will export your customized file.
A14: TESTING:
B15: This is a testing feature currently.
B16: You can report any formula errors on the worksheet at: support@screener.in

Sheet Data Sheet
A1: COMPANY NAME | B1: TATA CONSULTANCY SERVICES LTD | E1: =IF(B2<>B3, "A NEW VERSION OF THE WORKSHEET IS AVAILABLE", "")
A2: LATEST VERSION | B2: 2.1 | E2: PLEASE DO NOT MAKE ANY CHANGES TO THIS SHEET
A3: CURRENT VERSION | B3: 2.1
A5: META
A6: Number of shares | B6: =IF(B9>0, B9/B8, 0) -> 361.80875
A7: Face Value | B7: 1
A8: Current Price | B8: 2365.6
A9: Market Capitalization | B9: 855894.78
A15: PROFIT & LOSS
A16: Report Date | B16: 42825 | C16: 43190 | D16: 43555 | E16: 43921 | F16: 44286 | G16: 44651 | H16: 45016 | I16: 45382 | J16: 45747 | K16: 46112
A17: Sales | B17: 117966 | C17: 123104 | D17: 146463 | E17: 156949 | F17: 164177 | G17: 191754 | H17: 225458 | I17: 240893 | J17: 255324 | K17: 267021
A18: Raw Material Cost | B18: 94 | C18: 86 | D18: 40 | E18: 18 | F18: 14 | G18: 29 | H18: 37 | I18: 42 | J18: 49 | K18: 43
A19: Change in Inventory | B19: 1
A20: Power and Fuel
A21: Other Mfr. Exp | B21: 2715 | C21: 2614 | D21: 2230 | E21: 1887 | F21: 1448 | G21: 1134 | H21: 1844 | I21: 3660 | J21: 11599 | K21: 4356
A22: Employee Cost | B22: 61621 | C22: 66396 | D22: 78246 | E22: 85952 | F22: 91814 | G22: 107554 | H22: 127522 | I22: 140131 | J22: 145788 | K22: 154994
A23: Selling and admin | B23: 16392 | C23: 16808 | D23: 20387 | E23: 20527 | F23: 18322 | G23: 23187 | H23: 28913 | I23: 24151 | J23: 20729 | K23: 24434
A24: Other Expenses | B24: 4834 | C24: 4684 | D24: 6054 | E24: 6456 | F24: 6033 | G24: 6793 | H24: 7883 | I24: 8613 | J24: 9752 | K24: 10796
A25: Other Income | B25: 4221 | C25: 3642 | D25: 4311 | E25: 4592 | F25: 1916 | G25: 4018 | H25: 3449 | I25: 3464 | J25: 3962 | K25: -124
A26: Depreciation | B26: 1987 | C26: 2014 | D26: 2056 | E26: 3529 | F26: 4065 | G26: 4604 | H26: 5022 | I26: 4985 | J26: 5242 | K26: 5560
A27: Interest | B27: 32 | C27: 52 | D27: 198 | E27: 924 | F27: 637 | G27: 784 | H27: 779 | I27: 778 | J27: 796 | K27: 1227
A28: Profit before tax | B28: 34513 | C28: 34092 | D28: 41563 | E28: 42248 | F28: 43760 | G28: 51687 | H28: 56907 | I28: 61997 | J28: 65331 | K28: 65487
A29: Tax | B29: 8156 | C29: 8212 | D29: 10001 | E29: 9801 | F29: 11198 | G29: 13238 | H29: 14604 | I29: 15898 | J29: 16534 | K29: 16033
A30: Net profit | B30: 26289 | C30: 25826 | D30: 31472 | E30: 32340 | F30: 32430 | G30: 38327 | H30: 42147 | I30: 45908 | J30: 48553 | K30: 49210
A31: Dividend Amount | B31: 9259 | C31: 9550 | D31: 11250 | E31: 27375 | F31: 14060 | G31: 15738 | H31: 42090 | I31: 26426 | J31: 45612 | K31: 39820
A40: Quarters
A41: Report Date | B41: 45382 | C41: 45473 | D41: 45565 | E41: 45657 | F41: 45747 | G41: 45838 | H41: 45930 | I41: 46022 | J41: 46112 | K41: 46203
A42: Sales | B42: 61237 | C42: 62613 | D42: 64259 | E42: 63973 | F42: 64479 | G42: 63437 | H42: 65799 | I42: 67087 | J42: 70698 | K42: 72275
A43: Expenses | B43: 44073 | C43: 45951 | D43: 47528 | E43: 46939 | F43: 47499 | G43: 46562 | H43: 47821 | I43: 48818 | J43: 51422 | K43: 53719
A44: Other Income | B44: 1157 | C44: 962 | D44: 729 | E44: 1243 | F44: 1028 | G44: 1660 | H44: -268 | I44: -2273 | J44: 757 | K44: 900
A45: Depreciation | B45: 1246 | C45: 1220 | D45: 1266 | E45: 1377 | F45: 1379 | G45: 1361 | H45: 1413 | I45: 1380 | J45: 1406 | K45: 1239
A46: Interest | B46: 226 | C46: 173 | D46: 162 | E46: 234 | F46: 227 | G46: 195 | H46: 229 | I46: 538 | J46: 265 | K46: 273
A47: Profit before tax | B47: 16849 | C47: 16231 | D47: 16032 | E47: 16666 | F47: 16402 | G47: 16979 | H47: 16068 | I47: 14078 | J47: 18362 | K47: 17944
A48: Tax | B48: 4347 | C48: 4126 | D48: 4077 | E48: 4222 | F48: 4109 | G48: 4160 | H48: 3937 | I48: 3358 | J48: 4578 | K48: 4524
A49: Net profit | B49: 12434 | C49: 12040 | D49: 11909 | E49: 12380 | F49: 12224 | G49: 12760 | H49: 12075 | I49: 10657 | J49: 13718 | K49: 13349
A50: Operating Profit | B50: 17164 | C50: 16662 | D50: 16731 | E50: 17034 | F50: 16980 | G50: 16875 | H50: 17978 | I50: 18269 | J50: 19276 | K50: 18556
A55: BALANCE SHEET
A56: Report Date | B56: 42825 | C56: 43190 | D56: 43555 | E56: 43921 | F56: 44286 | G56: 44651 | H56: 45016 | I56: 45382 | J56: 45747 | K56: 46112
A57: Equity Share Capital | B57: 197 | C57: 191 | D57: 375 | E57: 375 | F57: 370 | G57: 366 | H57: 366 | I57: 362 | J57: 362 | K57: 362
A58: Reserves | B58: 86017 | C58: 84937 | D58: 89071 | E58: 83751 | F58: 86063 | G58: 88773 | H58: 90058 | I58: 90127 | J58: 94394 | K58: 106878
A59: Borrowings | B59: 289 | C59: 247 | D59: 62 | E59: 8174 | F59: 7795 | G59: 7818 | H59: 7688 | I59: 8021 | J59: 9392 | K59: 11283
A60: Other Liabilities | B60: 15830 | C60: 19751 | D60: 24393 | E60: 27827 | F60: 35764 | G60: 43967 | H60: 44747 | I60: 46962 | J60: 54501 | K60: 62644
A61: Total | B61: 102333 | C61: 105126 | D61: 113901 | E61: 120127 | F61: 129992 | G61: 140924 | H61: 142859 | I61: 145472 | J61: 158649 | K61: 181167
A62: Net Block | B62: 11701 | C62: 11973 | D62: 12290 | E62: 20928 | F62: 21021 | G62: 21298 | H62: 20515 | I62: 19604 | J62: 23053 | K62: 31343
A63: Capital Work in Progress | B63: 1541 | C63: 1278 | D63: 963 | E63: 906 | F63: 926 | G63: 1205 | H63: 1234 | I63: 1564 | J63: 1546 | K63: 2665
A64: Investments | B64: 41980 | C64: 36008 | D64: 29330 | E64: 26356 | F64: 29373 | G64: 30485 | H64: 37163 | I64: 31762 | J64: 30964 | K64: 33988
A65: Other Assets | B65: 47111 | C65: 55867 | D65: 71318 | E65: 71937 | F65: 78672 | G65: 87936 | H65: 83947 | I65: 92542 | J65: 103086 | K65: 113171
A66: Total | B66: 102333 | C66: 105126 | D66: 113901 | E66: 120127 | F66: 129992 | G66: 140924 | H66: 142859 | I66: 145472 | J66: 158649 | K66: 181167
A67: Receivables | B67: 22617 | C67: 24943 | D67: 27346 | E67: 30532 | F67: 30079 | G67: 41810 | H67: 49954 | I67: 53577 | J67: 59046 | K67: 67714
... A70: No. of Equity Shares | B70: 1970427941 | C70: 1914287591 | D70: 3752384706 | E70: 3752384706 | F70: 3699051373 | G70: 3659051373 | H70: 3659051373 | I70: 3618087518 | J70: 3618087518 | K70: 3618087518
A71: New Bonus Shares
A72: Face value | B72: 1 | C72: 1 | D72: 1 | E72: 1 | F72: 1 | G72: 1 | H72: 1 | I72: 1 | J72: 1 | K72: 1
A75: =A65 -> Other Assets | B75: =B65-(B67+B68+B69) -> 20324 | C75: =C65-(C67+C68+C69) -> 23737 | D75: =D65-(D67+D68+D69) -> 31114 | E75: =E65-(E67+E68+E69) -> 31734 | F75: =F65-(F67+F68+F69) -> 39256 | G75: =G65-(G67+G68+G69) -> 27885 | H75: =H65-(H67+H68+H69) -> 22933 | I75: =I65-(I67+I68+I69) -> 25651 | ... K75: =K65-(K67+K68+K69) -> 32520
B78: =B75+B76+B77 -> 20324
A80: CASH FLOW: | E80: =E75=D67+D68+D69 -> FALSE
A81: Report Date | B81: 42825 | C81: 43190 | D81: 43555 | E81: 43921 | F81: 44286 | G81: 44651 | H81: 45016 | I81: 45382 | J81: 45747 | K81: 46112
A82: Cash from Operating Activity | B82: 25223 | C82: 25067 | D82: 28593 | E82: 32369 | F82: 38802 | G82: 39949 | H82: 41965 | I82: 44338 | J82: 48908 | K82: 52094
A83: Cash from Investing Activity | B83: -16895 | C83: 3104 | D83: 1645 | E83: 8968 | F83: -7956 | G83: -738 | H83: 548 | I83: 6091 | J83: -2144 | K83: -11886
A84: Cash from Financing Activity | B84: -11026 | C84: -26885 | D84: -27897 | E84: -39915 | F84: -32634 | G84: -33581 | H84: -47878 | I84: -48536 | J84: -47438 | K84: -42133
A85: Net Cash Flow | B85: -2698 | C85: 1286 | D85: 2341 | E85: 1422 | F85: -1788 | G85: 5630 | H85: -5365 | I85: 1893 | J85: -674 | K85: -1925
C88: =C67/B67-1 -> 0.10284299 | D88: =D67/C67-1 -> 0.096339654 | E88: =E67/D67-1 -> 0.11650698 | F88: =F67/E67-1 -> -0.014836892 | G88: =G67/F67-1 -> 0.39000632 | H88: =H67/G67-1 -> 0.19478594 | I88: =I67/H67-1 -> 0.072526725 | J88: =J67/I67-1 -> 0.10207738 | K88: =K67/J67-1 -> 0.1468008
A90: PRICE: | B90: 1215.9 | C90: 1424.58 | D90: 2001.65 | E90: 1826.1 | F90: 3177.85 | G90: 3739.95 | H90: 3205.9 | I90: 3876.3 | J90: 3606.15 | K90: 2358.9
A92: DERIVED:
A93: Adjusted Equity Shares in Cr | B93: 394.09 | C93: 382.86 | D93: 375.24 | E93: 375.24 | F93: 369.91 | G93: 365.91 | H93: 365.91 | I93: 361.81 | J93: 361.81 | K93: 361.81
B96: 1
C99: =B90*B93 -> 479174.03
A100: CaptalEmployed | B100: =B61-B60 -> 86503 | C100: =C61-C60 -> 85375 | D100: =D61-D60 -> 89508 | E100: =E61-E60 -> 92300 | F100: =F61-F60 -> 94228 | G100: =G61-G60 -> 96957 | H100: =H61-H60 -> 98112 | I100: =I61-I60 -> 98510 | ... K100: =K61-K60 -> 118523
A101: MCP | B101: =B70*B90/100000000 -> 23958.433 | C101: =C70*C90/100000000 -> 27270.558 | D101: =D70*D90/100000000 -> 75109.608 | E101: =E70*E90/100000000 -> 68522.297 | F101: =F70*F90/100000000 -> 117550.3 | G101: =G70*G90/100000000 -> 136846.69 | H101: =H70*H90/100000000 -> 117305.53 | I101: =I70*I90/100000000 -> 140247.93 | ... K101: =K70*K90/100000000 -> 85347.066
A102: Debt | B102: =B59 -> 289 | C102: =C59 -> 247 | D102: =D59 -> 62 | E102: =E59 -> 8174 | F102: =F59 -> 7795 | G102: =G59 -> 7818 | H102: =H59 -> 7688 | I102: =I59 -> 8021 | ... K102: =K59 -> 11283
A103: Cash | B103: =B69 -> 4149 | C103: =C69 -> 7161 | D103: =D69 -> 12848 | E103: =E69 -> 9666 | F103: =F69 -> 9329 | G103: =G69 -> 18221 | H103: =H69 -> 11032 | I103: =I69 -> 13286 | ... K103: =K69 -> 12908
A105: Enterpresas Value | B105: =(B101+B102)-B103 -> 20098.433 | C105: =(C101+C102)-C103 -> 20356.558 | D105: =(D101+D102)-D103 -> 62323.608 | E105: =(E101+E102)-E103 -> 67030.297 | F105: =(F101+F102)-F103 -> 116016.3 | G105: =(G101+G102)-G103 -> 126443.69 | H105: =(H101+H102)-H103 -> 113961.53 | I105: =(I101+I102)-I103 -> 134982.93 | ... K105: =(K101+K102)-K103 -> 83722.066
A107: Book Value | B107: =B57+B58 -> 86214 | C107: =C57+C58 -> 85128 | D107: =D57+D58 -> 89446 | E107: =E57+E58 -> 84126 | F107: =F57+F58 -> 86433 | G107: =G57+G58 -> 89139 | H107: =H57+H58 -> 90424 | I107: =I57+I58 -> 90489 | ... K107: =K57+K58 -> 107240
A108: P/B | B108: =B101/B107 -> 0.27789493 | C108: =C101/C107 -> 0.32034769 | D108: =D101/D107 -> 0.83972015 | E108: =E101/E107 -> 0.81451985 | F108: =F101/F107 -> 1.3600165 | G108: =G101/G107 -> 1.5352056 | H108: =H101/H107 -> 1.2972831 | I108: =I101/I107 -> 1.5498892 | ... K108: =K101/K107 -> 0.79585105
A109: Return on Equity | B109: =B49/(B57+B58)*$B$96 -> 0.14422252 | C109: =C49/(C57+C58)*$B$96 -> 0.14143408 | D109: =D49/(D57+D58)*$B$96 -> 0.13314178 | E109: =E49/(E57+E58)*$B$96 -> 0.14716021 | F109: =F49/(F57+F58)*$B$96 -> 0.14142746 | G109: =G49/(G57+G58)*$B$96 -> 0.14314722 | H109: =H49/(H57+H58)*$B$96 -> 0.13353756 | I109: =I49/(I57+I58)*$B$96 -> 0.11777122 | ... K109: =K49/(K57+K58)*$B$96 -> 0.12447781
A110: Return on Capital Employed | B110: ='Historicail Financial Statement'!D17/'Data Sheet'!B100*'Data Sheet'!$B$96 -> 0.45670092 | C110: ='Historicail Financial Statement'!E17/'Data Sheet'!C100*'Data Sheet'!$B$96 -> 0.49322401 | D110: ='Historicail Financial Statement'!F17/'Data Sheet'!D100*'Data Sheet'!$B$96 -> 0.52002056 | E110: ='Historicail Financial Statement'!G17/'Data Sheet'!E100*'Data Sheet'!$B$96 -> 0.57483207 | F110: ='Historicail Financial Statement'!H17/'Data Sheet'!F100*'Data Sheet'!$B$96 -> 0.6288895 | G110: ='Historicail Financial Statement'!I17/'Data Sheet'!G100*'Data Sheet'!$B$96 -> 0.66313933 | H110: ='Historicail Financial Statement'!J17/'Data Sheet'!H100*'Data Sheet'!$B$96 -> 0.68704134 | I110: ='Historicail Financial Statement'!K17/'Data Sheet'!I100*'Data Sheet'!$B$96 -> 0.73493046 | J110: ='Historicail Financial Statement'!L17/'Data Sheet'!J100*'Data Sheet'!$B$96 -> 0.71128586 | K110: ='Historicail Financial Statement'!K17/'Data Sheet'!K100*'Data Sheet'!$B$96 -> 0.61083503

Sheet One Page Profil
B2: Tcs-One Page Profile
B11: Key Financial Matrics | D11: ='Historicail Financial Statement'!H4 -> 45016 | E11: ='Historicail Financial Statement'!I4 -> 45382 | F11: ='Historicail Financial Statement'!J4 -> 45747 | G11: ='Historicail Financial Statement'!K4 -> 46112 | I11: 5yers - Shre Price
B13: Total Sales | D13: ='Historicail Financial Statement'!H7 -> 225458 | E13: ='Historicail Financial Statement'!I7 -> 240893 | F13: ='Historicail Financial Statement'!J7 -> 255324 | G13: ='Historicail Financial Statement'!K7 -> 267021
B14: Sales Growth (y-oy) | D14: ='Historicail Financial Statement'!H8 -> 0.17576687 | E14: ='Historicail Financial Statement'!I8 -> 0.068460645 | F14: ='Historicail Financial Statement'!J8 -> 0.059906265 | G14: ='Historicail Financial Statement'!K8 -> 0.04581238
B15: Gross Profit Margin (%) | D15: ='Historicail Financial Statement'!G13 -> 0.99393494 | E15: ='Historicail Financial Statement'!H13 -> 0.99165698 | F15: ='Historicail Financial Statement'!I13 -> 0.98463218 | G15: ='Historicail Financial Statement'!J13 -> 0.95437953
B16: EBITDA Margin (%) | D16: ='Historicail Financial Statement'!H18 -> 0.26283831 | E16: ='Historicail Financial Statement'!I18 -> 0.26690688 | F16: ='Historicail Financial Statement'!J18 -> 0.26400573 | G16: ='Historicail Financial Statement'!K18 -> 0.27113223
B17: EBIT Margin (%) | D17: ='Historicail Financial Statement'!H24 -> 0.24056365 | E17: ='Historicail Financial Statement'!I24 -> 0.24621305 | F17: ='Historicail Financial Statement'!J24 -> 0.24347496 | G17: ='Historicail Financial Statement'!K24 -> 0.2503099
B18: Net Profit Margin(%) | D18: ='Historicail Financial Statement'!H39 -> 0.1876314 | E18: ='Historicail Financial Statement'!I39 -> 0.19136712 | F18: ='Historicail Financial Statement'!J39 -> 0.19111795 | G18: ='Historicail Financial Statement'!K39 -> 0.18520641
B19: Earning Per Share in (Cr.rs) | D19: ='Historicail Financial Statement'!H43 -> 115.6104 | E19: ='Historicail Financial Statement'!I43 -> 127.41218 | F19: ='Historicail Financial Statement'!J43 -> 134.86913 | G19: ='Historicail Financial Statement'!K43 -> 136.685
B20: EPS Growth (y-oy) | D20: ='Historicail Financial Statement'!H44 -> 0.10023668 | E20: ='Historicail Financial Statement'!I44 -> 0.10208236 | F20: ='Historicail Financial Statement'!J44 -> 0.058526215 | G20: ='Historicail Financial Statement'!K44 -> 0.013463942
B21: Divident Per Share | D21: ='Historicail Financial Statement'!H47 -> 0.9949649 | E21: ='Historicail Financial Statement'!I47 -> 0.57324454 | F21: ='Historicail Financial Statement'!J47 -> 0.93472959 | G21: ='Historicail Financial Statement'!K47 -> 0.8051927
B22: DPS Growth (y-oy) | D22: ='Data Sheet'!H88 -> 0.19478594 | E22: ='Data Sheet'!I88 -> 0.072526725 | F22: ='Data Sheet'!J88 -> 0.10207738 | G22: ='Data Sheet'!K88 -> 0.1468008
B24: Key Financial ratios | D24: =D11 -> 45016 | E24: =E11 -> 45382 | F24: =F11 -> 45747 | G24: =G11 -> 46112 | I24: Valume
B26: Price to Earning | D26: ='Data Sheet'!$B$8/'Historicail Financial Statement'!H43 -> 20.461828 | E26: ='Data Sheet'!$B$8/'Historicail Financial Statement'!I43 -> 18.566514 | F26: ='Data Sheet'!$B$8/'Historicail Financial Statement'!J43 -> 17.539966 | G26: ='Data Sheet'!$B$8/'Historicail Financial Statement'!K43 -> 17.306947
B27: EV/EBITDA | D27: ='Data Sheet'!H105/'Historicail Financial Statement'!H17 -> 1.9231092 | E27: ='Data Sheet'!I105/'Historicail Financial Statement'!I17 -> 2.0993985 | F27: ='Data Sheet'!J105/'Historicail Financial Statement'!J17 -> 1.8455452 | G27: ='Data Sheet'!K105/'Historicail Financial Statement'!K17 -> 1.1564141
B28: EV/Sales | D28: ='Data Sheet'!H105/'Historicail Financial Statement'!H7 -> 0.50546677 | E28: ='Data Sheet'!I105/'Historicail Financial Statement'!I7 -> 0.56034391 | F28: ='Data Sheet'!J105/'Historicail Financial Statement'!J7 -> 0.48723451 | G28: ='Data Sheet'!K105/'Historicail Financial Statement'!K7 -> 0.31354113
B29: Price to Book Valu | D29: ='Data Sheet'!H108 -> 1.2972831 | E29: ='Data Sheet'!I108 -> 1.5498892 | F29: ='Data Sheet'!J108 -> 1.3769436 | G29: ='Data Sheet'!K108 -> 0.79585105
B30: Return on Equity | D30: ='Data Sheet'!H109 -> 0.13353756 | E30: ='Data Sheet'!I109 -> 0.11777122 | F30: ='Data Sheet'!J109 -> 0.14477184 | G30: ='Data Sheet'!K109 -> 0.12447781
B31: Return on CapitalEmployed | D31: ='Data Sheet'!H110 -> 0.68704134 | E31: ='Data Sheet'!I110 -> 0.73493046 | F31: ='Data Sheet'!J110 -> 0.71128586 | G31: ='Data Sheet'!K110 -> 0.61083503
B34: Top 10 Share Holder | D34: Share Pres | E34: Shares Holding | G34: Current Mareket valu | I34: Share Holing Pettren
B35: Tata Sons Private Limited | D35: 0.7174 | E35: 2595499419 | G35: =E35*Comps_val!$P$28/100000000 -> 61399.134
B36: LIC | D36: 0.0552 | E36: 199553451 | G36: =E36*Comps_val!$P$28/100000000 -> 4720.6364
B37: SBI Mutual Fund | D37: 0.0125 | E37: 45239395 | G37: =E37*Comps_val!$P$28/100000000 -> 1070.1831
B38: ICICI Prudential Mutual | D38: 0.0106 | E38: 38172688 | G38: =E38*Comps_val!$P$28/100000000 -> 903.01311
B39: National Pension | D39: 0.0079 | E39: 28525843 | G39: =E39*Comps_val!$P$28/100000000 -> 674.80734
B40: Nippon Life India | D40: 0.005 | E40: 17924007 | G40: =E40*Comps_val!$P$28/100000000 -> 424.01031
B41: UTI Mutual Fund | D41: 0.0049 | E41: 17573906 | G41: =E41*Comps_val!$P$28/100000000 -> 415.72832
B42: HDFC Mutual Fund | D42: 0.0046 | E42: 16686284 | G42: =E42*Comps_val!$P$28/100000000 -> 394.73073
B43: VTI | D43: 0.0041 | E43: 14892949 | G43: =E43*Comps_val!$P$28/100000000 -> 352.3076
B44: V ME | D44: 0.0039 | E44: 14139580 | G44: =E44*Comps_val!$P$28/100000000 -> 334.4859
B45: Managireal Ramunuration | D45: Disgnation | E45: Remuniration (INR.Crs) | G45: Salary Per Month | I45: Capital Sturcture
B46: K. Krithivasan | D46: CEO | E46: 26.52 | G46: 221
B47: Samir Seksaria | D47: CFO | E47: 8.64 | G47: 72 | I47: Share Price on | L47: ='Data Sheet'!B8 -> 2365.6
B48: Milind Lakkad | D48: CHRO | E48: 6.18 | G48: 51.5 | I48: No of Shares | L48: ='Data Sheet'!B6 -> 361.80875
B49: Ashok Pai | D49: Head – Global Consulting | E49: 5.14 | G49: 4.5 | I49: MCP | L49: =L47*L48 -> 855894.78
B50: Siva Ganesan | D50: Head – AI & Data Business Unit | E50: 5.12 | G50: 4.2 | I50: Less: Cash | L50: ='Data Sheet'!K69 -> 12908
B51: V. Rajanna | D51: President – Technology | E51: 6.15. | G51: 5.2 | I51: Add : Total Debt | L51: ='Data Sheet'!K102 -> 11283
B52: Krishnan Ramanujam | D52: President -CBG | E52: 4.15 | G52: 3.5 | I52: Add:monatary Intrast | L52: ='Data Sheet'!K46 -> 273
I53: Enteprise Value | L53: =L49+L51+L52-(L50) -> 854542.78
B54: Recent Update

Sheet Historicail Financial Statement
B3: ="Historical Financial Statement - "&'Data Sheet'!B1 -> Historical Financial Statement - TATA CONSULTANCY SERVICES LTD
B4: Years | D4: ='Data Sheet'!D16 -> 43555 | E4: ='Data Sheet'!E16 -> 43921 | F4: ='Data Sheet'!F16 -> 44286 | G4: ='Data Sheet'!G16 -> 44651 | H4: ='Data Sheet'!H16 -> 45016 | I4: ='Data Sheet'!I16 -> 45382 | J4: ='Data Sheet'!J16 -> 45747 | K4: ='Data Sheet'!K16 -> 46112 | L4: LTM
A6: # | B6: ="Income Statement - "&'Data Sheet'!B1 -> Income Statement - TATA CONSULTANCY SERVICES LTD
B7: Sales | D7: =IFERROR('Data Sheet'!D17,0) -> 146463 | E7: =IFERROR('Data Sheet'!E17,0) -> 156949 | F7: =IFERROR('Data Sheet'!F17,0) -> 164177 | G7: =IFERROR('Data Sheet'!G17,0) -> 191754 | H7: =IFERROR('Data Sheet'!H17,0) -> 225458 | I7: =IFERROR('Data Sheet'!I17,0) -> 240893 | J7: =IFERROR('Data Sheet'!J17,0) -> 255324 | K7: =IFERROR('Data Sheet'!K17,0) -> 267021 | L7: =IFERROR(SUM('Data Sheet'!H42:K42),0) -> 275859
B8: Sales Growth | D8: - | E8: =E7/D7-1 -> 0.071594874 | F8: =F7/E7-1 -> 0.046053177 | G8: =G7/F7-1 -> 0.16797115 | H8: =H7/G7-1 -> 0.17576687 | I8: =I7/H7-1 -> 0.068460645 | J8: =J7/I7-1 -> 0.059906265 | K8: =K7/J7-1 -> 0.04581238 | L8: =L7/K7-1 -> 0.03309852
B10: COGS | D10: =IFERROR(SUM('Data Sheet'!D18:D21),0) -> 2270 | E10: =IFERROR(SUM('Data Sheet'!E18:E21),0) -> 1905 | F10: =IFERROR(SUM('Data Sheet'!F18:F21),0) -> 1462 | G10: =IFERROR(SUM('Data Sheet'!G18:G21),0) -> 1163 | H10: =IFERROR(SUM('Data Sheet'!H18:H21),0) -> 1881 | I10: =IFERROR(SUM('Data Sheet'!I18:I21),0) -> 3702 | J10: =IFERROR(SUM('Data Sheet'!J18:J21),0) -> 11648 | K10: =IFERROR(SUM('Data Sheet'!K18:K21),0) -> 4399 | L10: =IFERROR(SUM('Data Sheet'!H43:K43),0) -> 201780
B11: COGS % Sales | D11: =D10/D7 -> 0.015498795 | E11: =E10/E7 -> 0.012137701 | F11: =F10/F7 -> 0.0089050232 | G11: =G10/G7 -> 0.0060650625 | H11: =H10/H7 -> 0.0083430173 | I11: =I10/I7 -> 0.015367819 | J11: =J10/J7 -> 0.045620467 | K11: =K10/K7 -> 0.01647436 | L11: =L10/L7 -> 0.73146064
B12: Gross Profit | D12: =D7-D10 -> 144193 | E12: =E7-E10 -> 155044 | F12: =F7-F10 -> 162715 | G12: =G7-G10 -> 190591 | H12: =H7-H10 -> 223577 | I12: =I7-I10 -> 237191 | J12: =J7-J10 -> 243676 | K12: =K7-K10 -> 262622 | L12: =L7-L10 -> 74079
B13: Gross Margins | D13: =D12/D7 -> 0.98450121 | E13: =E12/E7 -> 0.9878623 | F13: =F12/F7 -> 0.99109498 | G13: =G12/G7 -> 0.99393494 | H13: =H12/H7 -> 0.99165698 | I13: =I12/I7 -> 0.98463218 | J13: =J12/J7 -> 0.95437953 | K13: =K12/K7 -> 0.98352564 | L13: =L12/L7 -> 0.26853936
B15: Seling & Genral Expances | D15: =IFERROR(SUM('Data Sheet'!D22:D24),0) -> 104687 | E15: =IFERROR(SUM('Data Sheet'!E22:E24),0) -> 112935 | F15: =IFERROR(SUM('Data Sheet'!F22:F24),0) -> 116169 | G15: =IFERROR(SUM('Data Sheet'!G22:G24),0) -> 137534 | H15: =IFERROR(SUM('Data Sheet'!H22:H24),0) -> 164318 | I15: =IFERROR(SUM('Data Sheet'!I22:I24),0) -> 172895 | J15: =IFERROR(SUM('Data Sheet'!J22:J24),0) -> 176269 | K15: =IFERROR(SUM('Data Sheet'!K22:K24),0) -> 190224
B16: S&Gexp % Sales | D16: =D15/D7 -> 0.71476755 | E16: =E15/E7 -> 0.71956495 | F16: =F15/F7 -> 0.70758389 | G16: =G15/G7 -> 0.71724188 | H16: =H15/H7 -> 0.72881867 | I16: =I15/I7 -> 0.7177253 | J16: =J15/J7 -> 0.6903738 | K16: =K15/K7 -> 0.71239341 | L16: =L15/L7 -> 0
B17: EBITDA | D17: =D12-D15 -> 39506 | E17: =E12-E15 -> 42109 | F17: =F12-F15 -> 46546 | G17: =G12-G15 -> 53057 | H17: =H12-H15 -> 59259 | I17: =I12-I15 -> 64296 | J17: =J12-J15 -> 67407 | K17: =K12-K15 -> 72398 | L17: =L12-L15 -> 74079
B18: EBITDA Margins | D18: =D17/D7 -> 0.26973365 | E18: =E17/E7 -> 0.26829734 | F18: =F17/F7 -> 0.28351109 | G18: =G17/G7 -> 0.27669305 | H18: =H17/H7 -> 0.26283831 | I18: =I17/I7 -> 0.26690688 | J18: =J17/J7 -> 0.26400573 | K18: =K17/K7 -> 0.27113223 | L18: =L17/L7 -> 0.26853936
B20: Depreciation | D20: =IFERROR('Data Sheet'!D26,0) -> 2056 | E20: =IFERROR('Data Sheet'!E26,0) -> 3529 | F20: =IFERROR('Data Sheet'!F26,0) -> 4065 | G20: =IFERROR('Data Sheet'!G26,0) -> 4604 | H20: =IFERROR('Data Sheet'!H26,0) -> 5022 | I20: =IFERROR('Data Sheet'!I26,0) -> 4985 | J20: =IFERROR('Data Sheet'!J26,0) -> 5242 | K20: =IFERROR('Data Sheet'!K26,0) -> 5560 | L20: =IFERROR(SUM('Data Sheet'!H45:K45),0) -> 5438
B21: Depreciation % Sales | D21: =D20/D7 -> 0.014037675 | E21: =E20/E7 -> 0.022485011 | F21: =F20/F7 -> 0.024759863 | G21: =G20/G7 -> 0.024009929 | H21: =H20/H7 -> 0.022274659 | I21: =I20/I7 -> 0.020693835 | J21: =J20/J7 -> 0.020530777 | K21: =K20/K7 -> 0.020822332 | L21: =L20/L7 -> 0.019712969
B23: EBIT | D23: =D17-D20 -> 37450 | E23: =E17-E20 -> 38580 | F23: =F17-F20 -> 42481 | G23: =G17-G20 -> 48453 | H23: =H17-H20 -> 54237 | I23: =I17-I20 -> 59311 | J23: =J17-J20 -> 62165 | K23: =K17-K20 -> 66838 | L23: =L17-L20 -> 68641
B24: EBIT Margin | D24: =D23/D7 -> 0.25569598 | E24: =E23/E7 -> 0.24581233 | F24: =F23/F7 -> 0.25875123 | G24: =G23/G7 -> 0.25268313 | H24: =H23/H7 -> 0.24056365 | I24: =I23/I7 -> 0.24621305 | J24: =J23/J7 -> 0.24347496 | K24: =K23/K7 -> 0.2503099 | L24: =L23/L7 -> 0.24882639
B26: Interest | D26: =IFERROR('Data Sheet'!D27,0) -> 198 | E26: =IFERROR('Data Sheet'!E27,0) -> 924 | F26: =IFERROR('Data Sheet'!F27,0) -> 637 | G26: =IFERROR('Data Sheet'!G27,0) -> 784 | H26: =IFERROR('Data Sheet'!H27,0) -> 779 | I26: =IFERROR('Data Sheet'!I27,0) -> 778 | J26: =IFERROR('Data Sheet'!J27,0) -> 796 | K26: =IFERROR('Data Sheet'!K27,0) -> 1227 | L26: =IFERROR(SUM('Data Sheet'!H46:K46),0) -> 1305
B27: Interest % Sales | D27: =D26/D7 -> 0.0013518773 | E27: =E26/E7 -> 0.0058872627 | F27: =F26/F7 -> 0.0038799588 | G27: =G26/G7 -> 0.0040885718 | H27: =H26/H7 -> 0.003455189 | I27: =I26/I7 -> 0.0032296497 | J27: =J26/J7 -> 0.0031176074 | K27: =K26/K7 -> 0.0045951442 | L27: =L26/L7 -> 0.0047306776
B29: Other Income | D29: =IFERROR('Data Sheet'!D25,0) -> 4311 | E29: =IFERROR('Data Sheet'!E25,0) -> 4592 | F29: =IFERROR('Data Sheet'!F25,0) -> 1916 | G29: =IFERROR('Data Sheet'!G25,0) -> 4018 | H29: =IFERROR('Data Sheet'!H25,0) -> 3449 | I29: =IFERROR('Data Sheet'!I25,0) -> 3464 | J29: =IFERROR('Data Sheet'!J25,0) -> 3962 | K29: =IFERROR('Data Sheet'!K25,0) -> -124 | L29: =IFERROR(SUM('Data Sheet'!H44:K44),0) -> -884
B30: Other Income % Sales | D30: =D29/D7 -> 0.029434055 | E30: =E29/E7 -> 0.029257912 | F30: =F29/F7 -> 0.011670331 | G30: =G29/G7 -> 0.020953931 | H30: =H29/H7 -> 0.015297749 | I30: =I29/I7 -> 0.014379828 | J30: =J29/J7 -> 0.015517539 | K30: =K29/K7 -> -0.00046438295 | L30: =L29/L7 -> -0.0032045357
B32: EBT | D32: =(D23+D29)-D26 -> 41563 | E32: =(E23+E29)-E26 -> 42248 | F32: =(F23+F29)-F26 -> 43760 | G32: =(G23+G29)-G26 -> 51687 | H32: =(H23+H29)-H26 -> 56907 | I32: =(I23+I29)-I26 -> 61997 | J32: =(J23+J29)-J26 -> 65331 | K32: =(K23+K29)-K26 -> 65487 | L32: =(L23+L29)-L26 -> 66452
B33: EBT Margin | D33: =D32/D7 -> 0.28377816 | E33: =E32/E7 -> 0.26918298 | F33: =F32/F7 -> 0.2665416 | G33: =G32/G7 -> 0.26954848 | H33: =H32/H7 -> 0.25240621 | I33: =I32/I7 -> 0.25736323 | J33: =J32/J7 -> 0.25587489 | K33: =K32/K7 -> 0.24525037 | L33: =L32/L7 -> 0.24089118
B35: TAX | D35: =IFERROR('Data Sheet'!D29,0) -> 10001 | E35: =IFERROR('Data Sheet'!E29,0) -> 9801 | F35: =IFERROR('Data Sheet'!F29,0) -> 11198 | G35: =IFERROR('Data Sheet'!G29,0) -> 13238 | H35: =IFERROR('Data Sheet'!H29,0) -> 14604 | I35: =IFERROR('Data Sheet'!I29,0) -> 15898 | J35: =IFERROR('Data Sheet'!J29,0) -> 16534 | K35: =IFERROR('Data Sheet'!K29,0) -> 16033 | L35: =IFERROR(SUM('Data Sheet'!H48:K48),0) -> 16397
B36: Tax % sales | D36: =D35/D7 -> 0.068283457 | E36: =E35/E7 -> 0.062447037 | F36: =F35/F7 -> 0.068206874 | G36: =G35/G7 -> 0.06903637 | H36: =H35/H7 -> 0.064774814 | I36: =I35/I7 -> 0.065996106 | J36: =J35/J7 -> 0.064756936 | K36: =K35/K7 -> 0.060043967 | L36: =L35/L7 -> 0.059439786
B38: Net Profit | D38: =D32-D35 -> 31562 | E38: =E32-E35 -> 32447 | F38: =F32-F35 -> 32562 | G38: =G32-G35 -> 38449 | H38: =H32-H35 -> 42303 | I38: =I32-I35 -> 46099 | J38: =J32-J35 -> 48797 | K38: =K32-K35 -> 49454 | L38: =L32-L35 -> 50055
B39: Net Margin | D39: =D38/D7 -> 0.2154947 | E39: =E38/E7 -> 0.20673595 | F39: =F38/F7 -> 0.19833472 | G39: =G38/G7 -> 0.20051211 | H39: =H38/H7 -> 0.1876314 | I39: =I38/I7 -> 0.19136712 | J39: =J38/J7 -> 0.19111795 | K39: =K38/K7 -> 0.18520641 | L39: =L38/L7 -> 0.18145139
B41: No of Shares | D41: =IFERROR('Data Sheet'!D93,0) -> 375.24 | E41: =IFERROR('Data Sheet'!E93,0) -> 375.24 | F41: =IFERROR('Data Sheet'!F93,0) -> 369.91 | G41: =IFERROR('Data Sheet'!G93,0) -> 365.91 | H41: =IFERROR('Data Sheet'!H93,0) -> 365.91 | I41: =IFERROR('Data Sheet'!I93,0) -> 361.81 | J41: =IFERROR('Data Sheet'!J93,0) -> 361.81 | K41: =IFERROR('Data Sheet'!K93,0) -> 361.81
B43: EPS | D43: =D38/D41 -> 84.111502 | E43: =E38/E41 -> 86.469993 | F43: =F38/F41 -> 88.026817 | G43: =G38/G41 -> 105.07775 | H43: =H38/H41 -> 115.6104 | I43: =I38/I41 -> 127.41218 | J43: =J38/J41 -> 134.86913 | K43: =K38/K41 -> 136.685
B44: EPS Growth | D44: - | E44: =E43/D43-1 -> 0.028040048 | F44: =F43/E43-1 -> 0.01800422 | G44: =G43/F43-1 -> 0.19370158 | H44: =H43/G43-1 -> 0.10023668 | I44: =I43/H43-1 -> 0.10208236 | J44: =J43/I43-1 -> 0.058526215 | K44: =K43/J43-1 -> 0.013463942
B46: Divident Per Share | D46: =IFERROR('Data Sheet'!D31/'Historicail Financial Statement'!D41,0) -> 29.980812 | E46: =IFERROR('Data Sheet'!E31/'Historicail Financial Statement'!E41,0) -> 72.95331 | F46: =IFERROR('Data Sheet'!F31/'Historicail Financial Statement'!F41,0) -> 38.009245 | G46: =IFERROR('Data Sheet'!G31/'Historicail Financial Statement'!G41,0) -> 43.010576 | H46: =IFERROR('Data Sheet'!H31/'Historicail Financial Statement'!H41,0) -> 115.02829 | I46: =IFERROR('Data Sheet'!I31/'Historicail Financial Statement'!I41,0) -> 73.038335 | J46: =IFERROR('Data Sheet'!J31/'Historicail Financial Statement'!J41,0) -> 126.06617 | K46: =IFERROR('Data Sheet'!K31/'Historicail Financial Statement'!K41,0) -> 110.05777
B47: Divident Pay Out Ratio | D47: =D46/D43 -> 0.35644129 | E47: =E46/E43 -> 0.84368355 | F47: =F46/F43 -> 0.43179166 | G47: =G46/G43 -> 0.40932144 | H47: =H46/H43 -> 0.9949649 | I47: =I46/I43 -> 0.57324454 | J47: =J46/J43 -> 0.93472959 | K47: =K46/K43 -> 0.8051927
B49: Retaind Ernings | D49: =IFERROR(IF(D43>D46,1-D47,0),0) -> 0.64355871 | E49: =IFERROR(IF(E43>E46,1-E47,0),0) -> 0.15631645 | F49: =IFERROR(IF(F43>F46,1-F47,0),0) -> 0.56820834 | G49: =IFERROR(IF(G43>G46,1-G47,0),0) -> 0.59067856 | H49: =IFERROR(IF(H43>H46,1-H47,0),0) -> 0.0050351039 | I49: =IFERROR(IF(I43>I46,1-I47,0),0) -> 0.42675546 | J49: =IFERROR(IF(J43>J46,1-J47,0),0) -> 0.065270406 | K49: =IFERROR(IF(K43>K46,1-K47,0),0) -> 0.1948073
A51: # | B51: ="Balance Sheet - "&'Data Sheet'!B1 -> Balance Sheet - TATA CONSULTANCY SERVICES LTD
B53: Equity Share Capital | D53: =IFERROR('Data Sheet'!D57,0) -> 375 | E53: =IFERROR('Data Sheet'!E57,0) -> 375 | F53: =IFERROR('Data Sheet'!F57,0) -> 370 | G53: =IFERROR('Data Sheet'!G57,0) -> 366 | H53: =IFERROR('Data Sheet'!H57,0) -> 366 | I53: =IFERROR('Data Sheet'!I57,0) -> 362 | J53: =IFERROR('Data Sheet'!J57,0) -> 362 | K53: =IFERROR('Data Sheet'!K57,0) -> 362
B54: Reserves | D54: =IFERROR('Data Sheet'!D58,0) -> 89071 | E54: =IFERROR('Data Sheet'!E58,0) -> 83751 | F54: =IFERROR('Data Sheet'!F58,0) -> 86063 | G54: =IFERROR('Data Sheet'!G58,0) -> 88773 | H54: =IFERROR('Data Sheet'!H58,0) -> 90058 | I54: =IFERROR('Data Sheet'!I58,0) -> 90127 | J54: =IFERROR('Data Sheet'!J58,0) -> 94394 | K54: =IFERROR('Data Sheet'!K58,0) -> 106878
B55: Borrowings | D55: =IFERROR('Data Sheet'!D59,0) -> 62 | E55: =IFERROR('Data Sheet'!E59,0) -> 8174 | F55: =IFERROR('Data Sheet'!F59,0) -> 7795 | G55: =IFERROR('Data Sheet'!G59,0) -> 7818 | H55: =IFERROR('Data Sheet'!H59,0) -> 7688 | I55: =IFERROR('Data Sheet'!I59,0) -> 8021 | J55: =IFERROR('Data Sheet'!J59,0) -> 9392 | K55: =IFERROR('Data Sheet'!K59,0) -> 11283
B56: Other Liabilities | D56: =IFERROR('Data Sheet'!D60,0) -> 24393 | E56: =IFERROR('Data Sheet'!E60,0) -> 27827 | F56: =IFERROR('Data Sheet'!F60,0) -> 35764 | G56: =IFERROR('Data Sheet'!G60,0) -> 43967 | H56: =IFERROR('Data Sheet'!H60,0) -> 44747 | I56: =IFERROR('Data Sheet'!I60,0) -> 46962 | J56: =IFERROR('Data Sheet'!J60,0) -> 54501 | K56: =IFERROR('Data Sheet'!K60,0) -> 62644
B57: Total Liabilities. | D57: =SUM(D53:D56) -> 113901 | E57: =SUM(E53:E56) -> 120127 | F57: =SUM(F53:F56) -> 129992 | G57: =SUM(G53:G56) -> 140924 | H57: =SUM(H53:H56) -> 142859 | I57: =SUM(I53:I56) -> 145472 | J57: =SUM(J53:J56) -> 158649 | K57: =SUM(K53:K56) -> 181167
B59: Fixed Assets &Net Block | D59: =IFERROR('Data Sheet'!D62,0) -> 12290 | E59: =IFERROR('Data Sheet'!E62,0) -> 20928 | F59: =IFERROR('Data Sheet'!F62,0) -> 21021 | G59: =IFERROR('Data Sheet'!G62,0) -> 21298 | H59: =IFERROR('Data Sheet'!H62,0) -> 20515 | I59: =IFERROR('Data Sheet'!I62,0) -> 19604 | J59: =IFERROR('Data Sheet'!J62,0) -> 23053 | K59: =IFERROR('Data Sheet'!K62,0) -> 31343
B60: Capital Work in Progress | D60: =IFERROR('Data Sheet'!D63,0) -> 963 | E60: =IFERROR('Data Sheet'!E63,0) -> 906 | F60: =IFERROR('Data Sheet'!F63,0) -> 926 | G60: =IFERROR('Data Sheet'!G63,0) -> 1205 | H60: =IFERROR('Data Sheet'!H63,0) -> 1234 | I60: =IFERROR('Data Sheet'!I63,0) -> 1564 | J60: =IFERROR('Data Sheet'!J63,0) -> 1546 | K60: =IFERROR('Data Sheet'!K63,0) -> 2665
B61: Investments | D61: =IFERROR('Data Sheet'!D64,0) -> 29330 | E61: =IFERROR('Data Sheet'!E64,0) -> 26356 | F61: =IFERROR('Data Sheet'!F64,0) -> 29373 | G61: =IFERROR('Data Sheet'!G64,0) -> 30485 | H61: =IFERROR('Data Sheet'!H64,0) -> 37163 | I61: =IFERROR('Data Sheet'!I64,0) -> 31762 | J61: =IFERROR('Data Sheet'!J64,0) -> 30964 | K61: =IFERROR('Data Sheet'!K64,0) -> 33988
B62: Other Assets | D62: ='Data Sheet'!D75 -> 31114 | E62: ='Data Sheet'!E75 -> 31734 | F62: ='Data Sheet'!F75 -> 39256 | G62: ='Data Sheet'!G75 -> 27885 | H62: ='Data Sheet'!H75 -> 22933 | I62: ='Data Sheet'!I75 -> 25651 | J62: ='Data Sheet'!J75 -> 28556 | K62: ='Data Sheet'!K75 -> 32520
B63: Total Non Current Assets | D63: =SUM(D59:D62) -> 73697 | E63: =SUM(E59:E62) -> 79924 | F63: =SUM(F59:F62) -> 90576 | G63: =SUM(G59:G62) -> 80873 | H63: =SUM(H59:H62) -> 81845 | I63: =SUM(I59:I62) -> 78581 | J63: =SUM(J59:J62) -> 84119 | K63: =SUM(K59:K62) -> 100516
B65: Receivables | D65: =IFERROR('Data Sheet'!D67,0) -> 27346 | E65: =IFERROR('Data Sheet'!E67,0) -> 30532 | F65: =IFERROR('Data Sheet'!F67,0) -> 30079 | G65: =IFERROR('Data Sheet'!G67,0) -> 41810 | H65: =IFERROR('Data Sheet'!H67,0) -> 49954 | I65: =IFERROR('Data Sheet'!I67,0) -> 53577 | J65: =IFERROR('Data Sheet'!J67,0) -> 59046 | K65: =IFERROR('Data Sheet'!K67,0) -> 67714
B66: Inventory | D66: =IFERROR('Data Sheet'!D68,0) -> 10 | E66: =IFERROR('Data Sheet'!E68,0) -> 5 | F66: =IFERROR('Data Sheet'!F68,0) -> 8 | G66: =IFERROR('Data Sheet'!G68,0) -> 20 | H66: =IFERROR('Data Sheet'!H68,0) -> 28 | I66: =IFERROR('Data Sheet'!I68,0) -> 28 | J66: =IFERROR('Data Sheet'!J68,0) -> 21 | K66: =IFERROR('Data Sheet'!K68,0) -> 29
B67: Cash & Bank | D67: =IFERROR('Data Sheet'!D69,0) -> 12848 | E67: =IFERROR('Data Sheet'!E69,0) -> 9666 | F67: =IFERROR('Data Sheet'!F69,0) -> 9329 | G67: =IFERROR('Data Sheet'!G69,0) -> 18221 | H67: =IFERROR('Data Sheet'!H69,0) -> 11032 | I67: =IFERROR('Data Sheet'!I69,0) -> 13286 | J67: =IFERROR('Data Sheet'!J69,0) -> 15463 | K67: =IFERROR('Data Sheet'!K69,0) -> 12908
B68: Total Current Assets | D68: =SUM(D65:D67) -> 40204 | E68: =SUM(E65:E67) -> 40203 | F68: =SUM(F65:F67) -> 39416 | G68: =SUM(G65:G67) -> 60051 | H68: =SUM(H65:H67) -> 61014 | I68: =SUM(I65:I67) -> 66891 | J68: =SUM(J65:J67) -> 74530 | K68: =SUM(K65:K67) -> 80651
B70: Total Assets | D70: =D63+D68 -> 113901 | E70: =E63+E68 -> 120127 | F70: =F63+F68 -> 129992 | G70: =G63+G68 -> 140924 | H70: =H63+H68 -> 142859 | I70: =I63+I68 -> 145472 | J70: =J63+J68 -> 158649 | K70: =K63+K68 -> 181167
B72: Check | D72: =D57=D70 -> TRUE | E72: =E57=E70 -> TRUE | F72: =F57=F70 -> TRUE | G72: =G57=G70 -> TRUE | H72: =H57=H70 -> TRUE | I72: =I57=I70 -> TRUE | J72: =J57=J70 -> TRUE | K72: =K57=K70 -> TRUE
A74: # | B74: ="Cash Flow Statement-"&'Data Sheet'!B1 -> Cash Flow Statement-TATA CONSULTANCY SERVICES LTD
B76: Cash from Operating Activity | D76: =IFERROR('Data Sheet'!D82,0) -> 28593 | E76: =IFERROR('Data Sheet'!E82,0) -> 32369 | F76: =IFERROR('Data Sheet'!F82,0) -> 38802 | G76: =IFERROR('Data Sheet'!G82,0) -> 39949 | H76: =IFERROR('Data Sheet'!H82,0) -> 41965 | I76: =IFERROR('Data Sheet'!I82,0) -> 44338 | J76: =IFERROR('Data Sheet'!J82,0) -> 48908 | K76: =IFERROR('Data Sheet'!K82,0) -> 52094
B78: Cash from Investing Activity | D78: =IFERROR('Data Sheet'!D83,0) -> 1645 | E78: =IFERROR('Data Sheet'!E83,0) -> 8968 | F78: =IFERROR('Data Sheet'!F83,0) -> -7956 | G78: =IFERROR('Data Sheet'!G83,0) -> -738 | H78: =IFERROR('Data Sheet'!H83,0) -> 548 | I78: =IFERROR('Data Sheet'!I83,0) -> 6091 | J78: =IFERROR('Data Sheet'!J83,0) -> -2144 | K78: =IFERROR('Data Sheet'!K83,0) -> -11886
B80: Cash from Financing Activity | D80: =IFERROR('Data Sheet'!D84,0) -> -27897 | E80: =IFERROR('Data Sheet'!E84,0) -> -39915 | F80: =IFERROR('Data Sheet'!F84,0) -> -32634 | G80: =IFERROR('Data Sheet'!G84,0) -> -33581 | H80: =IFERROR('Data Sheet'!H84,0) -> -47878 | I80: =IFERROR('Data Sheet'!I84,0) -> -48536 | J80: =IFERROR('Data Sheet'!J84,0) -> -47438 | K80: =IFERROR('Data Sheet'!K84,0) -> -42133
B82: Net Cash Flow | D82: =SUM(D76:D80) -> 2341 | E82: =SUM(E76:E80) -> 1422 | F82: =SUM(F76:F80) -> -1788 | G82: =SUM(G76:G80) -> 5630 | H82: =SUM(H76:H80) -> -5365 | I82: =SUM(I76:I80) -> 1893 | J82: =SUM(J76:J80) -> -674 | K82: =SUM(K76:K80) -> -1925

Sheet Ratio Analysis
B5: ="Rario Analysis-"&'Data Sheet'!B1 -> Rario Analysis-TATA CONSULTANCY SERVICES LTD
B6: Years | D6: ='Historicail Financial Statement'!D4 -> 43555 | E6: ='Historicail Financial Statement'!E4 -> 43921 | F6: ='Historicail Financial Statement'!F4 -> 44286 | G6: ='Historicail Financial Statement'!G4 -> 44651 | H6: ='Historicail Financial Statement'!H4 -> 45016 | I6: ='Historicail Financial Statement'!I4 -> 45382 | J6: ='Historicail Financial Statement'!J4 -> 45747 | K6: ='Historicail Financial Statement'!K4 -> 46112 | L6: Trand Lein | M6: Average | N6: Median
B8: SalesGrowth | D8: ='Historicail Financial Statement'!D8 -> - | E8: ='Historicail Financial Statement'!E8 -> 0.071594874 | F8: ='Historicail Financial Statement'!F8 -> 0.046053177 | G8: ='Historicail Financial Statement'!G8 -> 0.16797115 | H8: ='Historicail Financial Statement'!H8 -> 0.17576687 | I8: ='Historicail Financial Statement'!I8 -> 0.068460645 | J8: ='Historicail Financial Statement'!J8 -> 0.059906265 | K8: ='Historicail Financial Statement'!K8 -> 0.04581238 | M8: =AVERAGE(E8:K8) -> 0.090795052 | N8: =MEDIAN(E8:K8) -> 0.068460645
B9: EBITDA Growth | E9: ='Historicail Financial Statement'!E17/'Historicail Financial Statement'!D17-1 -> 0.065888726 | F9: ='Historicail Financial Statement'!F17/'Historicail Financial Statement'!E17-1 -> 0.1053694 | G9: ='Historicail Financial Statement'!G17/'Historicail Financial Statement'!F17-1 -> 0.13988313 | H9: ='Historicail Financial Statement'!H17/'Historicail Financial Statement'!G17-1 -> 0.11689315 | I9: ='Historicail Financial Statement'!I17/'Historicail Financial Statement'!H17-1 -> 0.084999747 | J9: ='Historicail Financial Statement'!J17/'Historicail Financial Statement'!I17-1 -> 0.048385592 | K9: ='Historicail Financial Statement'!K17/'Historicail Financial Statement'!J17-1 -> 0.074042755 | M9: =AVERAGE(E9:K9) -> 0.090780357 | N9: =MEDIAN(E9:K9) -> 0.084999747
B10: EBIT Growth | E10: ='Historicail Financial Statement'!E23/'Historicail Financial Statement'!D23-1 -> 0.030173565 | F10: ='Historicail Financial Statement'!F23/'Historicail Financial Statement'!E23-1 -> 0.10111457 | G10: ='Historicail Financial Statement'!G23/'Historicail Financial Statement'!F23-1 -> 0.14058049 | H10: ='Historicail Financial Statement'!H23/'Historicail Financial Statement'!G23-1 -> 0.11937341 | I10: ='Historicail Financial Statement'!I23/'Historicail Financial Statement'!H23-1 -> 0.093552372 | J10: ='Historicail Financial Statement'!J23/'Historicail Financial Statement'!I23-1 -> 0.048119236 | K10: ='Historicail Financial Statement'!K23/'Historicail Financial Statement'!J23-1 -> 0.075170916 | M10: =AVERAGE(E10:K10) -> 0.086869223 | N10: =MEDIAN(E10:K10) -> 0.093552372
B11: Net Profit Growth | E11: ='Historicail Financial Statement'!E38/'Historicail Financial Statement'!D38-1 -> 0.028040048 | F11: ='Historicail Financial Statement'!F38/'Historicail Financial Statement'!E38-1 -> 0.0035442414 | G11: ='Historicail Financial Statement'!G38/'Historicail Financial Statement'!F38-1 -> 0.18079356 | H11: ='Historicail Financial Statement'!H38/'Historicail Financial Statement'!G38-1 -> 0.10023668 | I11: ='Historicail Financial Statement'!I38/'Historicail Financial Statement'!H38-1 -> 0.089733589 | J11: ='Historicail Financial Statement'!J38/'Historicail Financial Statement'!I38-1 -> 0.058526215 | K11: ='Historicail Financial Statement'!K38/'Historicail Financial Statement'!J38-1 -> 0.013463942 | M11: =AVERAGE(E11:K11) -> 0.067762611 | N11: =MEDIAN(E11:K11) -> 0.058526215
B12: Dividend Growth | E12: ='Historicail Financial Statement'!E46/'Historicail Financial Statement'!D46-1 -> 1.4333333 | F12: ='Historicail Financial Statement'!F46/'Historicail Financial Statement'!E46-1 -> -0.47899217 | G12: ='Historicail Financial Statement'!G46/'Historicail Financial Statement'!F46-1 -> 0.13158196 | H12: ='Historicail Financial Statement'!H46/'Historicail Financial Statement'!G46-1 -> 1.6744186 | I12: ='Historicail Financial Statement'!I46/'Historicail Financial Statement'!H46-1 -> -0.36504022 | J12: ='Historicail Financial Statement'!J46/'Historicail Financial Statement'!I46-1 -> 0.7260274 | K12: ='Historicail Financial Statement'!K46/'Historicail Financial Statement'!J46-1 -> -0.12698413 | M12: =AVERAGE(E12:K12) -> 0.42776354 | N12: =MEDIAN(E12:K12) -> 0.13158196
B14: Gross Margin | D14: ='Historicail Financial Statement'!D13 -> 0.98450121 | E14: ='Historicail Financial Statement'!E13 -> 0.9878623 | F14: ='Historicail Financial Statement'!F13 -> 0.99109498 | G14: ='Historicail Financial Statement'!G13 -> 0.99393494 | H14: ='Historicail Financial Statement'!H13 -> 0.99165698 | I14: ='Historicail Financial Statement'!I13 -> 0.98463218 | J14: ='Historicail Financial Statement'!J13 -> 0.95437953 | K14: ='Historicail Financial Statement'!K13 -> 0.98352564 | M14: =AVERAGE(E14:K14) -> 0.98386951 | N14: =MEDIAN(E14:K14) -> 0.9878623
B15: EBITDA Margin | D15: ='Historicail Financial Statement'!D18 -> 0.26973365 | E15: ='Historicail Financial Statement'!E18 -> 0.26829734 | F15: ='Historicail Financial Statement'!F18 -> 0.28351109 | G15: ='Historicail Financial Statement'!G18 -> 0.27669305 | H15: ='Historicail Financial Statement'!H18 -> 0.26283831 | I15: ='Historicail Financial Statement'!I18 -> 0.26690688 | J15: ='Historicail Financial Statement'!J18 -> 0.26400573 | K15: ='Historicail Financial Statement'!K18 -> 0.27113223 | M15: =AVERAGE(E15:K15) -> 0.27048352 | N15: =MEDIAN(E15:K15) -> 0.26829734
B16: EBIT Margin | D16: ='Historicail Financial Statement'!D24 -> 0.25569598 | E16: ='Historicail Financial Statement'!E24 -> 0.24581233 | F16: ='Historicail Financial Statement'!F24 -> 0.25875123 | G16: ='Historicail Financial Statement'!G24 -> 0.25268313 | H16: ='Historicail Financial Statement'!H24 -> 0.24056365 | I16: ='Historicail Financial Statement'!I24 -> 0.24621305 | J16: ='Historicail Financial Statement'!J24 -> 0.24347496 | K16: ='Historicail Financial Statement'!K24 -> 0.2503099 | M16: =AVERAGE(E16:K16) -> 0.24825832 | N16: =MEDIAN(E16:K16) -> 0.24621305
B17: EBT Margin | D17: ='Historicail Financial Statement'!D33 -> 0.28377816 | E17: ='Historicail Financial Statement'!E33 -> 0.26918298 | F17: ='Historicail Financial Statement'!F33 -> 0.2665416 | G17: ='Historicail Financial Statement'!G33 -> 0.26954848 | H17: ='Historicail Financial Statement'!H33 -> 0.25240621 | I17: ='Historicail Financial Statement'!I33 -> 0.25736323 | J17: ='Historicail Financial Statement'!J33 -> 0.25587489 | K17: ='Historicail Financial Statement'!K33 -> 0.24525037 | M17: =AVERAGE(E17:K17) -> 0.25945254 | N17: =MEDIAN(E17:K17) -> 0.25736323
B18: Net Profit Margin | D18: ='Historicail Financial Statement'!D39 -> 0.2154947 | E18: ='Historicail Financial Statement'!E39 -> 0.20673595 | F18: ='Historicail Financial Statement'!F39 -> 0.19833472 | G18: ='Historicail Financial Statement'!G39 -> 0.20051211 | H18: ='Historicail Financial Statement'!H39 -> 0.1876314 | I18: ='Historicail Financial Statement'!I39 -> 0.19136712 | J18: ='Historicail Financial Statement'!J39 -> 0.19111795 | K18: ='Historicail Financial Statement'!K39 -> 0.18520641 | M18: =AVERAGE(E18:K18) -> 0.19441509 | N18: =MEDIAN(E18:K18) -> 0.19136712
B20: SalesExpenses%Sales | D20: ='Historicail Financial Statement'!D16 -> 0.71476755 | E20: ='Historicail Financial Statement'!E16 -> 0.71956495 | F20: ='Historicail Financial Statement'!F16 -> 0.70758389 | G20: ='Historicail Financial Statement'!G16 -> 0.71724188 | H20: ='Historicail Financial Statement'!H16 -> 0.72881867 | I20: ='Historicail Financial Statement'!I16 -> 0.7177253 | J20: ='Historicail Financial Statement'!J16 -> 0.6903738 | K20: ='Historicail Financial Statement'!K16 -> 0.71239341 | M20: =AVERAGE(E20:K20) -> 0.71338599 | N20: =MEDIAN(E20:K20) -> 0.71724188
B21: Depreciation%Sales | D21: ='Historicail Financial Statement'!D21 -> 0.014037675 | E21: ='Historicail Financial Statement'!E21 -> 0.022485011 | F21: ='Historicail Financial Statement'!F21 -> 0.024759863 | G21: ='Historicail Financial Statement'!G21 -> 0.024009929 | H21: ='Historicail Financial Statement'!H21 -> 0.022274659 | I21: ='Historicail Financial Statement'!I21 -> 0.020693835 | J21: ='Historicail Financial Statement'!J21 -> 0.020530777 | K21: ='Historicail Financial Statement'!K21 -> 0.020822332 | M21: =AVERAGE(E21:K21) -> 0.022225201 | N21: =MEDIAN(E21:K21) -> 0.022274659
B22: OperatingIncome%Sales | D22: =D17 -> 0.28377816 | E22: =E17 -> 0.26918298 | F22: =F17 -> 0.2665416 | G22: =G17 -> 0.26954848 | H22: =H17 -> 0.25240621 | I22: =I17 -> 0.25736323 | J22: =J17 -> 0.25587489 | K22: =K17 -> 0.24525037 | M22: =AVERAGE(E22:K22) -> 0.25945254 | N22: =MEDIAN(E22:K22) -> 0.25736323
B24: Return on Capital Employed | D24: ='Historicail Financial Statement'!D23/SUM('Historicail Financial Statement'!D53:D55) -> 0.41839836 | E24: ='Historicail Financial Statement'!E23/SUM('Historicail Financial Statement'!E53:E55) -> 0.41798483 | F24: ='Historicail Financial Statement'!F23/SUM('Historicail Financial Statement'!F53:F55) -> 0.45083202 | G24: ='Historicail Financial Statement'!G23/SUM('Historicail Financial Statement'!G53:G55) -> 0.499737 | H24: ='Historicail Financial Statement'!H23/SUM('Historicail Financial Statement'!H53:H55) -> 0.552807 | I24: ='Historicail Financial Statement'!I23/SUM('Historicail Financial Statement'!I53:I55) -> 0.60208101 | J24: ='Historicail Financial Statement'!J23/SUM('Historicail Financial Statement'!J53:J55) -> 0.59689096 | K24: ='Historicail Financial Statement'!K23/SUM('Historicail Financial Statement'!K53:K55) -> 0.5639243 | M24: =AVERAGE(E24:K24) -> 0.52632245 | N24: =MEDIAN(E24:K24) -> 0.552807
B25: Retained Earnings% | D25: ='Historicail Financial Statement'!D49 -> 0.64355871 | E25: ='Historicail Financial Statement'!E49 -> 0.15631645 | F25: ='Historicail Financial Statement'!F49 -> 0.56820834 | G25: ='Historicail Financial Statement'!G49 -> 0.59067856 | H25: ='Historicail Financial Statement'!H49 -> 0.0050351039 | I25: ='Historicail Financial Statement'!I49 -> 0.42675546 | J25: ='Historicail Financial Statement'!J49 -> 0.065270406 | K25: ='Historicail Financial Statement'!K49 -> 0.1948073 | M25: =AVERAGE(E25:K25) -> 0.28672452 | N25: =MEDIAN(E25:K25) -> 0.1948073
B26: Return on Equity% | D26: ='Historicail Financial Statement'!D38/SUM('Historicail Financial Statement'!D53:D54) -> 0.35286094 | E26: ='Historicail Financial Statement'!E38/SUM('Historicail Financial Statement'!E53:E54) -> 0.38569527 | F26: ='Historicail Financial Statement'!F38/SUM('Historicail Financial Statement'!F53:F54) -> 0.37673111 | G26: ='Historicail Financial Statement'!G38/SUM('Historicail Financial Statement'!G53:G54) -> 0.43133757 | H26: ='Historicail Financial Statement'!H38/SUM('Historicail Financial Statement'!H53:H54) -> 0.46782934 | I26: ='Historicail Financial Statement'!I38/SUM('Historicail Financial Statement'!I53:I54) -> 0.50944314 | J26: ='Historicail Financial Statement'!J38/SUM('Historicail Financial Statement'!J53:J54) -> 0.5149753 | K26: ='Historicail Financial Statement'!K38/SUM('Historicail Financial Statement'!K53:K54) -> 0.46115256 | M26: =AVERAGE(E26:K26) -> 0.4495949 | N26: =MEDIAN(E26:K26) -> 0.46115256
B27: Self Sustained Growth Rate | D27: =D25*D26 -> 0.22708673 | E27: =E25*E26 -> 0.060290517 | F27: =F25*F26 -> 0.21406176 | G27: =G25*G26 -> 0.25478186 | H27: =H25*H26 -> 0.0023555693 | I27: =I25*I26 -> 0.21740764 | J27: =J25*J26 -> 0.033612647 | K27: =K25*K26 -> 0.089835882 | M27: =AVERAGE(E27:K27) -> 0.12462084 | N27: =MEDIAN(E27:K27) -> 0.089835882
B28: Interest Coverage Ratio | D28: ='Historicail Financial Statement'!D23/'Historicail Financial Statement'!D26 -> 189.14141 | E28: ='Historicail Financial Statement'!E23/'Historicail Financial Statement'!E26 -> 41.753247 | F28: ='Historicail Financial Statement'!F23/'Historicail Financial Statement'!F26 -> 66.689168 | G28: ='Historicail Financial Statement'!G23/'Historicail Financial Statement'!G26 -> 61.802296 | H28: ='Historicail Financial Statement'!H23/'Historicail Financial Statement'!H26 -> 69.623877 | I28: ='Historicail Financial Statement'!I23/'Historicail Financial Statement'!I26 -> 76.235219 | J28: ='Historicail Financial Statement'!J23/'Historicail Financial Statement'!J26 -> 78.096734 | K28: ='Historicail Financial Statement'!K23/'Historicail Financial Statement'!K26 -> 54.472698 | M28: =AVERAGE(E28:K28) -> 64.096177 | N28: =MEDIAN(E28:K28) -> 66.689168
B30: Debtor Turnover Ratio | D30: ='Historicail Financial Statement'!D7/'Historicail Financial Statement'!D65 -> 5.3559204 | E30: ='Historicail Financial Statement'!E7/'Historicail Financial Statement'!E65 -> 5.1404756 | F30: ='Historicail Financial Statement'!F7/'Historicail Financial Statement'!F65 -> 5.4581934 | G30: ='Historicail Financial Statement'!G7/'Historicail Financial Statement'!G65 -> 4.5863191 | H30: ='Historicail Financial Statement'!H7/'Historicail Financial Statement'!H65 -> 4.5133122 | I30: ='Historicail Financial Statement'!I7/'Historicail Financial Statement'!I65 -> 4.4962017 | J30: ='Historicail Financial Statement'!J7/'Historicail Financial Statement'!J65 -> 4.324154 | K30: ='Historicail Financial Statement'!K7/'Historicail Financial Statement'!K65 -> 3.9433647 | M30: =AVERAGE(E30:K30) -> 4.6374315 | N30: =MEDIAN(E30:K30) -> 4.5133122
B31: Creditor Turnover Ratio | D31: ='Historicail Financial Statement'!D7/'Historicail Financial Statement'!D56 -> 6.0043045 | E31: ='Historicail Financial Statement'!E7/'Historicail Financial Statement'!E56 -> 5.6401696 | F31: ='Historicail Financial Statement'!F7/'Historicail Financial Statement'!F56 -> 4.5905659 | G31: ='Historicail Financial Statement'!G7/'Historicail Financial Statement'!G56 -> 4.3613164 | H31: ='Historicail Financial Statement'!H7/'Historicail Financial Statement'!H56 -> 5.0385054 | I31: ='Historicail Financial Statement'!I7/'Historicail Financial Statement'!I56 -> 5.1295303 | J31: ='Historicail Financial Statement'!J7/'Historicail Financial Statement'!J56 -> 4.6847581 | K31: ='Historicail Financial Statement'!K7/'Historicail Financial Statement'!K56 -> 4.2625152 | M31: =AVERAGE(E31:K31) -> 4.8153373 | N31: =MEDIAN(E31:K31) -> 4.6847581
B32: Inventory Turnover | D32: ='Historicail Financial Statement'!D7/'Historicail Financial Statement'!D66 -> 14646.3 | E32: ='Historicail Financial Statement'!E7/'Historicail Financial Statement'!E66 -> 31389.8 | F32: ='Historicail Financial Statement'!F7/'Historicail Financial Statement'!F66 -> 20522.125 | G32: ='Historicail Financial Statement'!G7/'Historicail Financial Statement'!G66 -> 9587.7 | H32: ='Historicail Financial Statement'!H7/'Historicail Financial Statement'!H66 -> 8052.0714 | I32: ='Historicail Financial Statement'!I7/'Historicail Financial Statement'!I66 -> 8603.3214 | J32: ='Historicail Financial Statement'!J7/'Historicail Financial Statement'!J66 -> 12158.286 | K32: ='Historicail Financial Statement'!K7/'Historicail Financial Statement'!K66 -> 9207.6207 | M32: =AVERAGE(E32:K32) -> 14217.275 | N32: =MEDIAN(E32:K32) -> 9587.7
B33: Fixed Asset Turnover | D33: ='Historicail Financial Statement'!D7/'Historicail Financial Statement'!D59 -> 11.91725 | E33: ='Historicail Financial Statement'!E7/'Historicail Financial Statement'!E59 -> 7.4994744 | F33: ='Historicail Financial Statement'!F7/'Historicail Financial Statement'!F59 -> 7.8101422 | G33: ='Historicail Financial Statement'!G7/'Historicail Financial Statement'!G59 -> 9.0033806 | H33: ='Historicail Financial Statement'!H7/'Historicail Financial Statement'!H59 -> 10.98991 | I33: ='Historicail Financial Statement'!I7/'Historicail Financial Statement'!I59 -> 12.287951 | J33: ='Historicail Financial Statement'!J7/'Historicail Financial Statement'!J59 -> 11.075522 | K33: ='Historicail Financial Statement'!K7/'Historicail Financial Statement'!K59 -> 8.5193185 | M33: =AVERAGE(E33:K33) -> 9.5979569 | N33: =MEDIAN(E33:K33) -> 9.0033806
B34: Capital Turnover Ratio | D34: ='Historicail Financial Statement'!D7/SUM('Historicail Financial Statement'!D53:D54) -> 1.6374461 | E34: ='Historicail Financial Statement'!E7/SUM('Historicail Financial Statement'!E53:E54) -> 1.865642 | F34: ='Historicail Financial Statement'!F7/SUM('Historicail Financial Statement'!F53:F54) -> 1.8994713 | G34: ='Historicail Financial Statement'!G7/SUM('Historicail Financial Statement'!G53:G54) -> 2.1511796 | H34: ='Historicail Financial Statement'!H7/SUM('Historicail Financial Statement'!H53:H54) -> 2.4933425 | I34: ='Historicail Financial Statement'!I7/SUM('Historicail Financial Statement'!I53:I54) -> 2.6621247 | J34: ='Historicail Financial Statement'!J7/SUM('Historicail Financial Statement'!J53:J54) -> 2.6945418 | K34: ='Historicail Financial Statement'!K7/SUM('Historicail Financial Statement'!K53:K54) -> 2.4899385 | M34: =AVERAGE(E34:K34) -> 2.32232 | N34: =MEDIAN(E34:K34) -> 2.4899385
B37: Debtor Days | D37: =365/D30 -> 68.148884 | E37: =365/E30 -> 71.005104 | F37: =365/F30 -> 66.871943 | G37: =365/G30 -> 79.58452 | H37: =365/H30 -> 80.87187 | I37: =365/I30 -> 81.179632 | J37: =365/J30 -> 84.409574 | K37: =365/K30 -> 92.560548 | M37: =AVERAGE(E37:K37) -> 79.497598 | N37: =MEDIAN(E37:K37) -> 80.87187
B38: Payable Days | D38: =365/D31 -> 60.789722 | E38: =365/E31 -> 64.714366 | F38: =365/F31 -> 79.510894 | G38: =365/G31 -> 83.690327 | H38: =365/H31 -> 72.442118 | I38: =365/I31 -> 71.156613 | J38: =365/J31 -> 77.912241 | K38: =365/K31 -> 85.630194 | M38: =AVERAGE(E38:K38) -> 76.436679 | N38: =MEDIAN(E38:K38) -> 77.912241
B39: Inventory Days | D39: =365/D32 -> 0.02492097 | E39: =365/E32 -> 0.011627981 | F39: =365/F32 -> 0.017785683 | G39: =365/G32 -> 0.03806961 | H39: =365/H32 -> 0.045329951 | I39: =365/I32 -> 0.042425475 | J39: =365/J32 -> 0.03002068 | K39: =365/K32 -> 0.039641077 | M39: =AVERAGE(E39:K39) -> 0.032128637 | N39: =MEDIAN(E39:K39) -> 0.03806961
B40: Cash Conversion Cycle | D40: =SUM(D37,D39)-D38 -> 7.3840834 | E40: =SUM(E37,E39)-E38 -> 6.3023657 | F40: =SUM(F37,F39)-F38 -> -12.621165 | G40: =SUM(G37,G39)-G38 -> -4.0677378 | H40: =SUM(H37,H39)-H38 -> 8.4750818 | I40: =SUM(I37,I39)-I38 -> 10.065444 | J40: =SUM(J37,J39)-J38 -> 6.5273535 | K40: =SUM(K37,K39)-K38 -> 6.9699949 | M40: =AVERAGE(E40:K40) -> 3.0930482 | N40: =MEDIAN(E40:K40) -> 6.5273535
B42: CFO/Sales | D42: ='Historicail Financial Statement'!D76/'Historicail Financial Statement'!D7 -> 0.19522337 | E42: ='Historicail Financial Statement'!E76/'Historicail Financial Statement'!E7 -> 0.20623897 | F42: ='Historicail Financial Statement'!F76/'Historicail Financial Statement'!F7 -> 0.23634248 | G42: ='Historicail Financial Statement'!G76/'Historicail Financial Statement'!G7 -> 0.20833464 | H42: ='Historicail Financial Statement'!H76/'Historicail Financial Statement'!H7 -> 0.18613223 | I42: ='Historicail Financial Statement'!I76/'Historicail Financial Statement'!I7 -> 0.18405682 | J42: ='Historicail Financial Statement'!J76/'Historicail Financial Statement'!J7 -> 0.19155269 | K42: ='Historicail Financial Statement'!K76/'Historicail Financial Statement'!K7 -> 0.19509327 | M42: =AVERAGE(E42:K42) -> 0.2011073 | N42: =MEDIAN(E42:K42) -> 0.19509327
B43: CFO/Total Assets | D43: ='Historicail Financial Statement'!D76/'Historicail Financial Statement'!D70 -> 0.25103379 | E43: ='Historicail Financial Statement'!E76/'Historicail Financial Statement'!E70 -> 0.26945649 | F43: ='Historicail Financial Statement'!F76/'Historicail Financial Statement'!F70 -> 0.29849529 | G43: ='Historicail Financial Statement'!G76/'Historicail Financial Statement'!G70 -> 0.28347904 | H43: ='Historicail Financial Statement'!H76/'Historicail Financial Statement'!H70 -> 0.29375118 | I43: ='Historicail Financial Statement'!I76/'Historicail Financial Statement'!I70 -> 0.30478718 | J43: ='Historicail Financial Statement'!J76/'Historicail Financial Statement'!J70 -> 0.30827802 | K43: ='Historicail Financial Statement'!K76/'Historicail Financial Statement'!K70 -> 0.28754685 | M43: =AVERAGE(E43:K43) -> 0.29225629 | N43: =MEDIAN(E43:K43) -> 0.29375118
B44: CFO/Total Debt | D44: ='Historicail Financial Statement'!D76/'Historicail Financial Statement'!D55 -> 461.17742 | E44: ='Historicail Financial Statement'!E76/'Historicail Financial Statement'!E55 -> 3.9599951 | F44: ='Historicail Financial Statement'!F76/'Historicail Financial Statement'!F55 -> 4.9778063 | G44: ='Historicail Financial Statement'!G76/'Historicail Financial Statement'!G55 -> 5.1098746 | H44: ='Historicail Financial Statement'!H76/'Historicail Financial Statement'!H55 -> 5.4585068 | I44: ='Historicail Financial Statement'!I76/'Historicail Financial Statement'!I55 -> 5.5277397 | J44: ='Historicail Financial Statement'!J76/'Historicail Financial Statement'!J55 -> 5.2074106 | K44: ='Historicail Financial Statement'!K76/'Historicail Financial Statement'!K55 -> 4.6170345 | M44: =AVERAGE(E44:K44) -> 4.9797668 | N44: =MEDIAN(E44:K44) -> 5.1098746

Sheet FORECASTING
B3: ="FORECASTING OF -"&'Data Sheet'!B1 -> FORECASTING OF -TATA CONSULTANCY SERVICES LTD
B5: Year Whight | C5: Years | D5: Sales | E5: Sales Growth | G5: Year Whight | H5: Years | I5: EBITDA | J5: EBITDA Growth | L5: Year Whight | M5: Years | N5: EPS | O5: EPS Growth
B7: 1 | C7: {=TRANSPOSE('Historicail Financial Statement'!D4:K4)} -> 43555 | D7: {=TRANSPOSE('Historicail Financial Statement'!D7:K7)} -> 146463 | G7: 1 | H7: {=TRANSPOSE('Historicail Financial Statement'!D4:K4)} -> 43555 | I7: {=TRANSPOSE('Historicail Financial Statement'!D17:K17)} -> 39506 | L7: 1 | M7: {=TRANSPOSE('Historicail Financial Statement'!D4:K4)} -> 43555 | N7: {=TRANSPOSE('Historicail Financial Statement'!D43:K43)} -> 84.111502
B8: 2 | C8: 43921 | D8: 156949 | E8: =D8/D7-1 -> 0.071594874 | G8: 2 | H8: 43921 | I8: 42109 | J8: =I8/I7-1 -> 0.065888726 | L8: 2 | M8: 43921 | N8: 86.469993 | O8: =N8/N7-1 -> 0.028040048
B9: 3 | C9: 44286 | D9: 164177 | E9: =D9/D8-1 -> 0.046053177 | G9: 3 | H9: 44286 | I9: 46546 | J9: =I9/I8-1 -> 0.1053694 | L9: 3 | M9: 44286 | N9: 88.026817 | O9: =N9/N8-1 -> 0.01800422
B10: 4 | C10: 44651 | D10: 191754 | E10: =D10/D9-1 -> 0.16797115 | G10: 4 | H10: 44651 | I10: 53057 | J10: =I10/I9-1 -> 0.13988313 | L10: 4 | M10: 44651 | N10: 105.07775 | O10: =N10/N9-1 -> 0.19370158
B11: 5 | C11: 45016 | D11: 225458 | E11: =D11/D10-1 -> 0.17576687 | G11: 5 | H11: 45016 | I11: 59259 | J11: =I11/I10-1 -> 0.11689315 | L11: 5 | M11: 45016 | N11: 115.6104 | O11: =N11/N10-1 -> 0.10023668
B12: 6 | C12: 45382 | D12: 240893 | E12: =D12/D11-1 -> 0.068460645 | G12: 6 | H12: 45382 | I12: 64296 | J12: =I12/I11-1 -> 0.084999747 | L12: 6 | M12: 45382 | N12: 127.41218 | O12: =N12/N11-1 -> 0.10208236
B13: 7 | C13: 45747 | D13: 255324 | E13: =D13/D12-1 -> 0.059906265 | G13: 7 | H13: 45747 | I13: 67407 | J13: =I13/I12-1 -> 0.048385592 | L13: 7 | M13: 45747 | N13: 134.86913 | O13: =N13/N12-1 -> 0.058526215
B14: 8 | C14: 46112 | D14: 267021 | E14: =D14/D13-1 -> 0.04581238 | G14: 8 | H14: 46112 | I14: 72398 | J14: =I14/I13-1 -> 0.074042755 | L14: 8 | M14: 46112 | N14: 136.685 | O14: =N14/N13-1 -> 0.013463942
B15: 9 | C15: =C14+365 -> 46477 | D15: =FORECAST(B15,_xlfn.ANCHORARRAY($D$7),$B$7:$B$14) -> 291699.5 | E15: =D15/D14-1 -> 0.09242157 | G15: 9 | H15: =H14+365 -> 46477 | I15: =FORECAST(G15,_xlfn.ANCHORARRAY($I$7),$G$7:$G$14) -> 77867.929 | J15: =I15/I14-1 -> 0.075553587 | L15: 9 | M15: =M14+365 -> 46477 | N15: =FORECAST(L15,_xlfn.ANCHORARRAY($N$7),$L$7:$L$14) -> 149.356 | O15: =N15/N14-1 -> 0.092702206
B16: 10 | C16: =C15+365 -> 46842 | D16: =FORECAST(B16,_xlfn.ANCHORARRAY($D$7),$B$7:$B$14) -> 310742.75 | E16: =D16/D15-1 -> 0.065283794 | G16: 10 | H16: =H15+365 -> 46842 | I16: =FORECAST(G16,_xlfn.ANCHORARRAY($I$7),$G$7:$G$14) -> 82822.524 | J16: =I16/I15-1 -> 0.063628189 | L16: 10 | M16: =M15+365 -> 46842 | N16: =FORECAST(L16,_xlfn.ANCHORARRAY($N$7),$L$7:$L$14) -> 158.15004 | O16: =N16/N15-1 -> 0.058879687
B17: 11 | C17: =C16+365 -> 47207 | D17: =FORECAST(B17,_xlfn.ANCHORARRAY($D$7),$B$7:$B$14) -> 329786 | E17: =D17/D16-1 -> 0.061283007 | G17: 11 | H17: =H16+365 -> 47207 | I17: =FORECAST(G17,_xlfn.ANCHORARRAY($I$7),$G$7:$G$14) -> 87777.119 | J17: =I17/I16-1 -> 0.059821834 | L17: 11 | M17: =M16+365 -> 47207 | N17: =FORECAST(L17,_xlfn.ANCHORARRAY($N$7),$L$7:$L$14) -> 166.94407 | O17: =N17/N16-1 -> 0.055605644
B18: 12 | C18: =C17+365 -> 47572 | D18: =FORECAST(B18,_xlfn.ANCHORARRAY($D$7),$B$7:$B$14) -> 348829.25 | E18: =D18/D17-1 -> 0.057744264 | G18: 12 | H18: =H17+365 -> 47572 | I18: =FORECAST(G18,_xlfn.ANCHORARRAY($I$7),$G$7:$G$14) -> 92731.714 | J18: =I18/I17-1 -> 0.056445179 | L18: 12 | M18: =M17+365 -> 47572 | N18: =FORECAST(L18,_xlfn.ANCHORARRAY($N$7),$L$7:$L$14) -> 175.73811 | O18: =N18/N17-1 -> 0.052676531
B19: 13 | C19: =C18+365 -> 47937 | D19: =FORECAST(B19,_xlfn.ANCHORARRAY($D$7),$B$7:$B$14) -> 367872.5 | E19: =D19/D18-1 -> 0.054591896 | G19: 13 | H19: =H18+365 -> 47937 | I19: =FORECAST(G19,_xlfn.ANCHORARRAY($I$7),$G$7:$G$14) -> 97686.31 | J19: =I19/I18-1 -> 0.05342935 | L19: 13 | M19: =M18+365 -> 47937 | N19: =FORECAST(L19,_xlfn.ANCHORARRAY($N$7),$L$7:$L$14) -> 184.53214 | O19: =N19/N18-1 -> 0.050040568

Sheet COMMANSIZE STATMENT
B2: ="Common Size Income Statement"&" "&"- "&'Data Sheet'!B1 -> Common Size Income Statement - TATA CONSULTANCY SERVICES LTD
B4: Purticlars | D4: ='Ratio Analysis'!D6 -> 43555 | E4: ='Ratio Analysis'!E6 -> 43921 | F4: ='Ratio Analysis'!F6 -> 44286 | G4: ='Ratio Analysis'!G6 -> 44651 | H4: ='Ratio Analysis'!H6 -> 45016 | I4: ='Ratio Analysis'!I6 -> 45382 | J4: ='Ratio Analysis'!J6 -> 45747 | K4: ='Ratio Analysis'!K6 -> 46112
B6: Sales | D6: ='Data Sheet'!D17/'Data Sheet'!D17 -> 1 | E6: ='Data Sheet'!E17/'Data Sheet'!E17 -> 1 | F6: ='Data Sheet'!F17/'Data Sheet'!F17 -> 1 | G6: ='Data Sheet'!G17/'Data Sheet'!G17 -> 1 | H6: ='Data Sheet'!H17/'Data Sheet'!H17 -> 1 | I6: ='Data Sheet'!I17/'Data Sheet'!I17 -> 1 | J6: ='Data Sheet'!J17/'Data Sheet'!J17 -> 1 | K6: ='Data Sheet'!K17/'Data Sheet'!K17 -> 1
B7: Raw Material Cost | D7: ='Data Sheet'!D18/'Data Sheet'!$D$17 -> 0.00027310652 | E7: ='Data Sheet'!E18/'Data Sheet'!$E$17 -> 0.00011468694 | F7: ='Data Sheet'!F18/'Data Sheet'!$F$17 -> 8.527382e-05 | G7: ='Data Sheet'!G18/'Data Sheet'!$G$17 -> 0.00015123544 | H7: ='Data Sheet'!H18/'Data Sheet'!$H$17 -> 0.00016411039 | I7: ='Data Sheet'!I18/'Data Sheet'!$I$17 -> 0.00017435127 | J7: ='Data Sheet'!J18/'Data Sheet'!$J$17 -> 0.00019191302 | K7: ='Data Sheet'!K18/'Data Sheet'!$K$17 -> 0.00016103602
B8: Change in Inventory | D8: ='Data Sheet'!D19/'Data Sheet'!$D$17 -> 0 | E8: ='Data Sheet'!E19/'Data Sheet'!$E$17 -> 0 | F8: ='Data Sheet'!F19/'Data Sheet'!$F$17 -> 0 | G8: ='Data Sheet'!G19/'Data Sheet'!$G$17 -> 0 | H8: ='Data Sheet'!H19/'Data Sheet'!$H$17 -> 0 | I8: ='Data Sheet'!I19/'Data Sheet'!$I$17 -> 0 | J8: ='Data Sheet'!J19/'Data Sheet'!$J$17 -> 0 | K8: ='Data Sheet'!K19/'Data Sheet'!$K$17 -> 0
B9: Power and Fuel | D9: ='Data Sheet'!D20/'Data Sheet'!$D$17 -> 0 | E9: ='Data Sheet'!E20/'Data Sheet'!$E$17 -> 0 | F9: ='Data Sheet'!F20/'Data Sheet'!$F$17 -> 0 | G9: ='Data Sheet'!G20/'Data Sheet'!$G$17 -> 0 | H9: ='Data Sheet'!H20/'Data Sheet'!$H$17 -> 0 | I9: ='Data Sheet'!I20/'Data Sheet'!$I$17 -> 0 | J9: ='Data Sheet'!J20/'Data Sheet'!$J$17 -> 0 | K9: ='Data Sheet'!K20/'Data Sheet'!$K$17 -> 0
B10: Other Mfr. Exp | D10: ='Data Sheet'!D21/'Data Sheet'!$D$17 -> 0.015225688 | E10: ='Data Sheet'!E21/'Data Sheet'!$E$17 -> 0.012023014 | F10: ='Data Sheet'!F21/'Data Sheet'!$F$17 -> 0.0088197494 | G10: ='Data Sheet'!G21/'Data Sheet'!$G$17 -> 0.0059138271 | H10: ='Data Sheet'!H21/'Data Sheet'!$H$17 -> 0.0081789069 | I10: ='Data Sheet'!I21/'Data Sheet'!$I$17 -> 0.015193468 | J10: ='Data Sheet'!J21/'Data Sheet'!$J$17 -> 0.045428554 | K10: ='Data Sheet'!K21/'Data Sheet'!$K$17 -> 0.016313324
B11: Employee Cost | D11: ='Data Sheet'!D22/'Data Sheet'!$D$17 -> 0.53423732 | E11: ='Data Sheet'!E22/'Data Sheet'!$E$17 -> 0.54764286 | F11: ='Data Sheet'!F22/'Data Sheet'!$F$17 -> 0.5592379 | G11: ='Data Sheet'!G22/'Data Sheet'!$G$17 -> 0.56089573 | H11: ='Data Sheet'!H22/'Data Sheet'!$H$17 -> 0.56561311 | I11: ='Data Sheet'!I22/'Data Sheet'!$I$17 -> 0.5817147 | J11: ='Data Sheet'!J22/'Data Sheet'!$J$17 -> 0.57099215 | K11: ='Data Sheet'!K22/'Data Sheet'!$K$17 -> 0.58045622
B12: Selling and admin | D12: ='Data Sheet'!D23/'Data Sheet'!$D$17 -> 0.13919556 | E12: ='Data Sheet'!E23/'Data Sheet'!$E$17 -> 0.13078771 | F12: ='Data Sheet'!F23/'Data Sheet'!$F$17 -> 0.11159907 | G12: ='Data Sheet'!G23/'Data Sheet'!$G$17 -> 0.12092055 | H12: ='Data Sheet'!H23/'Data Sheet'!$H$17 -> 0.12824118 | I12: ='Data Sheet'!I23/'Data Sheet'!$I$17 -> 0.10025613 | J12: ='Data Sheet'!J23/'Data Sheet'!$J$17 -> 0.081187041 | K12: ='Data Sheet'!K23/'Data Sheet'!$K$17 -> 0.091505912
B13: Other Expenses | D13: ='Data Sheet'!D24/'Data Sheet'!$D$17 -> 0.041334672 | E13: ='Data Sheet'!E24/'Data Sheet'!$E$17 -> 0.041134381 | F13: ='Data Sheet'!F24/'Data Sheet'!$F$17 -> 0.036746926 | G13: ='Data Sheet'!G24/'Data Sheet'!$G$17 -> 0.035425597 | H13: ='Data Sheet'!H24/'Data Sheet'!$H$17 -> 0.034964384 | I13: ='Data Sheet'!I24/'Data Sheet'!$I$17 -> 0.035754464 | J13: ='Data Sheet'!J24/'Data Sheet'!$J$17 -> 0.038194608 | K13: ='Data Sheet'!K24/'Data Sheet'!$K$17 -> 0.040431277
B14: Other Income | D14: ='Data Sheet'!D25/'Data Sheet'!$D$17 -> 0.029434055 | E14: ='Data Sheet'!E25/'Data Sheet'!$E$17 -> 0.029257912 | F14: ='Data Sheet'!F25/'Data Sheet'!$F$17 -> 0.011670331 | G14: ='Data Sheet'!G25/'Data Sheet'!$G$17 -> 0.020953931 | H14: ='Data Sheet'!H25/'Data Sheet'!$H$17 -> 0.015297749 | I14: ='Data Sheet'!I25/'Data Sheet'!$I$17 -> 0.014379828 | J14: ='Data Sheet'!J25/'Data Sheet'!$J$17 -> 0.015517539 | K14: ='Data Sheet'!K25/'Data Sheet'!$K$17 -> -0.00046438295
B15: Depreciation | D15: ='Data Sheet'!D26/'Data Sheet'!$D$17 -> 0.014037675 | E15: ='Data Sheet'!E26/'Data Sheet'!$E$17 -> 0.022485011 | F15: ='Data Sheet'!F26/'Data Sheet'!$F$17 -> 0.024759863 | G15: ='Data Sheet'!G26/'Data Sheet'!$G$17 -> 0.024009929 | H15: ='Data Sheet'!H26/'Data Sheet'!$H$17 -> 0.022274659 | I15: ='Data Sheet'!I26/'Data Sheet'!$I$17 -> 0.020693835 | J15: ='Data Sheet'!J26/'Data Sheet'!$J$17 -> 0.020530777 | K15: ='Data Sheet'!K26/'Data Sheet'!$K$17 -> 0.020822332
B16: Interest | D16: ='Data Sheet'!D27/'Data Sheet'!$D$17 -> 0.0013518773 | E16: ='Data Sheet'!E27/'Data Sheet'!$E$17 -> 0.0058872627 | F16: ='Data Sheet'!F27/'Data Sheet'!$F$17 -> 0.0038799588 | G16: ='Data Sheet'!G27/'Data Sheet'!$G$17 -> 0.0040885718 | H16: ='Data Sheet'!H27/'Data Sheet'!$H$17 -> 0.003455189 | I16: ='Data Sheet'!I27/'Data Sheet'!$I$17 -> 0.0032296497 | J16: ='Data Sheet'!J27/'Data Sheet'!$J$17 -> 0.0031176074 | K16: ='Data Sheet'!K27/'Data Sheet'!$K$17 -> 0.0045951442
B17: Profit before tax | D17: ='Data Sheet'!D28/'Data Sheet'!$D$17 -> 0.28377816 | E17: ='Data Sheet'!E28/'Data Sheet'!$E$17 -> 0.26918298 | F17: ='Data Sheet'!F28/'Data Sheet'!$F$17 -> 0.2665416 | G17: ='Data Sheet'!G28/'Data Sheet'!$G$17 -> 0.26954848 | H17: ='Data Sheet'!H28/'Data Sheet'!$H$17 -> 0.25240621 | I17: ='Data Sheet'!I28/'Data Sheet'!$I$17 -> 0.25736323 | J17: ='Data Sheet'!J28/'Data Sheet'!$J$17 -> 0.25587489 | K17: ='Data Sheet'!K28/'Data Sheet'!$K$17 -> 0.24525037
B18: Tax | D18: ='Data Sheet'!D29/'Data Sheet'!$D$17 -> 0.068283457 | E18: ='Data Sheet'!E29/'Data Sheet'!$E$17 -> 0.062447037 | F18: ='Data Sheet'!F29/'Data Sheet'!$F$17 -> 0.068206874 | G18: ='Data Sheet'!G29/'Data Sheet'!$G$17 -> 0.06903637 | H18: ='Data Sheet'!H29/'Data Sheet'!$H$17 -> 0.064774814 | I18: ='Data Sheet'!I29/'Data Sheet'!$I$17 -> 0.065996106 | J18: ='Data Sheet'!J29/'Data Sheet'!$J$17 -> 0.064756936 | K18: ='Data Sheet'!K29/'Data Sheet'!$K$17 -> 0.060043967
B19: Net profit | D19: ='Data Sheet'!D30/'Data Sheet'!$D$17 -> 0.21488021 | E19: ='Data Sheet'!E30/'Data Sheet'!$E$17 -> 0.2060542 | F19: ='Data Sheet'!F30/'Data Sheet'!$F$17 -> 0.19753071 | G19: ='Data Sheet'!G30/'Data Sheet'!$G$17 -> 0.19987588 | H19: ='Data Sheet'!H30/'Data Sheet'!$H$17 -> 0.18693947 | I19: ='Data Sheet'!I30/'Data Sheet'!$I$17 -> 0.19057424 | J19: ='Data Sheet'!J30/'Data Sheet'!$J$17 -> 0.1901623 | K19: ='Data Sheet'!K30/'Data Sheet'!$K$17 -> 0.18429262
B21: ="Common Size Balance Sheet Statement"&" "&"- "&'Data Sheet'!B1 -> Common Size Balance Sheet Statement - TATA CONSULTANCY SERVICES LTD
B23: Total Liabilities | D23: ='Data Sheet'!D61/'Data Sheet'!D61 -> 1 | E23: ='Data Sheet'!E61/'Data Sheet'!E61 -> 1 | F23: ='Data Sheet'!F61/'Data Sheet'!F61 -> 1 | G23: ='Data Sheet'!G61/'Data Sheet'!G61 -> 1 | H23: ='Data Sheet'!H61/'Data Sheet'!H61 -> 1 | I23: ='Data Sheet'!I61/'Data Sheet'!I61 -> 1 | J23: ='Data Sheet'!J61/'Data Sheet'!J61 -> 1 | K23: ='Data Sheet'!K61/'Data Sheet'!K61 -> 1
B24: Equity Share Capital | D24: ='Data Sheet'!D57/'Data Sheet'!$D$61 -> 0.0032923328 | E24: ='Data Sheet'!E57/'Data Sheet'!$E$61 -> 0.0031216962 | F24: ='Data Sheet'!F57/'Data Sheet'!$F$61 -> 0.002846329 | G24: ='Data Sheet'!G57/'Data Sheet'!$G$61 -> 0.0025971446 | H24: ='Data Sheet'!H57/'Data Sheet'!$H$61 -> 0.0025619667 | I24: ='Data Sheet'!I57/'Data Sheet'!$I$61 -> 0.0024884514 | J24: ='Data Sheet'!J57/'Data Sheet'!$J$61 -> 0.0022817667 | K24: ='Data Sheet'!K57/'Data Sheet'!$K$61 -> 0.0019981564
B25: Reserves | D25: ='Data Sheet'!D58/'Data Sheet'!$D$61 -> 0.78200367 | E25: ='Data Sheet'!E58/'Data Sheet'!$E$61 -> 0.69718714 | F25: ='Data Sheet'!F58/'Data Sheet'!$F$61 -> 0.66206382 | G25: ='Data Sheet'!G58/'Data Sheet'!$G$61 -> 0.62993528 | H25: ='Data Sheet'!H58/'Data Sheet'!$H$61 -> 0.6303978 | I25: ='Data Sheet'!I58/'Data Sheet'!$I$61 -> 0.61954878 | J25: ='Data Sheet'!J58/'Data Sheet'!$J$61 -> 0.59498642 | K25: ='Data Sheet'!K58/'Data Sheet'!$K$61 -> 0.58994188
B26: Borrowings | D26: ='Data Sheet'!D59/'Data Sheet'!$D$61 -> 0.00054433236 | E26: ='Data Sheet'!E59/'Data Sheet'!$E$61 -> 0.068044653 | F26: ='Data Sheet'!F59/'Data Sheet'!$F$61 -> 0.059965229 | G26: ='Data Sheet'!G59/'Data Sheet'!$G$61 -> 0.055476711 | H26: ='Data Sheet'!H59/'Data Sheet'!$H$61 -> 0.0538153 | I26: ='Data Sheet'!I59/'Data Sheet'!$I$61 -> 0.055137758 | J26: ='Data Sheet'!J59/'Data Sheet'!$J$61 -> 0.059199869 | K26: ='Data Sheet'!K59/'Data Sheet'!$K$61 -> 0.062279554
B27: Other Liabilities | D27: ='Data Sheet'!D60/'Data Sheet'!$D$61 -> 0.21415966 | E27: ='Data Sheet'!E60/'Data Sheet'!$E$61 -> 0.23164651 | F27: ='Data Sheet'!F60/'Data Sheet'!$F$61 -> 0.27512462 | G27: ='Data Sheet'!G60/'Data Sheet'!$G$61 -> 0.31199086 | H27: ='Data Sheet'!H60/'Data Sheet'!$H$61 -> 0.31322493 | I27: ='Data Sheet'!I60/'Data Sheet'!$I$61 -> 0.32282501 | J27: ='Data Sheet'!J60/'Data Sheet'!$J$61 -> 0.34353195 | K27: ='Data Sheet'!K60/'Data Sheet'!$K$61 -> 0.34578041
B29: Total Assets | D29: ='Data Sheet'!D66/'Data Sheet'!D66 -> 1 | E29: ='Data Sheet'!E66/'Data Sheet'!E66 -> 1 | F29: ='Data Sheet'!F66/'Data Sheet'!F66 -> 1 | G29: ='Data Sheet'!G66/'Data Sheet'!G66 -> 1 | H29: ='Data Sheet'!H66/'Data Sheet'!H66 -> 1 | I29: ='Data Sheet'!I66/'Data Sheet'!I66 -> 1 | J29: ='Data Sheet'!J66/'Data Sheet'!J66 -> 1 | K29: ='Data Sheet'!K66/'Data Sheet'!K66 -> 1
B30: Net Block | D30: ='Data Sheet'!D62/'Data Sheet'!$D$66 -> 0.10790072 | E30: ='Data Sheet'!E62/'Data Sheet'!$E$66 -> 0.17421562 | F30: ='Data Sheet'!F62/'Data Sheet'!$F$66 -> 0.16170995 | G30: ='Data Sheet'!G62/'Data Sheet'!$G$66 -> 0.15113111 | H30: ='Data Sheet'!H62/'Data Sheet'!$H$66 -> 0.14360313 | I30: ='Data Sheet'!I62/'Data Sheet'!$I$66 -> 0.13476133 | J30: ='Data Sheet'!J62/'Data Sheet'!$J$66 -> 0.1453082 | K30: ='Data Sheet'!K62/'Data Sheet'!$K$66 -> 0.17300612
B31: Capital Work in Progress | D31: ='Data Sheet'!D63/'Data Sheet'!$D$66 -> 0.0084547107 | E31: ='Data Sheet'!E63/'Data Sheet'!$E$66 -> 0.007542018 | F31: ='Data Sheet'!F63/'Data Sheet'!$F$66 -> 0.0071235153 | G31: ='Data Sheet'!G63/'Data Sheet'!$G$66 -> 0.0085507082 | H31: ='Data Sheet'!H63/'Data Sheet'!$H$66 -> 0.0086378877 | I31: ='Data Sheet'!I63/'Data Sheet'!$I$66 -> 0.01075121 | J31: ='Data Sheet'!J63/'Data Sheet'!$J$66 -> 0.0097447825 | K31: ='Data Sheet'!K63/'Data Sheet'!$K$66 -> 0.014710185
B32: Investments | D32: ='Data Sheet'!D64/'Data Sheet'!$D$66 -> 0.25750432 | E32: ='Data Sheet'!E64/'Data Sheet'!$E$66 -> 0.21940113 | F32: ='Data Sheet'!F64/'Data Sheet'!$F$66 -> 0.22596006 | G32: ='Data Sheet'!G64/'Data Sheet'!$G$66 -> 0.21632227 | H32: ='Data Sheet'!H64/'Data Sheet'!$H$66 -> 0.26013762 | I32: ='Data Sheet'!I64/'Data Sheet'!$I$66 -> 0.21833755 | J32: ='Data Sheet'!J64/'Data Sheet'!$J$66 -> 0.19517299 | K32: ='Data Sheet'!K64/'Data Sheet'!$K$66 -> 0.18760591
B33: Other Assets | D33: ='Data Sheet'!D75/'Data Sheet'!$D$66 -> 0.27316705 | E33: ='Data Sheet'!E75/'Data Sheet'!$E$66 -> 0.26417042 | F33: ='Data Sheet'!F75/'Data Sheet'!$F$66 -> 0.30198781 | G33: ='Data Sheet'!G75/'Data Sheet'!$G$66 -> 0.19787261 | H33: ='Data Sheet'!H75/'Data Sheet'!$H$66 -> 0.16052891 | I33: ='Data Sheet'!I75/'Data Sheet'!$I$66 -> 0.17632947 | J33: ='Data Sheet'!J75/'Data Sheet'!$J$66 -> 0.17999483 | K33: ='Data Sheet'!K75/'Data Sheet'!$K$66 -> 0.17950289
B34: Receivables | D34: ='Data Sheet'!D67/'Data Sheet'!$D$66 -> 0.24008569 | E34: ='Data Sheet'!E67/'Data Sheet'!$E$66 -> 0.25416434 | F34: ='Data Sheet'!F67/'Data Sheet'!$F$66 -> 0.23139116 | G34: ='Data Sheet'!G67/'Data Sheet'!$G$66 -> 0.29668474 | H34: ='Data Sheet'!H67/'Data Sheet'!$H$66 -> 0.34967345 | I34: ='Data Sheet'!I67/'Data Sheet'!$I$66 -> 0.36829768 | J34: ='Data Sheet'!J67/'Data Sheet'!$J$66 -> 0.3721801 | K34: ='Data Sheet'!K67/'Data Sheet'!$K$66 -> 0.37376564
B35: Inventory | D35: ='Data Sheet'!D68/'Data Sheet'!$D$66 -> 8.7795542e-05 | E35: ='Data Sheet'!E68/'Data Sheet'!$E$66 -> 4.1622616e-05 | F35: ='Data Sheet'!F68/'Data Sheet'!$F$66 -> 6.1542249e-05 | G35: ='Data Sheet'!G68/'Data Sheet'!$G$66 -> 0.00014192047 | H35: ='Data Sheet'!H68/'Data Sheet'!$H$66 -> 0.00019599745 | I35: ='Data Sheet'!I68/'Data Sheet'!$I$66 -> 0.0001924769 | J35: ='Data Sheet'!J68/'Data Sheet'!$J$66 -> 0.00013236768 | K35: ='Data Sheet'!K68/'Data Sheet'!$K$66 -> 0.0001600733
B36: Cash & Bank | D36: ='Data Sheet'!D69/'Data Sheet'!$D$66 -> 0.11279971 | E36: ='Data Sheet'!E69/'Data Sheet'!$E$66 -> 0.080464841 | F36: ='Data Sheet'!F69/'Data Sheet'!$F$66 -> 0.071765955 | G36: ='Data Sheet'!G69/'Data Sheet'!$G$66 -> 0.12929664 | H36: ='Data Sheet'!H69/'Data Sheet'!$H$66 -> 0.077222996 | I36: ='Data Sheet'!I69/'Data Sheet'!$I$66 -> 0.09133029 | J36: ='Data Sheet'!J69/'Data Sheet'!$J$66 -> 0.097466735 | K36: ='Data Sheet'!K69/'Data Sheet'!$K$66 -> 0.071249179

Sheet Risk Free Rate
B2: Return on Markets
F3: Average Return | H3: =AVERAGE(C5:C27) -> 0.15411739
B4: Year | C4: Annual | F4: Dividend Yield | H4: 1.39% 1
B5: 2000 | C5: -0.1465 | F5: Total Market Returns | H5: =SUM(H3:H4) -> 0.15411739
B6: 2001 | C6: -0.1618
B7: 2002 | C7: 0.0325
B8: 2003 | C8: 0.719
B9: 2004 | C9: 0.1068
B10: 2005 | C10: 0.3634
B11: 2006 | C11: 0.3983
B12: 2007 | C12: 0.5477
B13: 2008 | C13: -0.5179
B14: 2009 | C14: 0.7576
B15: 2010 | C15: 0.1795
B16: 2011 | C16: -0.2462
B17: 2012 | C17: 0.277
... B27: 2022 | C27: 0.0432

Sheet WACC
B3: ="Weighted Average Cost Of Capital-"&'Data Sheet'!B1 -> Weighted Average Cost Of Capital-TATA CONSULTANCY SERVICES LTD
B4: All Figures Are in INR unless Stated Otherwaise
B5: Peer Companies
I6: Debt/ | J6: Debt/ | K6: Levered | L6: Unlevered
B7: Company Name | E7: Country | F7: TotalDebt | G7: Total Equity | H7: Tax Rate1 | I7: Equity | J7: Capital | K7: Beta2 | L7: Beta3
B8: TCS | E8: India | F8: 11283 | G8: 737079.33 | H8: 0.25 | I8: =F8/G8 -> 0.015307715 | J8: =F8/(F8+G8) -> 0.015076921 | K8: ='Regretion Beta'!K13 -> 0.11676028 | L8: =K8/(1+(1-H8)*F8/G8) -> 0.11543499
B9: Infosys | E9: India | F9: 9176 | G9: 427062.4 | H9: 0.25 | I9: =F9/G9 -> 0.021486321 | J9: =F9/(F9+G9) -> 0.02103437 | K9: 0.77 | L9: =K9/(1+(1-H9)*F9/G9) -> 0.75778844
B10: HCL Teche | E10: India | F10: =[1]Sheet2!L5 -> 5215 | G10: =[1]Sheet2!N5 -> 309904.54 | H10: 0.25 | I10: =F10/G10 -> 0.016827763 | J10: =F10/(F10+G10) -> 0.016549275 | K10: 0.8 | L10: =K10/(1+(1-H10)*F10/G10) -> 0.79002918
B11: Wipro | E11: India | F11: =[1]Sheet2!L6 -> 20291 | G11: =[1]Sheet2!N6 -> 171677.17 | H11: 0.25 | I11: =F11/G11 -> 0.11819277 | J11: =F11/(F11+G11) -> 0.10569981 | K11: 0.65 | L11: =K11/(1+(1-H11)*F11/G11) -> 0.59707274
B12: LTM | E12: India | F12: =[1]Sheet2!L7 -> 2186.2 | G12: =[1]Sheet2!N7 -> 140423.83 | H12: 0.25 | I12: =F12/G12 -> 0.015568583 | J12: =F12/(F12+G12) -> 0.015329918 | K12: 0.78 | L12: =K12/(1+(1-H12)*F12/G12) -> 0.7709975
B13: Average | H13: =AVERAGE(H8:H12) -> 0.25 | I13: =AVERAGE(I8:I12) -> 0.03747663 | J13: =AVERAGE(J8:J12) -> 0.03473806 | K13: =AVERAGE(K8:K12) -> 0.62335206 | L13: =AVERAGE(L8:L12) -> 0.60626457
B14: Median | H14: =MEDIAN(H8:H12) -> 0.25 | I14: =MEDIAN(I8:I12) -> 0.016827763 | J14: =MEDIAN(J8:J12) -> 0.016549275 | K14: =MEDIAN(K8:K12) -> 0.77 | L14: =MEDIAN(L8:L12) -> 0.75778844
B17: Cost Of Debt | G17: Cost Of Equity
B18: Pre-Tax Cost of Debt | E18: 0.095 | G18: Risk Free Rate | L18: 0.083
B19: Tax Rate | E19: =H12 -> 0.25 | G19: Equity Risk Premium | L19: ='Risk Free Rate'!H5 -> 0.15411739
B20: Post-Tax Cost Of Debt | E20: =E18*(1-E19) -> 0.07125 | G20: Levered Bate4 | L20: ='Regretion Beta'!M11 -> 0.33757021
G21: Cost of Equity | L21: =L18+L19*L20 -> 0.13502544
B23: Capital Structre | G23: Levered Bate
D24: Cuurent | E24: Target | G24: Comps median levered Bate | L24: =L14 -> 0.75778844
B25: Total Debt | C25: =F8 -> 11283 | D25: =C25/C27 -> 0.015076921 | E25: =J13 -> 0.03473806 | G25: Targeted Debt/Equity | L25: =E29 -> 0.035988221
B26: Market Capitalizetion | C26: =G8 -> 737079.33 | D26: =C26/C27 -> 0.98492308 | E26: =E27-E25 -> 0.96526194 | G26: Tax Rate | L26: =E19 -> 0.25
B27: Total Capital | C27: =SUM(C25:C26) -> 748362.33 | D27: =C27/C27 -> 1 | E27: =D27/D27 -> 1 | G27: Levered Bate | L27: =L24*(1+(1-L26)*L25) -> 0.77824203
B29: Debt/Equity | D29: =D25/D26 -> 0.015307715 | E29: =E25/E26 -> 0.035988221
B30: Note: | G30: Weighte Average Cost Of Capital
B31: 1.Tax Rate Considered as maeginal Tax Rate for the Companey | K31: Total Cost | L31: Total Weught
B32: 2.Levered beto is bosed on 5 year monthly data | G32: Debt | K32: =E20 -> 0.07125 | L32: =E25 -> 0.03473806
B33: 3.Unlevered Beta = Levered Bate /(1+(1-Tax Rate )*Debt/Equty) | G33: Equity | K33: =L21 -> 0.13502544 | L33: =E26 -> 0.96526194
B34: 4.Levered Beta -Unlevered Beta *(1+(1-Tax Rate(*Debt/Equty) | G34: WACC | L34: =SUMPRODUCT(K32:K33,L32:L33) -> 0.13281

Sheet Regretion Beta
B2: ="Adjested Beta-"&'Data Sheet'!B1 -> Adjested Beta-TATA CONSULTANCY SERVICES LTD
B4: TCS Weekly Returns | F4: NIFY-50 Weekly Returns | J4: Beta Drifting
B5: Date | C5: Close | D5: Return | G5: Close | H5: Return
B6: 45931 | C6: 10.29 | G6: 24383.6 | J6: Levered Raw Beta | M6: =K13 -> 0.11676028
B7: 45933 | C7: 10.06 | D7: =C7/C6-1 -> -0.022351798 | G7: 24317.15 | H7: =G7/G6-1 -> -0.0027251923 | J7: Raw Beta Weight | M7: 0.75
B8: 45936 | C8: 10.19 | D8: =C8/C7-1 -> 0.012922465 | G8: 24250.2 | H8: =G8/G7-1 -> -0.0027532009
B9: 45937 | C9: 10.05 | D9: =C9/C8-1 -> -0.01373896 | G9: 23985.35 | H9: =G9/G8-1 -> -0.010921559 | J9: Market Beta | M9: 1
B10: 45938 | C10: 10.31 | D10: =C10/C9-1 -> 0.025870647 | G10: 23995.95 | H10: =G10/G9-1 -> 0.00044193643 | J10: Market Beta Weight | M10: 0.25
B11: 45939 | C11: 10.12 | D11: =C11/C10-1 -> -0.01842871 | G11: 23767.45 | H11: =G11/G10-1 -> -0.0095224402 | J11: Adjusted Beta | M11: =(M6*M7)+(M9*M10) -> 0.33757021
B12: 45940 | C12: 10.1 | D12: =C12/C11-1 -> -0.0019762846 | G12: 23869.6 | H12: =G12/G11-1 -> 0.0042978948
B13: 45943 | C13: 11.01 | D13: =C13/C12-1 -> 0.09009901 | G13: 23996.25 | H13: =G13/G12-1 -> 0.0053059121 | J13: Beta1 | K13: =SLOPE(D7:D127,H7:H127) -> 0.11676028
B14: 45944 | C14: 11.16 | D14: =C14/C13-1 -> 0.013623978 | G14: 24187.7 | H14: =G14/G13-1 -> 0.0079783299 | J14: Beta2 | K14: {=_xlfn.COVARIANCE.S(D7:D127,H7:H127/_xlfn.VAR.S(H7:H127))} -> 0.11676028
B15: 45945 | C15: 10.53 | D15: =C15/C14-1 -> -0.056451613 | G15: 24238.5 | H15: =G15/G14-1 -> 0.002100241 | J15: Beta3 | K15: =K34 -> 0.11676028
B16: 45946 | C16: 10.87 | D16: =C16/C15-1 -> 0.032288699 | G16: 24334.3 | H16: =G16/G15-1 -> 0.0039523898
B17: 45947 | C17: 11.63 | D17: =C17/C16-1 -> 0.069917203 | G17: 24072.75 | H17: =G17/G16-1 -> -0.010748203 | J17: SUMMARY OUTPUT
B18: 45950 | C18: 11.36 | D18: =C18/C17-1 -> -0.023215821 | G18: 24078.5 | H18: =G18/G17-1 -> 0.00023885929
B19: 45951 | C19: 11.3 | D19: =C19/C18-1 -> -0.0052816901 | G19: 24052.05 | H19: =G19/G18-1 -> -0.0010984904 | J19: Regression Statistics
B20: 45953 | C20: 11.73 | D20: =C20/C19-1 -> 0.038053097 | G20: 24211 | H20: =G20/G19-1 -> 0.0066085843 | J20: Multiple R | K20: 0.019142005
B21: 45954 | C21: 11.59 | D21: =C21/C20-1 -> -0.011935209 | G21: 24206.9 | H21: =G21/G20-1 -> -0.00016934451 | J21: R Square | K21: 0.00036641636
B22: 45957 | C22: 11.86 | D22: =C22/C21-1 -> 0.023295945 | G22: 23962.8 | H22: =G22/G21-1 -> -0.010083902 | J22: Adjusted R Square | K22: -0.0080338659
B23: 45958 | C23: 11.95 | D23: =C23/C22-1 -> 0.0075885329 | G23: 23882.05 | H23: =G23/G22-1 -> -0.0033698065 | J23: Standard Error | K23: 0.065302034
B24: 45959 | C24: 11.97 | D24: =C24/C23-1 -> 0.0016736402 | G24: 24398.7 | H24: =G24/G23-1 -> 0.021633402 | J24: Observations | K24: 121
B25: 45960 | C25: 12.07 | D25: =C25/C24-1 -> 0.0083542189 | G25: 24430.35 | H25: =G25/G24-1 -> 0.0012972003
B26: 45961 | C26: 12.15 | D26: =C26/C25-1 -> 0.0066280033 | G26: 24270.85 | H26: =G26/G25-1 -> -0.0065287644 | J26: ANOVA
B27: 45964 | C27: 12.67 | D27: =C27/C26-1 -> 0.042798354 | G27: 24175.7 | H27: =G27/G26-1 -> -0.0039203407 | K27: df | L27: SS | M27: MS | N27: F | O27: Significance F
B28: 45965 | C28: 12.65 | D28: =C28/C27-1 -> -0.001578532 | G28: 24005.85 | H28: =G28/G27-1 -> -0.0070256497 | J28: Regression | K28: 1 | L28: 0.00018600919 | M28: 0.00018600919 | N28: 0.04361953 | O28: 0.83492016
B29: 45967 | C29: 12.41 | D29: =C29/C28-1 -> -0.018972332 | G29: 23865.75 | H29: =G29/G28-1 -> -0.0058360775 | J29: Residual | K29: 119 | L29: 0.50745833 | M29: 0.0042643557
B30: 45968 | C30: 12.56 | D30: =C30/C29-1 -> 0.012087027 | G30: 23946.25 | H30: =G30/G29-1 -> 0.0033730346 | J30: Total | K30: 120 | L30: 0.50764434
B31: 45971 | C31: 12.3 | D31: =C31/C30-1 -> -0.020700637 | G31: 24056 | H31: =G31/G30-1 -> 0.0045831811
B32: 45972 | C32: 12.49 | D32: =C32/C31-1 -> 0.015447154 | G32: 24021.65 | H32: =G32/G31-1 -> -0.0014279182 | K32: Coefficients | L32: Standard Error | M32: t Stat | N32: P-value | O32: Lower 95% | P32: Upper 95% | Q32: Lower 95.0% | R32: Upper 95.0%
B33: 45973 | C33: 12.11 | D33: =C33/C32-1 -> -0.030424339 | G33: 23824.1 | H33: =G33/G32-1 -> -0.0082238314 | J33: Intercept | K33: 0.010248431 | L33: 0.00593879 | M33: 1.7256765 | N33: 0.087001296 | O33: -0.0015109667 | P33: 0.022007828 | Q33: -0.0015109667 | R33: 0.022007828
B34: 45974 | C34: 12.16 | D34: =C34/C33-1 -> 0.0041288192 | G34: 24102.9 | H34: =G34/G33-1 -> 0.011702436 | J34: X Variable 1 | K34: 0.11676028 | L34: 0.55905512 | M34: 0.20885289 | N34: 0.83492016 | O34: -0.99022469 | P34: 1.2237452 | Q34: -0.99022469 | R34: 1.2237452
B35: 45975 | C35: 11.94 | D35: =C35/C34-1 -> -0.018092105 | G35: 24013.1 | H35: =G35/G34-1 -> -0.0037256928
B36: 45978 | C36: 11.79 | D36: =C36/C35-1 -> -0.012562814 | G36: 24168 | H36: =G36/G35-1 -> 0.0064506457
B37: 45979 | C37: 12.1 | D37: =C37/C36-1 -> 0.026293469 | G37: 24085.7 | H37: =G37/G36-1 -> -0.0034053294
B38: 45980 | C38: 11.97 | D38: =C38/C37-1 -> -0.010743802 | G38: 23989.15 | H38: =G38/G37-1 -> -0.0040086026
B39: 45981 | C39: 12.14 | D39: =C39/C38-1 -> 0.014202172 | G39: 23853.9 | H39: =G39/G38-1 -> -0.0056379655
B40: 45982 | C40: 13.63 | D40: =C40/C39-1 -> 0.12273476 | G40: 23622.9 | H40: =G40/G39-1 -> -0.0096839511
B41: 45985 | C41: 13.24 | D41: =C41/C40-1 -> -0.028613353 | G41: 23161.6 | H41: =G41/G40-1 -> -0.019527662
B42: 45986 | C42: 12.24 | D42: =C42/C41-1 -> -0.075528701 | G42: 23214.95 | H42: =G42/G41-1 -> 0.0023033815
B43: 45987 | C43: 11.97 | D43: =C43/C42-1 -> -0.022058824 | G43: 23242.1 | H43: =G43/G42-1 -> 0.001169505
B44: 45988 | C44: 11.79 | D44: =C44/C43-1 -> -0.015037594 | G44: 23123 | H44: =G44/G43-1 -> -0.0051243218
B45: 45989 | C45: 11.62 | D45: =C45/C44-1 -> -0.014418999 | G45: 23366.7 | H45: =G45/G44-1 -> 0.01053929
B46: 45992 | C46: 11.63 | D46: =C46/C45-1 -> 0.0008605852 | G46: 23416.55 | H46: =G46/G45-1 -> 0.0021333778
... B127: 46111 | C127: 27.89 | D127: =C127/C126-1 -> 0.040671642 | G127: 25088.4 | H127: =G127/G126-1 -> -0.024843018

Sheet Instrc Growth
B2: ="Instrc Growth-"&'Data Sheet'!B1 -> Instrc Growth-TATA CONSULTANCY SERVICES LTD
A5: # | B5: Calculationof ROIC | D5: ='Historicail Financial Statement'!D4 -> 43555 | E5: ='Historicail Financial Statement'!E4 -> 43921 | F5: ='Historicail Financial Statement'!F4 -> 44286 | G5: ='Historicail Financial Statement'!G4 -> 44651 | H5: ='Historicail Financial Statement'!H4 -> 45016 | I5: ='Historicail Financial Statement'!I4 -> 45382 | J5: ='Historicail Financial Statement'!J4 -> 45747 | K5: ='Historicail Financial Statement'!K4 -> 46112
B7: Current Assets
B9: Receivables | D9: ='Data Sheet'!D67 -> 27346 | E9: ='Data Sheet'!E67 -> 30532 | F9: ='Data Sheet'!F67 -> 30079 | G9: ='Data Sheet'!G67 -> 41810 | H9: ='Data Sheet'!H67 -> 49954 | I9: ='Data Sheet'!I67 -> 53577 | J9: ='Data Sheet'!J67 -> 59046 | K9: ='Data Sheet'!K67 -> 67714
B10: Inventory | D10: ='Data Sheet'!D68 -> 10 | E10: ='Data Sheet'!E68 -> 5 | F10: ='Data Sheet'!F68 -> 8 | G10: ='Data Sheet'!G68 -> 20 | H10: ='Data Sheet'!H68 -> 28 | I10: ='Data Sheet'!I68 -> 28 | J10: ='Data Sheet'!J68 -> 21 | K10: ='Data Sheet'!K68 -> 29
B11: Total Current Assets | D11: =SUM(D9:D10) -> 27356 | E11: =SUM(E9:E10) -> 30537 | F11: =SUM(F9:F10) -> 30087 | G11: =SUM(G9:G10) -> 41830 | H11: =SUM(H9:H10) -> 49982 | I11: =SUM(I9:I10) -> 53605 | J11: =SUM(J9:J10) -> 59067 | K11: =SUM(K9:K10) -> 67743
B13: Current Liabilities
B15: ='Data Sheet'!A60 -> Other Liabilities | D15: ='Data Sheet'!D60 -> 24393 | E15: ='Data Sheet'!E60 -> 27827 | F15: ='Data Sheet'!F60 -> 35764 | G15: ='Data Sheet'!G60 -> 43967 | H15: ='Data Sheet'!H60 -> 44747 | I15: ='Data Sheet'!I60 -> 46962 | J15: ='Data Sheet'!J60 -> 54501 | K15: ='Data Sheet'!K60 -> 62644
B16: Total Current Liabilires | D16: =SUM(D15) -> 24393 | E16: =SUM(E15) -> 27827 | F16: =SUM(F15) -> 35764 | G16: =SUM(G15) -> 43967 | H16: =SUM(H15) -> 44747 | I16: =SUM(I15) -> 46962 | J16: =SUM(J15) -> 54501 | K16: =SUM(K15) -> 62644
A18: # | B18: Net Working Capital | D18: =D11-D16 -> 2963 | E18: =E11-E16 -> 2710 | F18: =F11-F16 -> -5677 | G18: =G11-G16 -> -2137 | H18: =H11-H16 -> 5235 | I18: =I11-I16 -> 6643 | J18: =J11-J16 -> 4566 | K18: =K11-K16 -> 5099
B20: Non Current Assets
B22: ='Data Sheet'!A63 -> Capital Work in Progress | D22: ='Data Sheet'!D63 -> 963 | E22: ='Data Sheet'!E63 -> 906 | F22: ='Data Sheet'!F63 -> 926 | G22: ='Data Sheet'!G63 -> 1205 | H22: ='Data Sheet'!H63 -> 1234 | I22: ='Data Sheet'!I63 -> 1564 | J22: ='Data Sheet'!J63 -> 1546 | K22: ='Data Sheet'!K63 -> 2665
B23: ='Data Sheet'!A65 -> Other Assets | D23: ='Data Sheet'!D65 -> 71318 | E23: ='Data Sheet'!E65 -> 71937 | F23: ='Data Sheet'!F65 -> 78672 | G23: ='Data Sheet'!G65 -> 87936 | H23: ='Data Sheet'!H65 -> 83947 | I23: ='Data Sheet'!I65 -> 92542 | J23: ='Data Sheet'!J65 -> 103086 | K23: ='Data Sheet'!K65 -> 113171
B24: ='Data Sheet'!A62 -> Net Block | D24: =SUM(D22:D23) -> 72281 | E24: =SUM(E22:E23) -> 72843 | F24: =SUM(F22:F23) -> 79598 | G24: =SUM(G22:G23) -> 89141 | H24: =SUM(H22:H23) -> 85181 | I24: =SUM(I22:I23) -> 94106 | J24: =SUM(J22:J23) -> 104632 | K24: =SUM(K22:K23) -> 115836
B25: Accumulated Depreciation | D25: ='Historicail Financial Statement'!D20 -> 2056 | E25: ='Historicail Financial Statement'!E20 -> 3529 | F25: ='Historicail Financial Statement'!F20 -> 4065 | G25: ='Historicail Financial Statement'!G20 -> 4604 | H25: ='Historicail Financial Statement'!H20 -> 5022 | I25: ='Historicail Financial Statement'!I20 -> 4985 | J25: ='Historicail Financial Statement'!J20 -> 5242 | K25: ='Historicail Financial Statement'!K20 -> 5560
B26: Net Non Current Assets | D26: =SUM(D24:D25) -> 74337 | E26: =SUM(E24:E25) -> 76372 | F26: =SUM(F24:F25) -> 83663 | G26: =SUM(G24:G25) -> 93745 | H26: =SUM(H24:H25) -> 90203 | I26: =SUM(I24:I25) -> 99091 | J26: =SUM(J24:J25) -> 109874 | K26: =SUM(K24:K25) -> 121396
B28: Invested Capital | D28: =D18+D26 -> 77300 | E28: =E18+E26 -> 79082 | F28: =F18+F26 -> 77986 | G28: =G18+G26 -> 91608 | H28: =H18+H26 -> 95438 | I28: =I18+I26 -> 105734 | J28: =J18+J26 -> 114440 | K28: =K18+K26 -> 126495
B29: EBIT(1-Tax) | D29: =D40 -> 28087.5 | E29: =E40 -> 28935 | F29: =F40 -> 31860.75 | G29: =G40 -> 36339.75 | H29: =H40 -> 40677.75 | I29: =I40 -> 44483.25 | J29: =J40 -> 46623.75 | K29: =K40 -> 50128.5
B31: ROIC | D31: =D29/D28 -> 0.36335705 | E31: =E29/E28 -> 0.36588604 | F31: =F29/F28 -> 0.40854448 | G31: =G29/G28 -> 0.39668752 | H31: =H29/H28 -> 0.42622174 | I31: =I29/I28 -> 0.42070904 | J31: =J29/J28 -> 0.40740781 | K31: =K29/K28 -> 0.39628839
B33: Calculation Of Reinvestment Rate | D33: =D5 -> 43555 | E33: =E5 -> 43921 | F33: =F5 -> 44286 | G33: =G5 -> 44651 | H33: =H5 -> 45016 | I33: =I5 -> 45382 | J33: =J5 -> 45747 | K33: =K5 -> 46112
B35: Net Capex | D35: =SUM('Cash Flow'!D9:D12) -> -20578 | E35: =SUM('Cash Flow'!E9:E12) -> 4205 | F35: =SUM('Cash Flow'!F9:F12) -> 5250 | G35: =SUM('Cash Flow'!G9:G12) -> 999 | H35: =SUM('Cash Flow'!H9:H12) -> -5971 | I35: =SUM('Cash Flow'!I9:I12) -> -4486 | J35: =SUM('Cash Flow'!J9:J12) -> -10121 | K35: =SUM('Cash Flow'!K9:K12) -> 3543
B36: Change in Working Capital | D36: - | E36: =E26-D26 -> 2035 | F36: =F26-E26 -> 7291 | G36: =G26-F26 -> 10082 | H36: =H26-G26 -> -3542 | I36: =I26-H26 -> 8888 | J36: =J26-I26 -> 10783 | K36: =K26-J26 -> 11522
B38: EBIT | D38: ='Historicail Financial Statement'!D23 -> 37450 | E38: ='Historicail Financial Statement'!E23 -> 38580 | F38: ='Historicail Financial Statement'!F23 -> 42481 | G38: ='Historicail Financial Statement'!G23 -> 48453 | H38: ='Historicail Financial Statement'!H23 -> 54237 | I38: ='Historicail Financial Statement'!I23 -> 59311 | J38: ='Historicail Financial Statement'!J23 -> 62165 | K38: ='Historicail Financial Statement'!K23 -> 66838
B39: Marginal Tax Ret | D39: 0.25 | E39: 0.25 | F39: 0.25 | G39: 0.25 | H39: 0.25 | I39: 0.25 | J39: 0.25 | K39: 0.25
B40: EBIT(1-Tax) | D40: =D38*(1-D39) -> 28087.5 | E40: =E38*(1-E39) -> 28935 | F40: =F38*(1-F39) -> 31860.75 | G40: =G38*(1-G39) -> 36339.75 | H40: =H38*(1-H39) -> 40677.75 | I40: =I38*(1-I39) -> 44483.25 | J40: =J38*(1-J39) -> 46623.75 | K40: =K38*(1-K39) -> 50128.5
B42: Reinvestment | E42: =SUM(E35:E36) -> 6240 | F42: =SUM(F35:F36) -> 12541 | G42: =SUM(G35:G36) -> 11081 | H42: =SUM(H35:H36) -> -9513 | I42: =SUM(I35:I36) -> 4402 | J42: =SUM(J35:J36) -> 662 | K42: =SUM(K35:K36) -> 15065
B44: Reinvestment Rate | E44: =E42/E40 -> 0.21565578 | F44: =F42/F40 -> 0.39361911 | G44: =G42/G40 -> 0.3049278 | H44: =H42/H40 -> -0.23386249 | I44: =I42/I40 -> 0.098958597 | J44: =J42/J40 -> 0.014198772 | K44: =K42/K40 -> 0.30052764
I45: 4-Years Average Rate | K45: =AVERAGE(H44:K44) -> 0.04495563
I46: 4-Years Median Rate | K46: =MEDIAN(H44:K44) -> 0.056578684
B48: Calculation of Growth Rate | D48: =D33 -> 43555 | E48: =E33 -> 43921 | F48: =F33 -> 44286 | G48: =G33 -> 44651 | H48: =H33 -> 45016 | I48: =I33 -> 45382 | J48: =J33 -> 45747 | K48: =K33 -> 46112
B50: Reinvestment Rate | E50: =E44 -> 0.21565578 | F50: =F44 -> 0.39361911 | G50: =G44 -> 0.3049278 | H50: =H44 -> -0.23386249 | I50: =I44 -> 0.098958597 | J50: =J44 -> 0.014198772 | K50: =K44 -> 0.30052764
B51: ROIC | E51: =E31 -> 0.36588604 | F51: =F31 -> 0.40854448 | G51: =G31 -> 0.39668752 | H51: =H31 -> 0.42622174 | I51: =I31 -> 0.42070904 | J51: =J31 -> 0.40740781 | K51: =K31 -> 0.39628839
B52: Intrinsic Growth | E52: =E50*E51 -> 0.07890544 | F52: =F50*F51 -> 0.16081091 | G52: =G50*G51 -> 0.12096105 | H52: =H50*H51 -> -0.099677277 | I52: =I50*I51 -> 0.041632777 | J52: =J50*J51 -> 0.0057846907 | K52: =K50*K51 -> 0.11909562
I53: 4-Years Average Rate | K53: =AVERAGE(H52:K52) -> 0.016708952
I54: 4-Years Median Rate | K54: =MEDIAN(H52:K52) -> 0.023708734

Sheet DCF
C2: ="DCF-"&'Data Sheet'!B1 -> DCF-TATA CONSULTANCY SERVICES LTD
B4: Calucletion Of Pv FCFF | D4: ='Instrc Growth'!K48 -> 46112 | E4: =D4+365 -> 46477 | F4: =E4+365 -> 46842 | G4: =F4+365 -> 47207 | H4: =G4+365 -> 47572 | I4: =H4+365 -> 47937 | J4: =I4+365 -> 48302
B6: EBIT | D6: ='Historicail Financial Statement'!K23 -> 66838 | E6: =D6*(1+$D$16) -> 76863.7 | F6: =E6*(1+$D$16) -> 88393.255 | G6: =F6*(1+$D$16) -> 101652.24 | H6: =G6*(1+$D$16) -> 116900.08 | I6: =H6*(1+$D$16) -> 134435.09 | J6: =I6*(1+$D$16) -> 154600.36
B7: Tax | D7: 0.25 | E7: 0.25 | F7: 0.25 | G7: 0.25 | H7: 0.25 | I7: 0.25 | J7: 0.25
B8: EBIT(1-TAX Rate) | D8: =D6*(1-D7) -> 50128.5 | E8: =E6*(1-E7) -> 57647.775 | F8: =F6*(1-F7) -> 66294.941 | G8: =G6*(1-G7) -> 76239.182 | H8: =H6*(1-H7) -> 87675.06 | I8: =I6*(1-I7) -> 100826.32 | J8: =J6*(1-J7) -> 115950.27
B9: Less: Reinvestment | D9: ='Instrc Growth'!K45 -> 0.04495563 | E9: =D9+($J$9-$D$9)/4 -> 0.052466723 | F9: =E9+($J$9-$D$9)/4 -> 0.059977815 | G9: =F9+($J$9-$D$9)/4 -> 0.067488908 | H9: =G9+($J$9-$D$9)/4 -> 0.075 | I9: =H9+($J$9-$D$9)/4 -> 0.082511092 | J9: 0.075
B10: Free Cash Flow to Frim | D10: =D8*(1-D9) -> 47874.942 | E10: =E8*(1-E9) -> 54623.185 | F10: =F8*(1-F9) -> 62318.716 | G10: =G8*(1-G9) -> 71093.883 | H10: =H8*(1-H9) -> 81099.43 | I10: =I8*(1-I9) -> 92507.029 | J10: =J8*(1-J9) -> 107254
B11: Mid Year Convenction | E11: 0.5 | F11: =E11+1 -> 1.5 | G11: =F11+1 -> 2.5 | H11: =G11+1 -> 3.5 | I11: =H11+1 -> 4.5 | J11: =I11+1 -> 5.5
B12: Discounting Factor | E12: =1/(1+$D$18)^E11 -> 0.93955339 | F12: =1/(1+$D$18)^F11 -> 0.82940068 | G12: =1/(1+$D$18)^G11 -> 0.73216221 | H12: =1/(1+$D$18)^H11 -> 0.64632393 | I12: =1/(1+$D$18)^I11 -> 0.57054928 | J12: =1/(1+$D$18)^J11 -> 0.5036584
B14: Pv Of FCFF | E14: =E10*E12 -> 51321.399 | F14: =F10*F12 -> 51687.185 | G14: =G10*G12 -> 52052.255 | H14: =H10*H12 -> 52416.502 | I14: =I10*I12 -> 52779.818 | J14: =J10*J12 -> 54019.376
B16: Expected Growth | D16: 0.15
B17: Terminal Growth | D17: 0.05
B18: WACC | D18: =WACC!L34 -> 0.13281
F19: Sensitivity Analysis
B20: Calculation of Terminal Value
F21: =D37 -> 2766.2324 | G21: 0.1 | H21: 0.12 | I21: =D18 -> 0.13281 | J21: 0.15
B22: FCFF(1+n) | D22: =J10*(1+D17) -> 112616.7 | F22: 0.03 | G22: 3112.6726 | H22: 2614.9937 | I22: 2397.958 | J22: 2179.5246
B23: WACC | D23: =D18 -> 0.13281 | F23: =D17 -> 0.05 | G23: 4008.4946 | H23: 3112.6726 | I23: 2766.2324 | J23: 2440.8061
B24: Terminal Growth | D24: =D17 -> 0.05 | F24: 0.07 | G24: 6098.7461 | H24: 4008.4946 | I24: 3369.0392 | J24: 2832.7282
B25: Terminal Value | D25: =D22/(D23-D24) -> 1359940.7 | F25: 0.08 | G25: 8711.5604 | H25: 4792.3389 | I25: 3841.6622 | J25: 3112.6726
B27: Calucletion of Equity Value Per Share
B29: Pv of FCFF | D29: =SUM(E14:J14) -> 314276.54
B30: Pv Of Terminal value | D30: =D25*J12 -> 684945.56
B31: Value of Operating Assets | D31: =D29+D30 -> 999222.1
B33: Add: Cash | D33: ='Data Sheet'!K69 -> 12908
B34: Less:Debt | D34: ='Data Sheet'!K59 -> 11283
B35: Value Of Equity | D35: =D31+D33-D34 -> 1000847.1
B36: Number of Shers | D36: ='Data Sheet'!B6 -> 361.80875
B37: Erquity Value Per Share | D37: =D35/D36 -> 2766.2324
B39: Share pres | D39: ='Data Sheet'!B8 -> 2365.6
B40: Discount/Primem | D40: =D37/D39 -> 1.1693576

Sheet Comps_val
E2: ="Relative Valuation of -"&'Data Sheet'!B1 -> Relative Valuation of -TATA CONSULTANCY SERVICES LTD
B4: Amount In Crores
B5: Comparable Company Valuation
C6: Market Data | J6: Financail | N6: Valuveation
B7: Copmanys | C7: Ticker | D7: Shre Price | E7: Shres Oust Standing | F7: Equity Value | G7: Net Debt | H7: Enterpries value | J7: Revenu | K7: EBITDA | L7: Net income | N7: EV/Revenu | O7: EV/EBITDA | P7: P/E
B9: TCS | D9: =DCF!D39 -> 2365.6 | E9: 361.81 | F9: =D9*E9 -> 855897.74 | G9: -1625 | H9: =F9+G9 -> 854272.74 | J9: 275859 | K9: 28606.578 | L9: 50055 | N9: =H9/J9 -> 3.0967731 | O9: =H9/K9 -> 29.862807 | P9: =F9/L9 -> 17.099146
B10: Infosys | D10: 1087.1 | E10: 405.76 | F10: =D10*E10 -> 441101.7 | G10: -13025 | H10: =F10+G10 -> 428076.7 | J10: 178650 | K10: 16542.99 | L10: 29474 | N10: =H10/J10 -> 2.3961752 | O10: =H10/K10 -> 25.876622 | P10: =F10/L10 -> 14.96579
B11: HCL Technologies | D11: 1221.3 | E11: 271.37 | F11: =D11*E11 -> 331424.18 | G11: -18210 | H11: =F11+G11 -> 313214.18 | J11: 134374 | K11: 14498.955 | L11: 17434 | N11: =H11/J11 -> 2.3309136 | O11: =H11/K11 -> 21.602535 | P11: =F11/L11 -> 19.01022
B12: Wipro | D12: 176.38 | E12: 990.41 | F12: =D12*E12 -> 174688.52 | G12: 9735.5 | H12: =F12+G12 -> 184424.02 | J12: 94968 | K12: 7958.3184 | L12: 13285.3 | N12: =H12/J12 -> 1.9419596 | O12: =H12/K12 -> 23.173742 | P12: =F12/L12 -> 13.149008
B13: Tech Mahindra | D13: 1576.4 | E13: 98.01 | F13: =D13*E13 -> 154502.96 | G13: -2919.2 | H13: =F13+G13 -> 151583.76 | J13: 59176.1 | K13: 9397.1647 | L13: 5163 | N13: =H13/J13 -> 2.5615707 | O13: =H13/K13 -> 16.130798 | P13: =F13/L13 -> 29.925037
B15: High | N15: =MAX(N10:N13) -> 2.5615707 | O15: =MAX(O10:O13) -> 25.876622 | P15: =MAX(P10:P13) -> 29.925037
B16: 75th Percentile | N16: =QUARTILE(N10:N13,3) -> 2.4375241 | O16: =QUARTILE(O10:O13,3) -> 23.849462 | P16: =QUARTILE(P10:P13,3) -> 21.738924
B17: Average | N17: =AVERAGE(N9:N13) -> 2.4654784 | O17: =AVERAGE(O9:O13) -> 23.329301 | P17: =AVERAGE(P9:P13) -> 18.82984
B18: Median | N18: =MEDIAN(N9:N13) -> 2.3961752 | O18: =MEDIAN(O9:O13) -> 23.173742 | P18: =MEDIAN(P9:P13) -> 17.099146
B19: 25 Percentile | N19: =QUARTILE(N9:N13,) -> 1.9419596 | O19: =QUARTILE(O9:O13,) -> 16.130798 | P19: =QUARTILE(P9:P13,) -> 13.149008
B20: Low | N20: =MIN(N9:N13) -> 1.9419596 | O20: =MIN(O9:O13) -> 16.130798 | P20: =MIN(P9:P13) -> 13.149008
B22: Tcs Comparable Valuation | N22: EV/Revenu | O22: EV/EBITDA | P22: P/E
B24: Implied Enterprise Value | N24: =J$9/N18 -> 115124.72 | O24: =K$9/O18 -> 1234.4393 | P24: =P25+P26 -> 854272.74
B25: Net Debt | N25: =$G$9 -> -1625 | O25: =$G$9 -> -1625 | P25: =$G$9 -> -1625
B26: Implied Market Value | N26: =N24-N25 -> 116749.72 | O26: =O24-O25 -> 2859.4393 | P26: =L$9*P18 -> 855897.74
B27: Shares Outstanding | N27: =$E$9 -> 361.81 | O27: =$E$9 -> 361.81 | P27: =$E$9 -> 361.81
B28: Implied Value per Share | N28: =N26/N27 -> 322.68241 | O28: =O26/O27 -> 7.9031517 | P28: =P26/P27 -> 2365.6
N30: =IF(D9>N28,"Undrvalued","Overvalued") -> Undrvalued | O30: =IF(E9>O28,"Undrvalue","Overvalue") -> Undrvalue | P30: =IF(F9>P28,"Undrvalue","Overvalue") -> Undrvalue

Sheet FootballFeledValuvetionAnalysis
C4: FootbollFiled Analysis - Valuation Summary(Rs) | J4: ="Football filed Analysis Data-"&'Data Sheet'!B1 -> Football filed Analysis Data-TATA CONSULTANCY SERVICES LTD
K6: Open low | L6: Low | M6: Open High | N6: high
J7: Comps | K7: 3112.6726 | L7: 3112.6726 | M7: 8711.5604 | N7: 8711.5604
J8: DCF Bare | K8: 2179.5246 | L8: 2179.5246 | M8: 3112.6726 | N8: 3112.6726
J9: DCFBase | K9: 2397.958 | L9: 2397.958 | M9: 3841.6622 | N9: 3841.6622
J10: DCFBull | K10: 2614.9937 | L10: 2614.9937 | M10: 4792.3389 | N10: 4792.3389
J11: 52W H/L | K11: 2745.55 | L11: 2745.55 | M11: 7584.55 | N11: 7584.55

Sheet VAR
F3: ="VAR-"&'Data Sheet'!B1 -> VAR-TATA CONSULTANCY SERVICES LTD
B5: Date | C5: Adj Closing | D5: Retuns | E5: Stanrded Retuns | F5: Replication | G5: Simulated Returns | I5: Caluclation of Value at Risk (Historical)
B6: 45931 | C6: 11.065 | D6: 0 | E6: 0 | F6: 1 | G6: =_xlfn.NORM.INV(RAND(),M$9,M$10) -> -0.0024541454
B7: 45933 | C7: 10.2875 | D7: =C6/C7-1 -> 0.075577157 | E7: 0.075577157 | F7: 2 | G7: =_xlfn.NORM.INV(RAND(),M$9,M$10) -> 0.015005039
B8: 45936 | C8: 10.06 | D8: =C7/C8-1 -> 0.022614314 | E8: 0.022614314 | F8: 3 | G8: =_xlfn.NORM.INV(RAND(),M$9,M$10) -> -0.0067060467 | I8: Historical Approach
B9: 45937 | C9: 10.1925 | D9: =C8/C9-1 -> -0.012999755 | E9: -0.012999755 | F9: 4 | G9: =_xlfn.NORM.INV(RAND(),M$9,M$10) -> 0.079589862 | I9: Mean | M9: =AVERAGE(E6:E127) -> -0.0052925377
B10: 45938 | C10: 10.05 | D10: =C9/C10-1 -> 0.014179104 | E10: 0.014179104 | F10: 5 | G10: =_xlfn.NORM.INV(RAND(),M$9,M$10) -> -0.01486397 | I10: Std Diveation | M10: =_xlfn.STDEV.S(E6:E127) -> 0.061682627
B11: 45939 | C11: 10.3125 | D11: =C10/C11-1 -> -0.025454545 | E11: -0.025454545 | F11: 6 | G11: =_xlfn.NORM.INV(RAND(),M$9,M$10) -> -0.035485931 | I11: Min | M11: =MIN(E6:E127) -> -0.20008757
B12: 45940 | C12: 10.12 | D12: =C11/C12-1 -> 0.019021739 | E12: 0.019021739 | F12: 7 | G12: =_xlfn.NORM.INV(RAND(),M$9,M$10) -> -0.082735187 | I12: Max | M12: =MAX(E6:E127) -> 0.23578418
B13: 45943 | C13: 10.1025 | D13: =C12/C13-1 -> 0.0017322445 | E13: 0.0017322445 | F13: 8 | G13: =_xlfn.NORM.INV(RAND(),M$9,M$10) -> 0.075986939 | I13: CMP | M13: ='Data Sheet'!B6*'Data Sheet'!B8 -> 855894.78
B14: 45944 | C14: 11.0075 | D14: =C13/C14-1 -> -0.08221667 | E14: -0.08221667 | F14: 9 | G14: =_xlfn.NORM.INV(RAND(),M$9,M$10) -> 0.011500883
B15: 45945 | C15: 11.155 | D15: =C14/C15-1 -> -0.01322277 | E15: -0.01322277 | F15: 10 | G15: =_xlfn.NORM.INV(RAND(),M$9,M$10) -> -0.14497769 | I15: Monte Carlo Simulation
B16: 45946 | C16: 10.53 | D16: =C15/C16-1 -> 0.059354226 | E16: 0.059354226 | F16: 11 | G16: =_xlfn.NORM.INV(RAND(),M$9,M$10) -> -0.10198731 | I16: Mean | M16: =AVERAGEA(G6:G10005) -> -0.005326697
B17: 45947 | C17: 10.865 | D17: =C16/C17-1 -> -0.03083295 | E17: -0.03083295 | F17: 12 | G17: =_xlfn.NORM.INV(RAND(),M$9,M$10) -> -0.075619326 | I17: Std Diveation | M17: =_xlfn.STDEV.S(G6:G10005) -> 0.061197714
B18: 45950 | C18: 11.625 | D18: =C17/C18-1 -> -0.065376344 | E18: -0.065376344 | F18: 13 | G18: =_xlfn.NORM.INV(RAND(),M$9,M$10) -> 0.050897816 | I18: Min | M18: =MIN(G6:G10005) -> -0.3064272
B19: 45951 | C19: 11.355 | D19: =C18/C19-1 -> 0.023778071 | E19: 0.023778071 | F19: 14 | G19: =_xlfn.NORM.INV(RAND(),M$9,M$10) -> 0.035687999 | I19: Max | M19: =MAX(G6:G10005) -> 0.21176516
B20: 45953 | C20: 11.2975 | D20: =C19/C20-1 -> 0.0050896216 | E20: 0.0050896216 | F20: 15 | G20: =_xlfn.NORM.INV(RAND(),M$9,M$10) -> -0.047883034 | I20: CMP | M20: =M13 -> 855894.78
B21: 45954 | C21: 11.7325 | D21: =C20/C21-1 -> -0.037076497 | E21: -0.037076497 | F21: 16 | G21: =_xlfn.NORM.INV(RAND(),M$9,M$10) -> -0.010927212
B22: 45957 | C22: 11.59 | D22: =C21/C22-1 -> 0.012295082 | E22: 0.012295082 | F22: 17 | G22: =_xlfn.NORM.INV(RAND(),M$9,M$10) -> 0.026167619 | I22: Percentile | J22: Confidance | K22: VRM% | L22: Stock Price | M22: VAR(INR
B23: 45958 | C23: 11.8575 | D23: =C22/C23-1 -> -0.022559561 | E23: -0.022559561 | F23: 18 | G23: =_xlfn.NORM.INV(RAND(),M$9,M$10) -> -0.014565497 | I23: 0.01 | J23: =100%-I23 -> 0.99 | K23: =_xlfn.PERCENTILE.INC(E9:E69,I23) -> -0.09320381 | L23: =$M$13*(1-K23) -> 935667.43 | M23: =M13-L23 -> -79772.654
B24: 45959 | C24: 11.9525 | D24: =C23/C24-1 -> -0.007948128 | E24: -0.007948128 | F24: 19 | G24: =_xlfn.NORM.INV(RAND(),M$9,M$10) -> -0.078285392 | I24: 0.05 | J24: =100%-I24 -> 0.95 | K24: =_xlfn.PERCENTILE.INC(E10:E70,I24) -> -0.065376344 | L24: =$M$13*(1-K24) -> 911850.05 | M24: =M14-L24 -> -911850.05
B25: 45960 | C25: 11.9725 | D25: =C24/C25-1 -> -0.0016704949 | E25: -0.0016704949 | F25: 20 | G25: =_xlfn.NORM.INV(RAND(),M$9,M$10) -> 0.038307951 | I25: 0.005 | J25: =100%-I25 -> 0.995 | K25: =_xlfn.PERCENTILE.INC(E11:E71,I25) -> -0.10144416 | L25: =$M$13*(1-K25) -> 942720.31 | M25: =M15-L25 -> -942720.31
B26: 45961 | C26: 12.0675 | D26: =C25/C26-1 -> -0.0078723845 | E26: -0.0078723845 | F26: 21 | G26: =_xlfn.NORM.INV(RAND(),M$9,M$10) -> -0.025419339 | I26: 0.1 | J26: =100%-I26 -> 0.9 | K26: =_xlfn.PERCENTILE.INC(E12:E72,I26) -> -0.040465851 | L26: =$M$13*(1-K26) -> 890529.29 | M26: =M16-L26 -> -890529.3
B27: 45964 | C27: 12.1525 | D27: =C26/C27-1 -> -0.0069944456 | E27: -0.0069944456 | F27: 22 | G27: =_xlfn.NORM.INV(RAND(),M$9,M$10) -> -0.0091588986
B28: 45965 | C28: 12.665 | D28: =C27/C28-1 -> -0.040465851 | E28: -0.040465851 | F28: 23 | G28: =_xlfn.NORM.INV(RAND(),M$9,M$10) -> 0.084000087
B29: 45967 | C29: 12.6525 | D29: =C28/C29-1 -> 0.00098794705 | E29: 0.00098794705 | F29: 24 | G29: =_xlfn.NORM.INV(RAND(),M$9,M$10) -> -0.052878565
B30: 45968 | C30: 12.41 | D30: =C29/C30-1 -> 0.019540693 | E30: 0.019540693 | F30: 25 | G30: =_xlfn.NORM.INV(RAND(),M$9,M$10) -> 0.095829495
B31: 45971 | C31: 12.5575 | D31: =C30/C31-1 -> -0.011745969 | E31: -0.011745969 | F31: 26 | G31: =_xlfn.NORM.INV(RAND(),M$9,M$10) -> -0.081005278
B32: 45972 | C32: 12.3 | D32: =C31/C32-1 -> 0.020934959 | E32: 0.020934959 | F32: 27 | G32: =_xlfn.NORM.INV(RAND(),M$9,M$10) -> 0.05839332
B33: 45973 | C33: 12.49 | D33: =C32/C33-1 -> -0.01521217 | E33: -0.01521217 | F33: 28 | G33: =_xlfn.NORM.INV(RAND(),M$9,M$10) -> -0.006483749
B34: 45974 | C34: 12.11 | D34: =C33/C34-1 -> 0.031379026 | E34: 0.031379026 | F34: 29 | G34: =_xlfn.NORM.INV(RAND(),M$9,M$10) -> 0.012146775
B35: 45975 | C35: 12.1625 | D35: =C34/C35-1 -> -0.0043165468 | E35: -0.0043165468 | F35: 30 | G35: =_xlfn.NORM.INV(RAND(),M$9,M$10) -> -0.068526208
B36: 45978 | C36: 11.9375 | D36: =C35/C36-1 -> 0.018848168 | E36: 0.018848168 | F36: 31 | G36: =_xlfn.NORM.INV(RAND(),M$9,M$10) -> -0.021290314
B37: 45979 | C37: 11.7875 | D37: =C36/C37-1 -> 0.012725345 | E37: 0.012725345 | F37: 32 | G37: =_xlfn.NORM.INV(RAND(),M$9,M$10) -> 0.027075306
B38: 45980 | C38: 12.095 | D38: =C37/C38-1 -> -0.025423729 | E38: -0.025423729 | F38: 33 | G38: =_xlfn.NORM.INV(RAND(),M$9,M$10) -> -0.035906716
... B127: 46111 | C127: 26.8025 | D127: =C126/C127-1 -> -0.080682772 | E127: -0.080682772 | F127: 122 | G127: =_xlfn.NORM.INV(RAND(),M$9,M$10) -> -0.024503083
F128: 123 | G128: =_xlfn.NORM.INV(RAND(),M$9,M$10) -> -0.060183242
F129: 124 | G129: =_xlfn.NORM.INV(RAND(),M$9,M$10) -> -0.043812443
F130: 125 | G130: =_xlfn.NORM.INV(RAND(),M$9,M$10) -> -0.049432442
F131: 126 | G131: =_xlfn.NORM.INV(RAND(),M$9,M$10) -> -0.055720383
F132: 127 | G132: =_xlfn.NORM.INV(RAND(),M$9,M$10) -> -0.12611509
F133: 128 | G133: =_xlfn.NORM.INV(RAND(),M$9,M$10) -> -0.035840998
F134: 129 | G134: =_xlfn.NORM.INV(RAND(),M$9,M$10) -> -0.015374073
F135: 130 | G135: =_xlfn.NORM.INV(RAND(),M$9,M$10) -> 0.010721276
F136: 131 | G136: =_xlfn.NORM.INV(RAND(),M$9,M$10) -> -0.0050194501
F137: 132 | G137: =_xlfn.NORM.INV(RAND(),M$9,M$10) -> 0.048876759
F138: 133 | G138: =_xlfn.NORM.INV(RAND(),M$9,M$10) -> -0.092541789
F139: 134 | G139: =_xlfn.NORM.INV(RAND(),M$9,M$10) -> 0.039350555
... F10005: 10000 | G10005: =_xlfn.NORM.INV(RAND(),M$9,M$10) -> 0.085183148

Sheet Dupoint Analysis
B3: ='Data Sheet'!B1 -> TATA CONSULTANCY SERVICES LTD
B4: BSE | (532540)
B5: ="INR"&'Data Sheet'!B8 -> INR2365.6
B6: 52 Weeks(High-3538.0&Low-2206.4
B9: About the company
B15: Financial Summary
B42: Recent Updates :
B54: Dupoint Analysis-Return On Equity&Return On Assets
B55: Return on Equity
D56: ='Historicail Financial Statement'!D4 -> 43555 | E56: ='Historicail Financial Statement'!E4 -> 43921 | F56: ='Historicail Financial Statement'!F4 -> 44286 | G56: ='Historicail Financial Statement'!G4 -> 44651 | H56: ='Historicail Financial Statement'!H4 -> 45016 | I56: ='Historicail Financial Statement'!I4 -> 45382 | J56: ='Historicail Financial Statement'!J4 -> 45747 | K56: ='Historicail Financial Statement'!K4 -> 46112
B57: Net Profit | D57: ='Historicail Financial Statement'!D38 -> 31562 | E57: ='Historicail Financial Statement'!E38 -> 32447 | F57: ='Historicail Financial Statement'!F38 -> 32562 | G57: ='Historicail Financial Statement'!G38 -> 38449 | H57: ='Historicail Financial Statement'!H38 -> 42303 | I57: ='Historicail Financial Statement'!I38 -> 46099 | J57: ='Historicail Financial Statement'!J38 -> 48797 | K57: ='Historicail Financial Statement'!K38 -> 49454
B58: Average Equity Shareholer Capital | D58: =('Data Sheet'!D57+'Data Sheet'!C57)+('Data Sheet'!D58+'Data Sheet'!C58)/2 -> 87570 | E58: =('Data Sheet'!E57+'Data Sheet'!D57)+('Data Sheet'!E58+'Data Sheet'!D58)/2 -> 87161 | F58: =('Data Sheet'!F57+'Data Sheet'!E57)+('Data Sheet'!F58+'Data Sheet'!E58)/2 -> 85652 | G58: =('Data Sheet'!G57+'Data Sheet'!F57)+('Data Sheet'!G58+'Data Sheet'!F58)/2 -> 88154 | H58: =('Data Sheet'!H57+'Data Sheet'!G57)+('Data Sheet'!H58+'Data Sheet'!G58)/2 -> 90147.5 | I58: =('Data Sheet'!I57+'Data Sheet'!H57)+('Data Sheet'!I58+'Data Sheet'!H58)/2 -> 90820.5 | J58: =('Data Sheet'!J57+'Data Sheet'!I57)+('Data Sheet'!J58+'Data Sheet'!I58)/2 -> 92984.5 | K58: =('Data Sheet'!K57+'Data Sheet'!J57)+('Data Sheet'!K58+'Data Sheet'!J58)/2 -> 101360
B59: Return on Eruity | D59: =D57/D58 -> 0.36042024 | E59: =E57/E58 -> 0.37226512 | F59: =F57/F58 -> 0.38016625 | G59: =G57/G58 -> 0.43615718 | H59: =H57/H58 -> 0.46926426 | I59: =I57/I58 -> 0.50758364 | J59: =J57/J58 -> 0.52478639 | K59: =K57/K58 -> 0.4879045
B61: ROE-Dupoint Equation
D62: =D56 -> 43555 | E62: =E56 -> 43921 | F62: =F56 -> 44286 | G62: =G56 -> 44651 | H62: =H56 -> 45016 | I62: =I56 -> 45382 | J62: =J56 -> 45747 | K62: =K56 -> 46112
B63: Net Profit | D63: =D57 -> 31562 | E63: =E57 -> 32447 | F63: =F57 -> 32562 | G63: =G57 -> 38449 | H63: =H57 -> 42303 | I63: =I57 -> 46099 | J63: =J57 -> 48797 | K63: =K57 -> 49454
B64: Revenu | D64: ='Historicail Financial Statement'!D7 -> 146463 | E64: ='Historicail Financial Statement'!E7 -> 156949 | F64: ='Historicail Financial Statement'!F7 -> 164177 | G64: ='Historicail Financial Statement'!G7 -> 191754 | H64: ='Historicail Financial Statement'!H7 -> 225458 | I64: ='Historicail Financial Statement'!I7 -> 240893 | J64: ='Historicail Financial Statement'!J7 -> 255324 | K64: ='Historicail Financial Statement'!K7 -> 267021
B65: Net Profit Margin(A) | D65: =D63/D64 -> 0.2154947 | E65: =E63/E64 -> 0.20673595 | F65: =F63/F64 -> 0.19833472 | G65: =G63/G64 -> 0.20051211 | H65: =H63/H64 -> 0.1876314 | I65: =I63/I64 -> 0.19136712 | J65: =J63/J64 -> 0.19111795 | K65: =K63/K64 -> 0.18520641
B67: =B64 -> Revenu | D67: =D64 -> 146463 | E67: =E64 -> 156949 | F67: =F64 -> 164177 | G67: =G64 -> 191754 | H67: =H64 -> 225458 | I67: =I64 -> 240893 | J67: =J64 -> 255324 | K67: =K64 -> 267021
B68: Average Total Assets | D68: =('Data Sheet'!D66+'Data Sheet'!C66)/2 -> 109513.5 | E68: =('Data Sheet'!E66+'Data Sheet'!D66)/2 -> 117014 | F68: =('Data Sheet'!F66+'Data Sheet'!E66)/2 -> 125059.5 | G68: =('Data Sheet'!G66+'Data Sheet'!F66)/2 -> 135458 | H68: =('Data Sheet'!H66+'Data Sheet'!G66)/2 -> 141891.5 | I68: =('Data Sheet'!I66+'Data Sheet'!H66)/2 -> 144165.5 | J68: =('Data Sheet'!J66+'Data Sheet'!I66)/2 -> 152060.5 | K68: =('Data Sheet'!K66+'Data Sheet'!J66)/2 -> 169908
B69: Average Turnover Ratio(B) | D69: =D67/D68 -> 1.3373968 | E69: =E67/E68 -> 1.3412839 | F69: =F67/F68 -> 1.3127911 | G69: =G67/G68 -> 1.4155975 | H69: =H67/H68 -> 1.5889465 | I69: =I67/I68 -> 1.6709476 | J69: =J67/J68 -> 1.6790948 | K69: =K67/K68 -> 1.5715623
B71: =B68 -> Average Total Assets | D71: =D68 -> 109513.5 | E71: =E68 -> 117014 | F71: =F68 -> 125059.5 | G71: =G68 -> 135458 | H71: =H68 -> 141891.5 | I71: =I68 -> 144165.5 | J71: =J68 -> 152060.5 | K71: =K68 -> 169908
B72: =B58 -> Average Equity Shareholer Capital | D72: =D58 -> 87570 | E72: =E58 -> 87161 | F72: =F58 -> 85652 | G72: =G58 -> 88154 | H72: =H58 -> 90147.5 | I72: =I58 -> 90820.5 | J72: =J58 -> 92984.5 | K72: =K58 -> 101360
B73: Equity Muliplier ( C ) | D73: =D71/D72 -> 1.2505824 | E73: =E71/E72 -> 1.3425041 | F73: =F71/F72 -> 1.4600885 | G73: =G71/G72 -> 1.5366064 | H73: =H71/H72 -> 1.5739926 | I73: =I71/I72 -> 1.5873674 | J73: =J71/J72 -> 1.6353317 | K73: =K71/K72 -> 1.6762826
B75: Return on Equity (A*B*C) | D75: =D65*D69*D73 -> 0.36042024 | E75: =E65*E69*E73 -> 0.37226512 | F75: =F65*F69*F73 -> 0.38016625 | G75: =G65*G69*G73 -> 0.43615718 | H75: =H65*H69*H73 -> 0.46926426 | I75: =I65*I69*I73 -> 0.50758364 | J75: =J65*J69*J73 -> 0.52478639 | K75: =K65*K69*K73 -> 0.4879045
B77: Return on Asset
D78: =D62 -> 43555 | E78: =E62 -> 43921 | F78: =F62 -> 44286 | G78: =G62 -> 44651 | H78: =H62 -> 45016 | I78: =I62 -> 45382 | J78: =J62 -> 45747 | K78: =K62 -> 46112
B79: =B57 -> Net Profit | D79: =D63 -> 31562 | E79: =E63 -> 32447 | F79: =F63 -> 32562 | G79: =G63 -> 38449 | H79: =H63 -> 42303 | I79: =I63 -> 46099 | J79: =J63 -> 48797 | K79: =K63 -> 49454
B80: =B68 -> Average Total Assets | D80: =D68 -> 109513.5 | E80: =E68 -> 117014 | F80: =F68 -> 125059.5 | G80: =G68 -> 135458 | H80: =H68 -> 141891.5 | I80: =I68 -> 144165.5 | J80: =J68 -> 152060.5 | K80: =K68 -> 169908
B81: Return on Assets | D81: =D79/D80 -> 0.28820191 | E81: =E79/E80 -> 0.27729161 | F81: =F79/F80 -> 0.26037206 | G81: =G79/G80 -> 0.28384444 | H81: =H79/H80 -> 0.29813625 | I81: =I79/I80 -> 0.31976444 | J81: =J79/J80 -> 0.32090517 | K81: =K79/K80 -> 0.2910634
B83: ROA-Dupoint Equation
D84: =D78 -> 43555 | E84: =E78 -> 43921 | F84: =F78 -> 44286 | G84: =G78 -> 44651 | H84: =H78 -> 45016 | I84: =I78 -> 45382 | J84: =J78 -> 45747 | K84: =K78 -> 46112
B85: =B79 -> Net Profit | D85: =D79 -> 31562 | E85: =E79 -> 32447 | F85: =F79 -> 32562 | G85: =G79 -> 38449 | H85: =H79 -> 42303 | I85: =I79 -> 46099 | J85: =J79 -> 48797 | K85: =K79 -> 49454
B86: =B64 -> Revenu | D86: =D67 -> 146463 | E86: =E67 -> 156949 | F86: =F67 -> 164177 | G86: =G67 -> 191754 | H86: =H67 -> 225458 | I86: =I67 -> 240893 | J86: =J67 -> 255324 | K86: =K67 -> 267021
B87: =B65 -> Net Profit Margin(A) | D87: =D85/D86 -> 0.2154947 | E87: =E85/E86 -> 0.20673595 | F87: =F85/F86 -> 0.19833472 | G87: =G85/G86 -> 0.20051211 | H87: =H85/H86 -> 0.1876314 | I87: =I85/I86 -> 0.19136712 | J87: =J85/J86 -> 0.19111795 | K87: =K85/K86 -> 0.18520641
B89: =B67 -> Revenu | D89: =D86 -> 146463 | E89: =E86 -> 156949 | F89: =F86 -> 164177 | G89: =G86 -> 191754 | H89: =H86 -> 225458 | I89: =I86 -> 240893 | J89: =J86 -> 255324 | K89: =K86 -> 267021
B90: =B80 -> Average Total Assets | D90: =D80 -> 109513.5 | E90: =E80 -> 117014 | F90: =F80 -> 125059.5 | G90: =G80 -> 135458 | H90: =H80 -> 141891.5 | I90: =I80 -> 144165.5 | J90: =J80 -> 152060.5 | K90: =K80 -> 169908
B91: =B69 -> Average Turnover Ratio(B) | D91: =D89/D90 -> 1.3373968 | E91: =E89/E90 -> 1.3412839 | F91: =F89/F90 -> 1.3127911 | G91: =G89/G90 -> 1.4155975 | H91: =H89/H90 -> 1.5889465 | I91: =I89/I90 -> 1.6709476 | J91: =J89/J90 -> 1.6790948 | K91: =K89/K90 -> 1.5715623
B93: Return on Asset | D93: =D87*D91 -> 0.28820191 | E93: =E87*E91 -> 0.27729161 | F93: =F87*F91 -> 0.26037206 | G93: =G87*G91 -> 0.28384444 | H93: =H87*H91 -> 0.29813625 | I93: =I87*I91 -> 0.31976444 | J93: =J87*J91 -> 0.32090517 | K93: =K87*K91 -> 0.2910634
B94: Dupoint Summary

Sheet Altman's Zscore Analysis
B3: ='Data Sheet'!B1 -> TATA CONSULTANCY SERVICES LTD
B4: BSE | (532540)
B5: ="INR"&'Data Sheet'!B8 -> INR2365.6
B6: 52 Weeks(High-3538.0&Low-2206.4
B9: Altman's Z Score analysis
B15: Financial Summary
B42: Recent Updates :
B54: Altman's Z Score-Calucletion
B55: Working Capital/Total Assets
D56: ='Historicail Financial Statement'!D4 -> 43555 | E56: ='Historicail Financial Statement'!E4 -> 43921 | F56: ='Historicail Financial Statement'!F4 -> 44286 | G56: ='Historicail Financial Statement'!G4 -> 44651 | H56: ='Historicail Financial Statement'!H4 -> 45016 | I56: ='Historicail Financial Statement'!I4 -> 45382 | J56: ='Historicail Financial Statement'!J4 -> 45747 | K56: ='Historicail Financial Statement'!K4 -> 46112
B57: Working Capital | D57: ='Instrc Growth'!D18 -> 2963 | E57: ='Instrc Growth'!E18 -> 2710 | F57: ='Instrc Growth'!F18 -> -5677 | G57: ='Instrc Growth'!G18 -> -2137 | H57: ='Instrc Growth'!H18 -> 5235 | I57: ='Instrc Growth'!I18 -> 6643 | J57: ='Instrc Growth'!J18 -> 4566 | K57: ='Instrc Growth'!K18 -> 5099
B58: Total assets | D58: ='Data Sheet'!D66 -> 113901 | E58: ='Data Sheet'!E66 -> 120127 | F58: ='Data Sheet'!F66 -> 129992 | G58: ='Data Sheet'!G66 -> 140924 | H58: ='Data Sheet'!H66 -> 142859 | I58: ='Data Sheet'!I66 -> 145472 | J58: ='Data Sheet'!J66 -> 158649 | K58: ='Data Sheet'!K66 -> 181167
B59: Working Capital /Total Assets (A) | D59: =D57/D58 -> 0.026013819 | E59: =E57/E58 -> 0.022559458 | F59: =F57/F58 -> -0.043671918 | G59: =G57/G58 -> -0.015164202 | H59: =H57/H58 -> 0.036644524 | I59: =I57/I58 -> 0.045665145 | J59: =J57/J58 -> 0.028780515 | K59: =K57/K58 -> 0.028145302
B61: Retade Ernings/Total Assets
D62: =D56 -> 43555 | E62: =E56 -> 43921 | F62: =F56 -> 44286 | G62: =G56 -> 44651 | H62: =H56 -> 45016 | I62: =I56 -> 45382 | J62: =J56 -> 45747 | K62: =K56 -> 46112
B63: Retade Ernings | D63: ='Historicail Financial Statement'!D41*'Historicail Financial Statement'!D43*'Historicail Financial Statement'!D49 -> 20312 | E63: ='Historicail Financial Statement'!E41*'Historicail Financial Statement'!E43*'Historicail Financial Statement'!E49 -> 5072 | F63: ='Historicail Financial Statement'!F41*'Historicail Financial Statement'!F43*'Historicail Financial Statement'!F49 -> 18502 | G63: ='Historicail Financial Statement'!G41*'Historicail Financial Statement'!G43*'Historicail Financial Statement'!G49 -> 22711 | H63: ='Historicail Financial Statement'!H41*'Historicail Financial Statement'!H43*'Historicail Financial Statement'!H49 -> 213 | I63: ='Historicail Financial Statement'!I41*'Historicail Financial Statement'!I43*'Historicail Financial Statement'!I49 -> 19673 | J63: ='Historicail Financial Statement'!J41*'Historicail Financial Statement'!J43*'Historicail Financial Statement'!J49 -> 3185 | K63: ='Historicail Financial Statement'!K41*'Historicail Financial Statement'!K43*'Historicail Financial Statement'!K49 -> 9634
B64: =B58 -> Total assets | D64: =D58 -> 113901 | E64: =E58 -> 120127 | F64: =F58 -> 129992 | G64: =G58 -> 140924 | H64: =H58 -> 142859 | I64: =I58 -> 145472 | J64: =J58 -> 158649 | K64: =K58 -> 181167
B65: Retade Ernings/Total Assets (B) | D65: =D63/D64 -> 0.1783303 | E65: =E63/E64 -> 0.042221982 | F65: =F63/F64 -> 0.14233184 | G65: =G63/G64 -> 0.16115779 | H65: =H63/H64 -> 0.0014909806 | I65: =I63/I64 -> 0.13523565 | J65: =J63/J64 -> 0.020075765 | K65: =K63/K64 -> 0.053177455
B67: EBIT/Total Assets
D68: =D62 -> 43555 | E68: =E62 -> 43921 | F68: =F62 -> 44286 | G68: =G62 -> 44651 | H68: =H62 -> 45016 | I68: =I62 -> 45382 | J68: =J62 -> 45747 | K68: =K62 -> 46112
B69: EBIT | D69: ='Historicail Financial Statement'!D32 -> 41563 | E69: ='Historicail Financial Statement'!E32 -> 42248 | F69: ='Historicail Financial Statement'!F32 -> 43760 | G69: ='Historicail Financial Statement'!G32 -> 51687 | H69: ='Historicail Financial Statement'!H32 -> 56907 | I69: ='Historicail Financial Statement'!I32 -> 61997 | J69: ='Historicail Financial Statement'!J32 -> 65331 | K69: ='Historicail Financial Statement'!K32 -> 65487
B70: =B64 -> Total assets | D70: =D64 -> 113901 | E70: =E64 -> 120127 | F70: =F64 -> 129992 | G70: =G64 -> 140924 | H70: =H64 -> 142859 | I70: =I64 -> 145472 | J70: =J64 -> 158649 | K70: =K64 -> 181167
B71: Average Turnover Ratio(C) | D71: =D69/D70 -> 0.36490461 | E71: =E69/E70 -> 0.35169446 | F71: =F69/F70 -> 0.3366361 | G71: =G69/G70 -> 0.36677216 | H71: =H69/H70 -> 0.39834382 | I71: =I69/I70 -> 0.42617823 | J71: =J69/J70 -> 0.41179585 | K71: =K69/K70 -> 0.36147312
B73: Market Cap /Long term Libuilities
D74: =D68 -> 43555 | E74: =E68 -> 43921 | F74: =F68 -> 44286 | G74: =G68 -> 44651 | H74: =H68 -> 45016 | I74: =I68 -> 45382 | J74: =J68 -> 45747 | K74: =K68 -> 46112
B75: Markrt Cap | D75: ='Data Sheet'!D70*'Data Sheet'!D90/1000000000 -> 7510.9608 | E75: ='Data Sheet'!E70*'Data Sheet'!E90/1000000000 -> 6852.2297 | F75: ='Data Sheet'!F70*'Data Sheet'!F90/1000000000 -> 11755.03 | G75: ='Data Sheet'!G70*'Data Sheet'!G90/1000000000 -> 13684.669 | H75: ='Data Sheet'!H70*'Data Sheet'!H90/1000000000 -> 11730.553 | I75: ='Data Sheet'!I70*'Data Sheet'!I90/1000000000 -> 14024.793 | J75: ='Data Sheet'!J70*'Data Sheet'!J90/1000000000 -> 13047.366 | K75: ='Data Sheet'!K70*'Data Sheet'!K90/1000000000 -> 8534.7066
B76: Long term Libuilities | D76: ='Data Sheet'!D59+'Data Sheet'!D60 -> 24455 | E76: ='Data Sheet'!E59+'Data Sheet'!E60 -> 36001 | F76: ='Data Sheet'!F59+'Data Sheet'!F60 -> 43559 | G76: ='Data Sheet'!G59+'Data Sheet'!G60 -> 51785 | H76: ='Data Sheet'!H59+'Data Sheet'!H60 -> 52435 | I76: ='Data Sheet'!I59+'Data Sheet'!I60 -> 54983 | J76: ='Data Sheet'!J59+'Data Sheet'!J60 -> 63893 | K76: ='Data Sheet'!K59+'Data Sheet'!K60 -> 73927
B77: Markrt Cap/Long Term Libuilites | D77: =D75/D76 -> 0.30713395 | E77: =E75/E76 -> 0.19033443 | F77: =F75/F76 -> 0.26986456 | G77: =G75/G76 -> 0.26425933 | H77: =H75/H76 -> 0.22371608 | I77: =I75/I76 -> 0.25507507 | J77: =J75/J76 -> 0.20420651 | K77: =K75/K76 -> 0.11544776
B79: Sales/Total Assets
D80: =D68 -> 43555 | E80: =E68 -> 43921 | F80: =F68 -> 44286 | G80: =G68 -> 44651 | H80: =H68 -> 45016 | I80: =I68 -> 45382 | J80: =J68 -> 45747 | K80: =K68 -> 46112
B81: Sales | D81: ='Historicail Financial Statement'!D7 -> 146463 | E81: ='Historicail Financial Statement'!E7 -> 156949 | F81: ='Historicail Financial Statement'!F7 -> 164177 | G81: ='Historicail Financial Statement'!G7 -> 191754 | H81: ='Historicail Financial Statement'!H7 -> 225458 | I81: ='Historicail Financial Statement'!I7 -> 240893 | J81: ='Historicail Financial Statement'!J7 -> 255324 | K81: ='Historicail Financial Statement'!K7 -> 267021
B82: Total assets | D82: =D70 -> 113901 | E82: =E70 -> 120127 | F82: =F70 -> 129992 | G82: =G70 -> 140924 | H82: =H70 -> 142859 | I82: =I70 -> 145472 | J82: =J70 -> 158649 | K82: =K70 -> 181167
B83: Sales/Total Assets | D83: =D81/D82 -> 1.2858798 | E83: =E81/E82 -> 1.3065256 | F83: =F81/F82 -> 1.2629777 | G83: =G81/G82 -> 1.3606909 | H83: =H81/H82 -> 1.5781855 | I83: =I81/I82 -> 1.6559407 | J83: =J81/J82 -> 1.6093641 | K83: =K81/K82 -> 1.4738943
B85: Altman's Z Score
D86: =D62 -> 43555 | E86: =E62 -> 43921 | F86: =F62 -> 44286 | G86: =G62 -> 44651 | H86: =H62 -> 45016 | I86: =I62 -> 45382 | J86: =J62 -> 45747 | K86: =K62 -> 46112
B87: Finanl Score | D87: =(D59*1.2)+(D65*1.4)+(D71*3.3)+(D77*0.6)+(D83*1) -> 2.9552244 | E87: =(E59*1.2)+(E65*1.4)+(E71*3.3)+(E77*0.6)+(E83*1) -> 2.6675001 | F87: =(F59*1.2)+(F65*1.4)+(F71*3.3)+(F77*0.6)+(F83*1) -> 2.6826539 | G87: =(G59*1.2)+(G65*1.4)+(G71*3.3)+(G77*0.6)+(G83*1) -> 2.9370185 | H87: =(H59*1.2)+(H65*1.4)+(H71*3.3)+(H77*0.6)+(H83*1) -> 3.0730105 | I87: =(I59*1.2)+(I65*1.4)+(I71*3.3)+(I77*0.6)+(I83*1) -> 3.459502 | J87: =(J59*1.2)+(J65*1.4)+(J71*3.3)+(J77*0.6)+(J83*1) -> 3.153457 | K87: =(K59*1.2)+(K65*1.4)+(K71*3.3)+(K77*0.6)+(K83*1) -> 2.844247
B88: Financail Staibulety | D88: =IF(D87<1.81,"Disterred",IF(D87>3,"Stong","GrayZone")) -> GrayZone | E88: =IF(E87<1.81,"Disterred",IF(E87>3,"Stong","GrayZone")) -> GrayZone | F88: =IF(F87<1.81,"Disterred",IF(F87>3,"Stong","GrayZone")) -> GrayZone | G88: =IF(G87<1.81,"Disterred",IF(G87>3,"Stong","GrayZone")) -> GrayZone | H88: =IF(H87<1.81,"Disterred",IF(H87>3,"Stong","GrayZone")) -> Stong | I88: =IF(I87<1.81,"Disterred",IF(I87>3,"Stong","GrayZone")) -> Stong | J88: =IF(J87<1.81,"Disterred",IF(J87>3,"Stong","GrayZone")) -> Stong | K88: =IF(K87<1.81,"Disterred",IF(K87>3,"Stong","GrayZone")) -> GrayZone

Sheet TCS-LBO
C2: TCS-LBO
B4: Caluclation of Income Statement | D4: ='Historicail Financial Statement'!K4 -> 46112 | E4: =D4+365 -> 46477 | F4: =E4+365 -> 46842 | G4: =F4+365 -> 47207 | H4: =G4+365 -> 47572 | J4: Company Data
J5: Share price | K5: ='Data Sheet'!B8 -> 2365.6
B6: Sales | D6: ='Historicail Financial Statement'!K7 -> 267021 | E6: =D6*(1+E20) -> 293723.1 | F6: =E6*(1+F20) -> 323095.41 | G6: =F6*(1+G20) -> 355404.95 | H6: =G6*(1+H20) -> 390945.45 | J6: Shares outstanding | K6: ='Data Sheet'!B6 -> 361.80875
B7: COGS | D7: ='Historicail Financial Statement'!K10 -> 4399 | E7: =E6*E21 -> 4838.9 | F7: =F6*F21 -> 5322.79 | G7: =G6*G21 -> 5855.069 | H7: =H6*H21 -> 6440.5759 | J7: Market Cap | K7: =K5*K6 -> 855894.78
B8: Gross profit | D8: =D6-D7 -> 262622 | E8: =E6-E7 -> 288884.2 | F8: =F6-F7 -> 317772.62 | G8: =G6-G7 -> 349549.88 | H8: =H6-H7 -> 384504.87 | J8: Existing net debt | K8: ='One Page Profil'!L51 -> 11283
B9: G&A Expenses | D9: ='Historicail Financial Statement'!K15 -> 190224 | E9: =E6*E22 -> 209246.4 | F9: =F6*F22 -> 230171.04 | G9: =G6*G22 -> 253188.14 | H9: =H6*H22 -> 278506.96 | J9: Enterprise value | K9: =K7+K8 -> 867177.78
B10: EBITDA | D10: =D8-D9 -> 72398 | E10: =E8-E9 -> 79637.8 | F10: =F8-F9 -> 87601.58 | G10: =G8-G9 -> 96361.738 | H10: =H8-H9 -> 105997.91 | J10: Current EBITDA | K10: =D10 -> 72398
B11: Depreciation | D11: ='Historicail Financial Statement'!K20 -> 5560 | E11: =E23 -> 5560 | F11: =F23 -> 5560 | G11: =G23 -> 5560 | H11: =H23 -> 5560 | J11: EV/EBITDA multiple | K11: =K9/K10 -> 11.977925
B12: EBIT | D12: =D10-D11 -> 66838 | E12: =E10-E11 -> 74077.8 | F12: =F10-F11 -> 82041.58 | G12: =G10-G11 -> 90801.738 | H12: =H10-H11 -> 100437.91 | J12: Tax rate | K12: 0.25
B13: Interest(-) | D13: ='Historicail Financial Statement'!K26 -> 1227 | E13: =E37+E38 -> -28597.21 | F13: =F37+F38 -> -25050.456 | G13: =G37+G38 -> -18229.839 | H13: =H37+H38 -> -11264.207 | J13: Working Cap as % of sales | K13: ='Instrc Growth'!K18/'Historicail Financial Statement'!K7 -> 0.019095876
B14: EBT | D14: =D12-D13 -> 65611 | E14: =E12+E13 -> 45480.59 | F14: =F12-F13 -> 107092.04 | G14: =G12-G13 -> 109031.58 | H14: =H12-H13 -> 111702.12
B15: Tax | D15: ='Historicail Financial Statement'!K35 -> 16033 | E15: =E14*$K$12 -> 11370.147 | F15: =F14*$K$12 -> 26773.009 | G15: =G14*$K$12 -> 27257.894 | H15: =H14*$K$12 -> 27925.53 | J15: Debt Facilities
B16: Net Profit | D16: =D14-D15 -> 49578 | E16: =E14-E15 -> 34110.442 | F16: =F14-F15 -> 80319.027 | G16: =G14-G15 -> 81773.683 | H16: =H14-H15 -> 83776.589 | K16: EBITDA multiple
J17: Term A | K17: 3
B18: KPI's | J18: Term B | K18: 3.5
K19: Intrast Reat
B20: Sales Growth % | D20: - | E20: 0.1 | F20: 0.1 | G20: 0.1 | H20: 0.1 | J20: Term A | K20: 0.05
B21: Cogs% | D21: =$D$7/$D$6 -> 0.01647436 | E21: =$D$7/$D$6 -> 0.01647436 | F21: =$D$7/$D$6 -> 0.01647436 | G21: =$D$7/$D$6 -> 0.01647436 | H21: =$D$7/$D$6 -> 0.01647436 | J21: Term B | K21: 0.07
B22: G&A EXP% | D22: =$D$9/$D$6 -> 0.71239341 | E22: =$D$9/$D$6 -> 0.71239341 | F22: =$D$9/$D$6 -> 0.71239341 | G22: =$D$9/$D$6 -> 0.71239341 | H22: =$D$9/$D$6 -> 0.71239341
B23: Deprciation % | D23: =$D$11 -> 5560 | E23: =$D$11 -> 5560 | F23: =$D$11 -> 5560 | G23: =$D$11 -> 5560 | H23: =$D$11 -> 5560 | J23: Term A repayment (yearly) | K23: 600
B25: Cash Flow Calculation | J25: Maximum amount of debt
B26: Net Income | D26: =D16 -> 49578 | E26: =E16 -> 34110.442 | F26: =F16 -> 80319.027 | G26: =G16 -> 81773.683 | H26: =H16 -> 83776.589 | J26: Term A | K26: =K10*K17 -> 217194
B27: Add-back D&A | D27: =D11 -> 5560 | E27: =E11 -> 5560 | F27: =F11 -> 5560 | G27: =G11 -> 5560 | H27: =H11 -> 5560 | J27: Term B | K27: =K10*K18 -> 253393
B28: Change in Working Capital | D28: =D6*$K$13 -> 5099 | E28: =E6*$K$13 -> 5608.9 | F28: =F6*$K$13 -> 6169.79 | G28: =G6*$K$13 -> 6786.769 | H28: =H6*$K$13 -> 7465.4459 | J28: Total debt | K28: =K26+K27 -> 470587
B29: CAPEX | D29: =D27 -> 5560 | E29: =E27 -> 5560 | F29: =F27 -> 5560 | G29: =G27 -> 5560 | H29: =H27 -> 5560
B30: Cash available for reimbursement | D30: =SUM(D26:D29) -> 65797 | E30: =SUM(E26:E29) -> 50839.342 | F30: =SUM(F26:F29) -> 97608.817 | G30: =SUM(G26:G29) -> 99680.452 | H30: =SUM(H26:H29) -> 102362.04 | J30: Acquisition premium | K30: 0.3
J31: Equity value with premium | K31: =K9*(1+K30) -> 1127331.1
B32: Debt structure | J32: Enterprise value at acquisition | K32: =K31+K8 -> 1138614.1
B33: Term A outstanding | E33: =K26 -> 217194 | F33: =E33+E41 -> 216594 | G33: =F33+F41 -> 215994 | H33: =G33+G41 -> 215394
B34: Term B outstanding | E34: =K27 -> 253393 | F34: =E34+E42 -> 203153.66 | G34: =F34+F42 -> 106144.84 | H34: =G34+G42 -> 7064.3889 | J34: Equity needed | K34: =K32-K28 -> 668027.11
B36: Interest amount: | J36: Lenders Covenants
B37: Term A | E37: =-E33*$K$20 -> -10859.7 | F37: =-F33*$K$20 -> -10829.7 | G37: =-G33*$K$20 -> -10799.7 | H37: =-H33*$K$20 -> -10769.7 | J37: No dividends distributed until 5 years
B38: Term B | E38: =-E34*$K$21 -> -17737.51 | F38: =-F34*$K$21 -> -14220.756 | G38: =-G34*$K$21 -> -7430.1388 | H38: =-H34*$K$21 -> -494.50722 | J38: Term A required payment of 400m per year
B40: Repayments:
B41: Term A | E41: =-$K$23 -> -600 | F41: =-$K$23 -> -600 | G41: =-$K$23 -> -600 | H41: =-$K$23 -> -600
B42: Term B | E42: =-E30-E41 -> -50239.342 | F42: =-F30-F41 -> -97008.817 | G42: =-G30-G41 -> -99080.452 | H42: =-H30-H41 -> -101762.04
B44: Outstanding at the end of 20x6
B45: Term A | D45: =H33+H37 -> 204624.3
B46: Term B | D46: =H34+(H38) -> 6569.8816
B48: Implied Enterprise value at exit | D48: =H10*K11 -> 1269635
B49: Net Debt at exit | D49: =D45+D46 -> 211194.18
B50: Implied value at exit | D50: =D48-D49 -> 1058440.8
B51: Investors Cash Flows | D51: =-K34 -> -668027.11 | E51: 0 | F51: 0 | G51: 0 | H51: =D50 -> 1058440.8
B52: IRR Equity | D52: =IRR(D51:H51) -> 0.1219361
B54: Cash-on-cash ratio | C54: =-H51/D51 -> 1.5844279
E56: Sensitivity Analysis
E58: =J11 -> EV/EBITDA multiple
D59: =D52 -> 0.1219361 | E59: 8 | F59: 10 | G59: 11.98 | H59: 13 | I59: 15
D60: 0.08 | E60: -0.019315147 | F60: 0.054510137 | G60: 0.1148877 | H60: 0.14251094 | I60: 0.1914995
D61: 0.1 | E61: -0.01190117 | F61: 0.061697741 | G61: 0.12199439 | H61: 0.14960488 | I61: 0.19860142
D62: 0.12 | E62: -0.0046504215 | F62: 0.068742262 | G62: 0.12896855 | H62: 0.15656987 | I62: 0.2055793
D63: 0.14 | E63: 0.0024452462 | F63: 0.075650175 | G63: 0.1358158 | H63: 0.16341125 | I63: 0.21243808

Sheet TCS-M&A Modeling
B2: TCS&Birlasoftltd-M&A
B4: KEY ASSUMPTIONS
B6: Financial Inputs
B8: TCS (Buyer)
B9: Current Share Price | E9: ='TCS-LBO'!K5 -> 2365.6
B10: Shares Outstanding | E10: ='TCS-LBO'!K6 -> 361.80875
B11: Net Income | E11: ='Historicail Financial Statement'!K7 -> 267021
B12: Tax Rate (%) | E12: 0.25
B13: Cost of Debt (%) | E13: =WACC!E20 -> 0.07125
B15: Brilasoft(Seller)
B16: Current Share Price | E16: 323
B17: Shares Outstanding | E17: 27.9
B18: Net Income | E18: 5309.96
B19: Tax Rate (%) | E19: 0.22
B20: Cost of Debt (%) | E20: 0.075
B22: Transaction Assumptions
B24: Target Premium (%) | E24: 0.5
B25: Cash Consideration (%) | E25: 0.2
B26: Stock Consideration (%) | E26: 0.5
B27: Debt Consideration (%) | E27: 0.3
B28: Pre-Tax Synergies | E28: 50
B29: Transaction Fees | E29: 5
B31: TRANSACTION & PROFORMA CALCULATIONS
B33: A. Purchase Price & Financing
B34: Purchase Price per Share | E34: =E16*(1+E24) -> 484.5
B35: Total Equity Value (Purchase Price) | E35: =E34*E17 -> 13517.55
B36: Cash Required | E36: =$E$35*E25 -> 2703.51
B37: Stock Required | E37: =$E$35*E26 -> 6758.775
B38: Debt Required | E38: =$E$35*E27 -> 4055.265
B39: Total Consideration (Check) | E39: =SUM(E36:E38) -> 13517.55
B41: B. Coforhe Net Income
B42: TCS Net Income | E42: =E11 -> 267021
B43: Target Net Income | E43: =E18 -> 5309.96
B44: Synergies (After-Tax) | E44: =E28*(1-E12) -> 37.5
B45: New Interest Expense (After-Tax) | E45: =E38*E13*(1-E12) -> 216.70322
B46: BirlaSoft Net Income | E46: =SUM(E42:E44)-E45-E29 -> 272146.76
B48: C. Coforge Shares Outstanding (millions)
B49: Tcs Shares Outstanding | E49: =E10 -> 361.80875
B50: New Shares Issued | E50: =E37/E9 -> 2.8571081
B51: BirlaSoft Shares Outstanding | E51: =E49+E50 -> 364.66586
B53: ACCRETION/DILUTION ANALYSIS
B55: TCS EPS (Standalone) | E55: =E11/E49 -> 738.01698
B56: Birlasoft EPS | E56: =E46/E51 -> 746.29075
B57: Accretion / (Dilution) % | E57: =E56/E55-1 -> 0.011210816
